Workbook

Sheet Read Me
A1: TSSRA Open-Source AI Pilot - Read Me
A3: Purpose | B3: Exploratory, open-source pilot covering every outcome family and consequence target archetype supplied by the user.
A4: Status | B4: Illustrative analytic pilot. It is not an approved TSSRA estimate, threat assessment, operational plan, or substitute for DHS/SRAD judgment.
A5: Security boundary | B5: No actual TSSRA scenario data or nonpublic information was used. Internal data should be inserted only in the DHS-approved Chat environment.
A6: Output interpretation | B6: P10/P50/P90 values are conditional consequences assuming the specified event occurs. They are not annual probabilities or expected annual loss.
A7: Outcome module | B7: Monetizes fatalities, injuries, and property damage for all 16 listed 9.0 outcome families.
A8: Consequence module | B8: Estimates first-order and second-order costs for five target archetypes across seven outage durations.
A9: Injury valuation | B9: Uses scenario-specific average MAIS fractions. Replace them with observed severity distributions when available.
A10: Indirect impacts | B10: Uses generic daily loss ranges and cross-sector allocation shares. Replace with asset-specific BEA/RIMS II, FAF, operational, and dependency inputs.
A11: Confidence | B11: High = multiple directly comparable official observations; Moderate = relevant observations with adjustment; Low = sparse data, analogy, or mechanistic modeling.
A12: Key definition | B12: IID is provisionally interpreted as improvised incendiary device. Confirm the intended TSSRA definition before use.
A13: Version | B13: Pilot 1.5 (2026-dollar escalation + cross-sector impacts view) generated 2026-08-03
A15: Recommended workflow: validate definitions -> replace generic target parameters -> validate source incidents -> run sensitivity review -> obtain SRAD acceptance.
A16: Temporal screening (mode-dependent) | B16: Aviation scenarios use incidents on or after September 11, 2001. Pre-2001 aviation events are excluded unless a mechanism-based justification is recorded (the mechanism must be unaffected by ATSA, hardened flight deck doors, federalized screening). All other modes may use pre-2001 incidents, but only to establish a steady-state baseline. Pre-2001 non-aviation evidence must never be pooled or compared in aggregate against aviation estimates.
A17: Evidence beyond terrorist incidents | B17: The evidence base is deliberately broader than terrorism. Accidents with comparable physical mechanisms (e.g., accidental derailment for intentional derailment) inform first- AND second-order consequences. Crime and other serious security incidents inform first-order consequences ONLY. Outage, maintenance, and non-adversarial disruption events inform second-order/indirect consequences ONLY. Non-adversarial evidence never establishes adversary intent, capability, or attack frequency.
A18: Wiring status (v1.3) | B18: The v1.1/v1.2 methods are now live in the calculations, not just documented. Injury value pulls the weapon-class blended fraction via the Weapon Class column on Outcome Scenarios (column AE, dropdown-selectable). Second-order consequence uses EFFECTIVE outage days (engineering + regulatory delay), not engineering days. The Consequence Targets grid is 45 rows (5 targets x 9 durations, now including 45 and 90 days). Prior per-scenario fractions are archived in columns AF-AH for audit. Executive Summary target references use SUMIFS on target+duration so future grid changes cannot silently misalign them.
A19: MAIS injury traceability | B19: Every MAIS level (1-6) maps to a historical TSSRA bucket: MAIS 1-2 = minor injury, MAIS 3-5 = severe injury, MAIS 6 = death. Minor and severe use distinct VSL fractions. MAIS 6 fatalities are valued through the deaths line only, never the blended injury value, so no fatality is double counted. See VSL and Injuries sheet, mapping and validation blocks.
A20: Hijacking scenario splits | B20: Passenger and cargo hijacking are each split into a traditional variant (coercion/diversion; aircraft lands) and an aircraft-as-weapon variant (9/11-style ground-target impact). Lumping these masked the catastrophic tail. AV-05a/AV-06a are traditional; AV-05b/AV-06b are aircraft-as-weapon. The aircraft-as-weapon variants use 9/11 only for the ground-impact consequence mechanism, with the temporal-screen exception recorded per scenario.
A21: Probability and severity (scope note) | B21: Weapon-class severity mixes are conditional injury distributions given an event of that mechanism. They are NOT weighted by probability of occurrence. Consequence and frequency remain separated by design; probability is a later Bayesian phase and is not folded into the blended VSL.
A22: Dollar basis (2026) | B22: Property damage and second-order/economic losses are escalated to 2026 dollars using a documented CPI-U factor (12 months ending June 2026, +3.5%, BLS), held in an editable cell on the VSL and Injuries sheet (K6). The DOT value of a statistical life keeps its official 2025 basis and is clearly labeled; escalating a statutory agency value would misrepresent it. Nominal 2025 property inputs are archived alongside the escalated values.
A23: Cross-sector impacts view | B23: A dedicated Cross-Sector Impacts sheet monetizes the CISA-sector allocation of each target second-order loss (30-day, P50, 2026 dollars), presented separately so it can be read apart from the direct-cost results. These are static screening allocations pending CGE/REMI replacement and are not additive to direct-cost totals.

Sheet VSL and Injuries
A1: DOT Valuation of Statistical Life and Injury Severity
A3: Input | B3: Value | J3: Inflation Adjustment (property and economic inputs only)
A4: VSL (2025 dollars) | B4: 14200000 | J4: Input dollar basis | K4: 2025
A5: Guidance base year | B5: 2025 | J5: Target dollar basis | K5: 2026
A6: Source URL | B6: https://www.transportation.gov/office-policy/transportation-policy/revised-departmental-guidance-on-valuation-of-a-statistical-life-in-economic-analysis | J6: CPI-U 12-month factor | K6: 1.035
J7: Basis note | K7: CPI-U all items, 12 months ending June 2026 = +3.5% (BLS). Interim factor; update to the finalized 2026 annual average when published.
A8: MAIS | B8: Severity | C8: Fraction of VSL | D8: Dollar Value | F8: Note | J8: Source | K8: U.S. BLS, CPI-U, news.release/cpi.nr0.htm (June 2026, USDL-26-1191)
A9: MAIS 1 | B9: Minor | C9: 0.003 | D9: 42600 | F9: The single averaged MAIS fraction is deprecated. Injury cost is now built from an explicit severity MIX that differs by weapon class (see below). Blast mechanisms load the high-severity tail (MAIS 4-6) that a single average understates. | J9: Applies to | K9: Property damage and second-order/economic loss inputs. NOT applied to the DOT VSL, which remains at its official 2025 value.
A10: MAIS 2 | B10: Moderate | C10: 0.047 | D10: 667400
A11: MAIS 3 | B11: Serious | C11: 0.105 | D11: 1491000 | J11: Factor cell reference | K11: 'VSL and Injuries'!$K$6
A12: MAIS 4 | B12: Severe | C12: 0.266 | D12: 3777200
A13: MAIS 5 | B13: Critical | C13: 0.593 | D13: 8420600
A14: MAIS 6 | B14: Fatal/unsurvivable | C14: 1 | D14: 14200000
A18: Weapon-Class Severity Mix (bi-modal; replaces single averaged fraction)
A20: Weapon Class | B20: MAIS1 | C20: MAIS2 | D20: MAIS3 | E20: MAIS4 | F20: MAIS5 | G20: Blended Fraction | H20: Trauma Scoring Basis | J20: Row Share Check
A21: Blunt / vehicular (MAIS-adequate) | B21: 0.55 | C21: 0.28 | D21: 0.12 | E21: 0.04 | F21: 0.01 | G21: =B21*$C$9+C21*$C$10+D21*$C$11+E21*$C$12+F21*$C$13 -> 0.04398 | H21: MAIS/AIS; blunt trauma well-characterized | J21: =SUM(B21:F21) -> 1
A22: Ballistic / edged | B22: 0.3 | C22: 0.3 | D22: 0.22 | E22: 0.13 | F22: 0.05 | G22: =B22*$C$9+C22*$C$10+D22*$C$11+E22*$C$12+F22*$C$13 -> 0.10233 | H22: MAIS/AIS with penetrating-trauma tail | J22: =SUM(B22:F22) -> 1
A23: Blast (primary/secondary/quaternary) | B23: 0.2 | C23: 0.22 | D23: 0.25 | E23: 0.22 | F23: 0.11 | G23: =B23*$C$9+C23*$C$10+D23*$C$11+E23*$C$12+F23*$C$13 -> 0.16094 | H23: NISS + TRISS; multi-region blast injury | J23: =SUM(B23:F23) -> 1
A24: Chemical / biological | B24: 0.25 | C24: 0.25 | D24: 0.25 | E24: 0.17 | F24: 0.08 | G24: =B24*$C$9+C24*$C$10+D24*$C$11+E24*$C$12+F24*$C$13 -> 0.13141 | H24: Toxidrome severity; delayed-effect uncertainty | J24: =SUM(B24:F24) -> 1
A25: Share check (each row must equal 100%)
A26: Use: assign each scenario a weapon class; injury value = injuries x VSL x that class blended fraction. For blast-dominant scenarios do not use a single blended civilian-crash average.
A28: MAIS-to-TSSRA Bucket Mapping (injury traceability)
A29: Every MAIS severity level maps to exactly one historical TSSRA bucket. Fatalities (MAIS 6) are valued through the deaths line, NOT the blended injury value, so no fatality is double counted. Minor and severe injury buckets use distinct VSL fractions.
A31: MAIS Level | B31: Severity | C31: TSSRA Bucket | D31: VSL Fraction | E31: 2025 Dollar Value | F31: Valued Through
A32: MAIS 1 | B32: Minor | C32: Minor injury | D32: 0.003 | E32: =C9*$B$4 -> 42600 | F32: Blended injury value
A33: MAIS 2 | B33: Moderate | C33: Minor injury | D33: 0.047 | E33: =C10*$B$4 -> 667400 | F33: Blended injury value
A34: MAIS 3 | B34: Serious | C34: Severe injury | D34: 0.105 | E34: =C11*$B$4 -> 1491000 | F34: Blended injury value
A35: MAIS 4 | B35: Severe | C35: Severe injury | D35: 0.266 | E35: =C12*$B$4 -> 3777200 | F35: Blended injury value
A36: MAIS 5 | B36: Critical | C36: Severe injury | D36: 0.593 | E36: =C13*$B$4 -> 8420600 | F36: Blended injury value
A37: MAIS 6 | B37: Fatal/unsurvivable | C37: Death (fatality) | D37: 1 | E37: =C14*$B$4 -> 14200000 | F37: Deaths line (VSL x fatalities) - separate from injury value
A39: TSSRA Bucket Definitions
A40: Bucket | B40: MAIS Range | C40: Definition
A41: Minor injury | B41: MAIS 1-2 | C41: Treated and released or short recovery; no lasting impairment
A42: Severe injury | B42: MAIS 3-5 | C42: Hospitalization, potential permanent impairment, high acute-care cost
A43: Death (fatality) | B43: MAIS 6 | C43: Valued at full VSL through the deaths estimate, never through the injury blend
A46: Weapon-Class Injury Value, Split by Severe vs Minor Bucket (per injured person)
A47: Shows how each weapon class blended fraction decomposes into minor (MAIS 1-2) and severe (MAIS 3-5) buckets. Minor share x its VSL fractions + severe share x its VSL fractions = the blended fraction in the mix table above. Makes the severe/minor split explicit and auditable.
A49: Weapon Class | B49: Minor Share (MAIS1-2) | C49: Severe Share (MAIS3-5) | D49: Minor $ per injured | E49: Severe $ per injured | F49: Blended $ per injured | G49: Check vs mix table
A50: Blunt / vehicular (MAIS-adequate) | B50: =B21+C21 -> 0.83 | C50: =D21+E21+F21 -> 0.17 | D50: =(B21*$C$9+C21*$C$10)*$B$4 -> 210302 | E50: =(D21*$C$11+E21*$C$12+F21*$C$13)*$B$4 -> 414214 | F50: =D50+E50 -> 624516 | G50: =ROUND(F50/$B$4-G21,6) -> 0
A51: Ballistic / edged | B51: =B22+C22 -> 0.6 | C51: =D22+E22+F22 -> 0.4 | D51: =(B22*$C$9+C22*$C$10)*$B$4 -> 213000 | E51: =(D22*$C$11+E22*$C$12+F22*$C$13)*$B$4 -> 1240086 | F51: =D51+E51 -> 1453086 | G51: =ROUND(F51/$B$4-G22,6) -> 0
A52: Blast (primary/secondary/quaternary) | B52: =B23+C23 -> 0.42 | C52: =D23+E23+F23 -> 0.58 | D52: =(B23*$C$9+C23*$C$10)*$B$4 -> 155348 | E52: =(D23*$C$11+E23*$C$12+F23*$C$13)*$B$4 -> 2130000 | F52: =D52+E52 -> 2285348 | G52: =ROUND(F52/$B$4-G23,6) -> 0
A53: Chemical / biological | B53: =B24+C24 -> 0.5 | C53: =D24+E24+F24 -> 0.5 | D53: =(B24*$C$9+C24*$C$10)*$B$4 -> 177500 | E53: =(D24*$C$11+E24*$C$12+F24*$C$13)*$B$4 -> 1688522 | F53: =D53+E53 -> 1866022 | G53: =ROUND(F53/$B$4-G24,6) -> 0
A54: Check column must be 0.000000 for every class.
A56: Severity-Class Application Validation
A57: Confirms every MAIS class referenced in the methodology is actually applied, so none is silently dropped.
A59: MAIS Class | B59: Referenced? | C59: Applied In | D59: Status
A60: MAIS 1 | B60: Yes | C60: Minor bucket, all weapon-class mixes | D60: Applied
A61: MAIS 2 | B61: Yes | C61: Minor bucket, all weapon-class mixes | D61: Applied
A62: MAIS 3 | B62: Yes | C62: Severe bucket, all weapon-class mixes | D62: Applied
A63: MAIS 4 | B63: Yes | C63: Severe bucket, all weapon-class mixes | D63: Applied
A64: MAIS 5 | B64: Yes | C64: Severe bucket, all weapon-class mixes | D64: Applied
A65: MAIS 6 | B65: Yes | C65: Deaths line (fatalities x VSL), separate from injury blend | D65: Applied - fatality only
A67: MAIS 6 confirmation: fatalities are valued separately from the blended injury value. A fatality is counted once, through the deaths estimate. Flag any future severity class not shown as Applied.

Sheet Evidence Screening
A1: Evidence Screening Rules (temporal + evidence class)
A2: Governs which incidents may enter the evidence base and what each may be used for. Applies to every scenario and every consequence target.
A4: 1. Temporal screening by mode
A5: Mode | B5: Period Screen | C5: Permitted Use | D5: Exception Rule | E5: Aggregation Rule
A6: Aviation (AV-01 to AV-11) | B6: On or after September 11, 2001 | C6: Full use for outcome and consequence estimation | D6: Pre-2001 aviation incident admissible ONLY with recorded mechanism-based justification: the mechanism must be unaffected by ATSA, hardened/locked flight deck doors, federalized screening, or expanded in-flight security | E6: Compare only against evidence screened to the same period
A7: Surface, pipeline, all other modes | B7: Pre-2001 admissible | C7: Steady-state baseline ONLY (long-run rates, severity distributions, physical-mechanism behavior) | D7: No exception needed; regime did not undergo an equivalent discontinuity | E7: MUST NOT be pooled or compared in aggregate against aviation estimates
A9: 2. Non-adversarial evidence classes and permitted scope
A10: Evidence Class | B10: Example | C10: Permitted Scope | D10: Prohibited Use
A11: Terrorist / intentional attack | B11: Vehicle ramming, aircraft hijacking | C11: First-order AND second-order consequences; adversary behavior | D11: None (primary evidence)
A12: Accident with comparable physical mechanism | B12: Accidental derailment as analog for intentional derailment; rupture, fire, collision, toxic release | C12: First-order AND second-order consequences; physical outcome, damage, restoration behavior | D12: Does not establish adversary intent, capability, target selection, or attack frequency
A13: Crime / other security-related serious incident | B13: Non-terrorist shooting or assault at a comparable target type | C13: First-order consequences ONLY (casualty counts, injury-severity mixes) | D13: Not used for indirect or cross-sector economic effects; not used for frequency
A14: Outage / maintenance / non-adversarial disruption | B14: Planned or unplanned service interruption, curtailment | C14: Second-order / indirect consequences ONLY (daily service-loss value, substitution, buffering, restoration curves) | D14: Not used to estimate casualties; not used for adversary behavior or frequency
A15: Mechanistic model | B15: Dispersion or crowd-exposure modeling where observations are absent | C15: Used where no observation exists; requires broad uncertainty and low confidence | D15: Does not raise confidence
A17: Per-run requirement | B17: Curate the referenced incident list each run: remove aviation incidents predating 2001-09-11 without recorded justification, confirm every reference is scenario-appropriate, verify no pre-2001 non-aviation evidence has been pooled into a cross-modal aggregate, and confirm each non-adversarial analog stays within its permitted scope.

Sheet Outcome Scenarios
A1: Conditional Outcome Estimates - All 9.0 Families
A3: ID | B3: Mode | C3: Scenario | D3: Evidence Class | E3: Confidence | F3: Primary Evidence / Analogs | G3: Low Fatalities | H3: Low Injuries | I3: Low Injury VSL Fraction | J3: Low Property Damage (2026$) | K3: Low Casualty Value | L3: Low Total Direct | M3: Best Fatalities | N3: Best Injuries | O3: Best Injury VSL Fraction | P3: Best Property Damage (2026$) | Q3: Best Casualty Value | R3: Best Total Direct | S3: High Fatalities | T3: High Injuries | U3: High Injury VSL Fraction | V3: High Property Damage (2026$) | W3: High Casualty Value | X3: High Total Direct | Y3: Source IDs | Z3: Key Assumptions | AA3: Limitations | AB3: Temporal Screen Applied | AC3: Pre-2001 Exception Justification (aviation only) | AD3: Non-Adversarial Evidence Used (class + permitted scope) | AE3: Weapon Class (drives injury severity mix) | AF3: Archived v1.2 Low Fraction | AG3: Archived v1.2 Best Fraction | AH3: Archived v1.2 High Fraction | AI3: Property Damage (nominal 2025) - Low | AJ3: Property Damage (nominal 2025) - Best | AK3: Property Damage (nominal 2025) - High
A4: AV-01 | B4: Aviation | C4: All UAS against aviation | D4: Mechanistic + observed disruption analogs | E4: Low | F4: FAA/GAO airport UAS sightings; TSA/CISA UAS threat guidance | G4: 0 | H4: 2 | I4: =IFERROR(INDEX('VSL and Injuries'!$G$21:$G$24,MATCH($AE4,'VSL and Injuries'!$A$21:$A$24,0)),"") -> 0.16094 | J4: =AI4*'VSL and Injuries'!$K$6 -> 517500 | K4: =G4*'VSL and Injuries'!$B$4+H4*'VSL and Injuries'!$B$4*I4 -> 4570696 | L4: =J4+K4 -> 5088196 | M4: 1 | N4: 15 | O4: =IFERROR(INDEX('VSL and Injuries'!$G$21:$G$24,MATCH($AE4,'VSL and Injuries'!$A$21:$A$24,0)),"") -> 0.16094 | P4: =AJ4*'VSL and Injuries'!$K$6 -> 10350000 | Q4: =M4*'VSL and Injuries'!$B$4+N4*'VSL and Injuries'!$B$4*O4 -> 48480220 | R4: =P4+Q4 -> 58830220 | S4: 20 | T4: 100 | U4: =IFERROR(INDEX('VSL and Injuries'!$G$21:$G$24,MATCH($AE4,'VSL and Injuries'!$A$21:$A$24,0)),"") -> 0.16094 | V4: =AK4*'VSL and Injuries'!$K$6 -> 155250000 | W4: =S4*'VSL and Injuries'!$B$4+T4*'VSL and Injuries'!$B$4*U4 -> 512534800 | X4: =V4+W4 -> 667784800 | Y4: S011; S012; S013 | Z4: Small-to-medium UAS event; ranges span disruption/collision through payload-enabled mass-casualty case; no active-war-zone incidents used. | AA4: No directly comparable successful domestic aviation UAS terrorist attack; high estimate is model-derived. | AB4: On or after 2001-09-11 (ATSA regime change) | AC4: None taken | AD4: To be recorded per run: accident (1st+2nd order) / crime (1st order only) / outage (2nd order only) | AE4: Blast (primary/secondary/quaternary) | AF4: 0.02 | AG4: 0.04 | AH4: 0.08 | AI4: 500000 | AJ4: 10000000 | AK4: 150000000
A5: AV-02 | B5: Aviation | C5: Aircraft assault on ground | D5: Observed attack analog + active-shooter analogs | E5: Moderate-Low | F5: Pan Am Flight 73 ground boarding attack; airport/transport active-shooter cases | G5: 0 | H5: 3 | I5: =IFERROR(INDEX('VSL and Injuries'!$G$21:$G$24,MATCH($AE5,'VSL and Injuries'!$A$21:$A$24,0)),"") -> 0.10233 | J5: =AI5*'VSL and Injuries'!$K$6 -> 1035000 | K5: =G5*'VSL and Injuries'!$B$4+H5*'VSL and Injuries'!$B$4*I5 -> 4359258 | L5: =J5+K5 -> 5394258 | M5: 8 | N5: 25 | O5: =IFERROR(INDEX('VSL and Injuries'!$G$21:$G$24,MATCH($AE5,'VSL and Injuries'!$A$21:$A$24,0)),"") -> 0.10233 | P5: =AJ5*'VSL and Injuries'!$K$6 -> 20700000 | Q5: =M5*'VSL and Injuries'!$B$4+N5*'VSL and Injuries'!$B$4*O5 -> 149927150 | R5: =P5+Q5 -> 170627150 | S5: 40 | T5: 100 | U5: =IFERROR(INDEX('VSL and Injuries'!$G$21:$G$24,MATCH($AE5,'VSL and Injuries'!$A$21:$A$24,0)),"") -> 0.10233 | V5: =AK5*'VSL and Injuries'!$K$6 -> 103500000 | W5: =S5*'VSL and Injuries'!$B$4+T5*'VSL and Injuries'!$B$4*U5 -> 713308600 | X5: =V5+W5 -> 816808600 | Y5: S006; S007; S023 | Z5: Occupied passenger aircraft at gate or stand; attacker access and response time drive dispersion. | AA5: Primary analog occurred outside the United States; aircraft and security configurations vary. | AB5: On or after 2001-09-11 (ATSA regime change) | AC5: None taken | AD5: To be recorded per run: accident (1st+2nd order) / crime (1st order only) / outage (2nd order only) | AE5: Ballistic / edged | AF5: 0.025 | AG5: 0.05 | AH5: 0.1 | AI5: 1000000 | AJ5: 20000000 | AK5: 100000000
A6: AV-03 | B6: Aviation | C6: Aircraft passenger assault with bladed weapons | D6: Observed attack/attempt analogs | E6: Moderate | F6: 9/11 Commission documentation; federal aircraft-interference and hijacking cases | G6: 0 | H6: 2 | I6: =IFERROR(INDEX('VSL and Injuries'!$G$21:$G$24,MATCH($AE6,'VSL and Injuries'!$A$21:$A$24,0)),"") -> 0.10233 | J6: =AI6*'VSL and Injuries'!$K$6 -> 103500 | K6: =G6*'VSL and Injuries'!$B$4+H6*'VSL and Injuries'!$B$4*I6 -> 2906172 | L6: =J6+K6 -> 3009672 | M6: 2 | N6: 8 | O6: =IFERROR(INDEX('VSL and Injuries'!$G$21:$G$24,MATCH($AE6,'VSL and Injuries'!$A$21:$A$24,0)),"") -> 0.10233 | P6: =AJ6*'VSL and Injuries'!$K$6 -> 517500 | Q6: =M6*'VSL and Injuries'!$B$4+N6*'VSL and Injuries'!$B$4*O6 -> 40024688 | R6: =P6+Q6 -> 40542188 | S6: 15 | T6: 35 | U6: =IFERROR(INDEX('VSL and Injuries'!$G$21:$G$24,MATCH($AE6,'VSL and Injuries'!$A$21:$A$24,0)),"") -> 0.10233 | V6: =AK6*'VSL and Injuries'!$K$6 -> 5175000 | W6: =S6*'VSL and Injuries'!$B$4+T6*'VSL and Injuries'!$B$4*U6 -> 263858010 | X6: =V6+W6 -> 269033010 | Y6: S005; S022 | Z6: Close-quarters assault without successful use of aircraft as a weapon; intervention and cockpit security remain active mitigations. | AA6: Small sample and major post-2001 security regime change. | AB6: On or after 2001-09-11 (ATSA regime change) | AC6: None taken | AD6: To be recorded per run: accident (1st+2nd order) / crime (1st order only) / outage (2nd order only) | AE6: Ballistic / edged | AF6: 0.02 | AG6: 0.035 | AH6: 0.08 | AI6: 100000 | AJ6: 500000 | AK6: 5000000
A7: AV-04 | B7: Aviation | C7: Airport passenger assembly assault | D7: Observed domestic airport + public assembly analogs | E7: Moderate | F7: Fort Lauderdale airport shooting; FBI active-shooter series | G7: 2 | H7: 8 | I7: =IFERROR(INDEX('VSL and Injuries'!$G$21:$G$24,MATCH($AE7,'VSL and Injuries'!$A$21:$A$24,0)),"") -> 0.10233 | J7: =AI7*'VSL and Injuries'!$K$6 -> 517500 | K7: =G7*'VSL and Injuries'!$B$4+H7*'VSL and Injuries'!$B$4*I7 -> 40024688 | L7: =J7+K7 -> 40542188 | M7: 10 | N7: 45 | O7: =IFERROR(INDEX('VSL and Injuries'!$G$21:$G$24,MATCH($AE7,'VSL and Injuries'!$A$21:$A$24,0)),"") -> 0.10233 | P7: =AJ7*'VSL and Injuries'!$K$6 -> 5175000 | Q7: =M7*'VSL and Injuries'!$B$4+N7*'VSL and Injuries'!$B$4*O7 -> 207388870 | R7: =P7+Q7 -> 212563870 | S7: 50 | T7: 200 | U7: =IFERROR(INDEX('VSL and Injuries'!$G$21:$G$24,MATCH($AE7,'VSL and Injuries'!$A$21:$A$24,0)),"") -> 0.10233 | V7: =AK7*'VSL and Injuries'!$K$6 -> 51750000 | W7: =S7*'VSL and Injuries'!$B$4+T7*'VSL and Injuries'!$B$4*U7 -> 1000617200 | X7: =V7+W7 -> 1052367200 | Y7: S007; S023 | Z7: Public-side or baggage-claim passenger assembly; no explosive effects included. | AA7: Casualties depend heavily on crowd density, weapon, duration, and police response. | AB7: On or after 2001-09-11 (ATSA regime change) | AC7: None taken | AD7: To be recorded per run: accident (1st+2nd order) / crime (1st order only) / outage (2nd order only) | AE7: Ballistic / edged | AF7: 0.025 | AG7: 0.05 | AH7: 0.1 | AI7: 500000 | AJ7: 5000000 | AK7: 50000000
A8: AV-05a | B8: Aviation | C8: Commercial passenger aircraft hijacking - traditional (coercion or diversion; aircraft lands) | D8: Attempt or advanced plot | E8: Moderate-Low | F8: Post-2001 aviation hijacking attempts and thwarted takeovers; onboard assault cases | G8: 0 | H8: 3 | I8: =IFERROR(INDEX('VSL and Injuries'!$G$21:$G$24,MATCH($AE8,'VSL and Injuries'!$A$21:$A$24,0)),"") -> 0.10233 | J8: =AI8*'VSL and Injuries'!$K$6 -> 2070000 | K8: =G8*'VSL and Injuries'!$B$4+H8*'VSL and Injuries'!$B$4*I8 -> 4359258 | L8: =K8+J8 -> 6429258 | M8: 2 | N8: 15 | O8: =IFERROR(INDEX('VSL and Injuries'!$G$21:$G$24,MATCH($AE8,'VSL and Injuries'!$A$21:$A$24,0)),"") -> 0.10233 | P8: =AJ8*'VSL and Injuries'!$K$6 -> 20700000 | Q8: =M8*'VSL and Injuries'!$B$4+N8*'VSL and Injuries'!$B$4*O8 -> 50196290 | R8: =Q8+P8 -> 70896290 | S8: 12 | T8: 60 | U8: =IFERROR(INDEX('VSL and Injuries'!$G$21:$G$24,MATCH($AE8,'VSL and Injuries'!$A$21:$A$24,0)),"") -> 0.10233 | V8: =AK8*'VSL and Injuries'!$K$6 -> 155250000 | W8: =S8*'VSL and Injuries'!$B$4+T8*'VSL and Injuries'!$B$4*U8 -> 257585160 | X8: =W8+V8 -> 412835160 | Y8: S007; S019; S032; S033 | Z8: Objective is coercion, diversion, or hostage leverage. Hardened cockpit doors and passenger response make cockpit breach and aircraft-as-weapon use unlikely. Casualties bounded by onboard population and standoff violence; property primarily airframe and ground handling. | AA8: Post-2001 successful U.S. passenger takeovers are near-absent; estimates rely on attempts, foreign analogs screened to post-2001, and onboard-assault mechanisms. | AB8: On or after 2001-09-11 (ATSA regime change) | AC8: None taken | AD8: Onboard-assault accident analogs used for casualty severity only (1st order); not for adversary capability. | AE8: Ballistic / edged | AF8: 0.025 | AG8: 0.06 | AH8: 0.12 | AI8: 2000000 | AJ8: 20000000 | AK8: 150000000
A9: AV-06a | B9: Aviation | C9: Cargo aircraft hijacking - traditional (diversion or theft; aircraft lands) | D9: Attempt or advanced plot | E9: Low | F9: Cargo aircraft security incidents; ground-based cargo theft and diversion analogs | G9: 0 | H9: 1 | I9: =IFERROR(INDEX('VSL and Injuries'!$G$21:$G$24,MATCH($AE9,'VSL and Injuries'!$A$21:$A$24,0)),"") -> 0.10233 | J9: =AI9*'VSL and Injuries'!$K$6 -> 5175000 | K9: =G9*'VSL and Injuries'!$B$4+H9*'VSL and Injuries'!$B$4*I9 -> 1453086 | L9: =K9+J9 -> 6628086 | M9: 1 | N9: 4 | O9: =IFERROR(INDEX('VSL and Injuries'!$G$21:$G$24,MATCH($AE9,'VSL and Injuries'!$A$21:$A$24,0)),"") -> 0.10233 | P9: =AJ9*'VSL and Injuries'!$K$6 -> 25875000 | Q9: =M9*'VSL and Injuries'!$B$4+N9*'VSL and Injuries'!$B$4*O9 -> 20012344 | R9: =Q9+P9 -> 45887344 | S9: 6 | T9: 15 | U9: =IFERROR(INDEX('VSL and Injuries'!$G$21:$G$24,MATCH($AE9,'VSL and Injuries'!$A$21:$A$24,0)),"") -> 0.10233 | V9: =AK9*'VSL and Injuries'!$K$6 -> 124200000 | W9: =S9*'VSL and Injuries'!$B$4+T9*'VSL and Injuries'!$B$4*U9 -> 106996290 | X9: =W9+V9 -> 231196290 | Y9: S017; S018; S029 | Z9: Objective is theft, diversion, or ground use; minimal onboard population (crew only). Consequence dominated by airframe value and cargo loss, not mass casualty. | AA9: Very sparse direct evidence; small cargo crews cap casualty ceilings; relies on cargo-security and diversion analogs. | AB9: On or after 2001-09-11 (ATSA regime change) | AC9: None taken | AD9: Cargo-theft and diversion accident analogs used for property/business estimates only (1st and 2nd order). | AE9: Ballistic / edged | AF9: 0.02 | AG9: 0.05 | AH9: 0.1 | AI9: 5000000 | AJ9: 25000000 | AK9: 120000000
A10: AV-07 | B10: Aviation | C10: Public charter hijacking | D10: Commercial hijacking analog with smaller occupancy | E10: Low | F10: Commercial hijacking record adjusted for charter occupancy and security variability | G10: 0 | H10: 2 | I10: =IFERROR(INDEX('VSL and Injuries'!$G$21:$G$24,MATCH($AE10,'VSL and Injuries'!$A$21:$A$24,0)),"") -> 0.10233 | J10: =AI10*'VSL and Injuries'!$K$6 -> 2070000 | K10: =G10*'VSL and Injuries'!$B$4+H10*'VSL and Injuries'!$B$4*I10 -> 2906172 | L10: =J10+K10 -> 4976172 | M10: 10 | N10: 25 | O10: =IFERROR(INDEX('VSL and Injuries'!$G$21:$G$24,MATCH($AE10,'VSL and Injuries'!$A$21:$A$24,0)),"") -> 0.10233 | P10: =AJ10*'VSL and Injuries'!$K$6 -> 31050000 | Q10: =M10*'VSL and Injuries'!$B$4+N10*'VSL and Injuries'!$B$4*O10 -> 178327150 | R10: =P10+Q10 -> 209377150 | S10: 100 | T10: 125 | U10: =IFERROR(INDEX('VSL and Injuries'!$G$21:$G$24,MATCH($AE10,'VSL and Injuries'!$A$21:$A$24,0)),"") -> 0.10233 | V10: =AK10*'VSL and Injuries'!$K$6 -> 207000000 | W10: =S10*'VSL and Injuries'!$B$4+T10*'VSL and Injuries'!$B$4*U10 -> 1601635750 | X10: =V10+W10 -> 1808635750 | Y10: S005; S006; S019 | Z10: Passenger charter aircraft; occupancy and screening controls may differ from scheduled service. | AA10: Public charter is heterogeneous; estimate must be tailored to aircraft and passenger count. | AB10: On or after 2001-09-11 (ATSA regime change) | AC10: None taken | AD10: To be recorded per run: accident (1st+2nd order) / crime (1st order only) / outage (2nd order only) | AE10: Ballistic / edged | AF10: 0.02 | AG10: 0.05 | AH10: 0.1 | AI10: 2000000 | AJ10: 30000000 | AK10: 200000000
A11: AV-08 | B11: Aviation | C11: All IID on commercial passenger aircraft | D11: Fire/sabotage analogs + evacuation studies | E11: Moderate-Low | F11: NTSB explosive/fire investigations and evacuation safety study | G11: 0 | H11: 5 | I11: =IFERROR(INDEX('VSL and Injuries'!$G$21:$G$24,MATCH($AE11,'VSL and Injuries'!$A$21:$A$24,0)),"") -> 0.16094 | J11: =AI11*'VSL and Injuries'!$K$6 -> 1035000 | K11: =G11*'VSL and Injuries'!$B$4+H11*'VSL and Injuries'!$B$4*I11 -> 11426740 | L11: =J11+K11 -> 12461740 | M11: 8 | N11: 40 | O11: =IFERROR(INDEX('VSL and Injuries'!$G$21:$G$24,MATCH($AE11,'VSL and Injuries'!$A$21:$A$24,0)),"") -> 0.16094 | P11: =AJ11*'VSL and Injuries'!$K$6 -> 25875000 | Q11: =M11*'VSL and Injuries'!$B$4+N11*'VSL and Injuries'!$B$4*O11 -> 205013920 | R11: =P11+Q11 -> 230888920 | S11: 120 | T11: 180 | U11: =IFERROR(INDEX('VSL and Injuries'!$G$21:$G$24,MATCH($AE11,'VSL and Injuries'!$A$21:$A$24,0)),"") -> 0.16094 | V11: =AK11*'VSL and Injuries'!$K$6 -> 155250000 | W11: =S11*'VSL and Injuries'!$B$4+T11*'VSL and Injuries'!$B$4*U11 -> 2115362640 | X11: =V11+W11 -> 2270612640 | Y11: S004; S025 | Z11: IID interpreted as improvised incendiary device; outcomes span contained cabin fire to loss of aircraft. | AA11: Confirm IID definition before operational use; fire behavior varies by location and phase of flight. | AB11: On or after 2001-09-11 (ATSA regime change) | AC11: None taken | AD11: To be recorded per run: accident (1st+2nd order) / crime (1st order only) / outage (2nd order only) | AE11: Blast (primary/secondary/quaternary) | AF11: 0.03 | AG11: 0.08 | AH11: 0.15 | AI11: 1000000 | AJ11: 25000000 | AK11: 150000000
A12: AV-09 | B12: Aviation | C12: All IID on cargo aircraft | D12: Cargo-fire/sabotage analogs + mechanistic model | E12: Low | F12: NTSB fire/explosion reports and cargo-aircraft economic values | G12: 0 | H12: 1 | I12: =IFERROR(INDEX('VSL and Injuries'!$G$21:$G$24,MATCH($AE12,'VSL and Injuries'!$A$21:$A$24,0)),"") -> 0.16094 | J12: =AI12*'VSL and Injuries'!$K$6 -> 5175000 | K12: =G12*'VSL and Injuries'!$B$4+H12*'VSL and Injuries'!$B$4*I12 -> 2285348 | L12: =J12+K12 -> 7460348 | M12: 2 | N12: 8 | O12: =IFERROR(INDEX('VSL and Injuries'!$G$21:$G$24,MATCH($AE12,'VSL and Injuries'!$A$21:$A$24,0)),"") -> 0.16094 | P12: =AJ12*'VSL and Injuries'!$K$6 -> 36225000 | Q12: =M12*'VSL and Injuries'!$B$4+N12*'VSL and Injuries'!$B$4*O12 -> 46682784 | R12: =P12+Q12 -> 82907784 | S12: 25 | T12: 50 | U12: =IFERROR(INDEX('VSL and Injuries'!$G$21:$G$24,MATCH($AE12,'VSL and Injuries'!$A$21:$A$24,0)),"") -> 0.16094 | V12: =AK12*'VSL and Injuries'!$K$6 -> 207000000 | W12: =S12*'VSL and Injuries'!$B$4+T12*'VSL and Injuries'!$B$4*U12 -> 469267400 | X12: =V12+W12 -> 676267400 | Y12: S004; S019; S025 | Z12: IID interpreted as improvised incendiary device; limited crew but potentially high aircraft/cargo loss. | AA12: Cargo type and fire-suppression capability materially alter outcomes. | AB12: On or after 2001-09-11 (ATSA regime change) | AC12: None taken | AD12: To be recorded per run: accident (1st+2nd order) / crime (1st order only) / outage (2nd order only) | AE12: Blast (primary/secondary/quaternary) | AF12: 0.025 | AG12: 0.07 | AH12: 0.14 | AI12: 5000000 | AJ12: 35000000 | AK12: 200000000
A13: AV-10 | B13: Aviation | C13: All Chem/Bio on commercial passenger aircraft | D13: Mechanistic toxicology model + mass-exposure guidance | E13: Low | F13: CDC chemical-agent health guidance; EPA dispersion tools; federal decontamination guidance | G13: 0 | H13: 10 | I13: =IFERROR(INDEX('VSL and Injuries'!$G$21:$G$24,MATCH($AE13,'VSL and Injuries'!$A$21:$A$24,0)),"") -> 0.13141 | J13: =AI13*'VSL and Injuries'!$K$6 -> 1035000 | K13: =G13*'VSL and Injuries'!$B$4+H13*'VSL and Injuries'!$B$4*I13 -> 18660220 | L13: =J13+K13 -> 19695220 | M13: 5 | N13: 100 | O13: =IFERROR(INDEX('VSL and Injuries'!$G$21:$G$24,MATCH($AE13,'VSL and Injuries'!$A$21:$A$24,0)),"") -> 0.13141 | P13: =AJ13*'VSL and Injuries'!$K$6 -> 10350000 | Q13: =M13*'VSL and Injuries'!$B$4+N13*'VSL and Injuries'!$B$4*O13 -> 257602200 | R13: =P13+Q13 -> 267952200 | S13: 75 | T13: 300 | U13: =IFERROR(INDEX('VSL and Injuries'!$G$21:$G$24,MATCH($AE13,'VSL and Injuries'!$A$21:$A$24,0)),"") -> 0.13141 | V13: =AK13*'VSL and Injuries'!$K$6 -> 77625000 | W13: =S13*'VSL and Injuries'!$B$4+T13*'VSL and Injuries'!$B$4*U13 -> 1624806600 | X13: =V13+W13 -> 1702431600 | Y13: S015; S016; S026 | Z13: Generic toxic chemical or biological exposure; excludes agent-specific classified parameters. | AA13: Agent, dose, ventilation, detection, medical response, and incubation dominate results. | AB13: On or after 2001-09-11 (ATSA regime change) | AC13: None taken | AD13: To be recorded per run: accident (1st+2nd order) / crime (1st order only) / outage (2nd order only) | AE13: Chemical / biological | AF13: 0.03 | AG13: 0.08 | AH13: 0.18 | AI13: 1000000 | AJ13: 10000000 | AK13: 75000000
A14: AV-11 | B14: Aviation | C14: All Chem/Bio at airport | D14: Mechanistic dispersion + public-space mass-exposure analogs | E14: Low | F14: CDC toxicology; EPA ALOHA/CAMEO; public mass-decontamination guidance | G14: 0 | H14: 25 | I14: =IFERROR(INDEX('VSL and Injuries'!$G$21:$G$24,MATCH($AE14,'VSL and Injuries'!$A$21:$A$24,0)),"") -> 0.13141 | J14: =AI14*'VSL and Injuries'!$K$6 -> 2070000 | K14: =G14*'VSL and Injuries'!$B$4+H14*'VSL and Injuries'!$B$4*I14 -> 46650550 | L14: =J14+K14 -> 48720550 | M14: 15 | N14: 300 | O14: =IFERROR(INDEX('VSL and Injuries'!$G$21:$G$24,MATCH($AE14,'VSL and Injuries'!$A$21:$A$24,0)),"") -> 0.13141 | P14: =AJ14*'VSL and Injuries'!$K$6 -> 31050000 | Q14: =M14*'VSL and Injuries'!$B$4+N14*'VSL and Injuries'!$B$4*O14 -> 772806600 | R14: =P14+Q14 -> 803856600 | S14: 150 | T14: 1500 | U14: =IFERROR(INDEX('VSL and Injuries'!$G$21:$G$24,MATCH($AE14,'VSL and Injuries'!$A$21:$A$24,0)),"") -> 0.13141 | V14: =AK14*'VSL and Injuries'!$K$6 -> 258750000 | W14: =S14*'VSL and Injuries'!$B$4+T14*'VSL and Injuries'!$B$4*U14 -> 4929033000 | X14: =V14+W14 -> 5187783000 | Y14: S015; S016; S026 | Z14: Public terminal release with variable ventilation and rapid emergency response. | AA14: Not agent-specific; high case is an intentionally broad planning bound. | AB14: On or after 2001-09-11 (ATSA regime change) | AC14: None taken | AD14: To be recorded per run: accident (1st+2nd order) / crime (1st order only) / outage (2nd order only) | AE14: Chemical / biological | AF14: 0.025 | AG14: 0.07 | AH14: 0.16 | AI14: 2000000 | AJ14: 30000000 | AK14: 250000000
A15: SU-01 | B15: Surface | C15: Assault on surface passenger vessels/stations | D15: Observed transit shooting + active-shooter/European attack analogs | E15: Moderate | F15: Brooklyn subway mass shooting; FBI active-shooter record; Europol TE-SAT | G15: 1 | H15: 5 | I15: =IFERROR(INDEX('VSL and Injuries'!$G$21:$G$24,MATCH($AE15,'VSL and Injuries'!$A$21:$A$24,0)),"") -> 0.10233 | J15: =AI15*'VSL and Injuries'!$K$6 -> 517500 | K15: =G15*'VSL and Injuries'!$B$4+H15*'VSL and Injuries'!$B$4*I15 -> 21465430 | L15: =J15+K15 -> 21982930 | M15: 10 | N15: 50 | O15: =IFERROR(INDEX('VSL and Injuries'!$G$21:$G$24,MATCH($AE15,'VSL and Injuries'!$A$21:$A$24,0)),"") -> 0.10233 | P15: =AJ15*'VSL and Injuries'!$K$6 -> 5175000 | Q15: =M15*'VSL and Injuries'!$B$4+N15*'VSL and Injuries'!$B$4*O15 -> 214654300 | R15: =P15+Q15 -> 219829300 | S15: 60 | T15: 250 | U15: =IFERROR(INDEX('VSL and Injuries'!$G$21:$G$24,MATCH($AE15,'VSL and Injuries'!$A$21:$A$24,0)),"") -> 0.10233 | V15: =AK15*'VSL and Injuries'!$K$6 -> 51750000 | W15: =S15*'VSL and Injuries'!$B$4+T15*'VSL and Injuries'!$B$4*U15 -> 1215271500 | X15: =V15+W15 -> 1267021500 | Y15: S008; S021; S023 | Z15: Firearm/grenade or bladed assault at vessel, station, or vehicle; ranges combine distinct subtypes. | AA15: Scenario should eventually be separated by vessel, station, and onboard configuration. | AB15: Pre-2001 admissible; steady-state use only; not aggregated with aviation | AC15: n/a (non-aviation) | AD15: To be recorded per run: accident (1st+2nd order) / crime (1st order only) / outage (2nd order only) | AE15: Ballistic / edged | AF15: 0.025 | AG15: 0.05 | AH15: 0.11 | AI15: 500000 | AJ15: 5000000 | AK15: 50000000
A16: SU-02 | B16: Surface | C16: Assault on Pipeline ICS center | D16: Facility assault analog + pipeline control-system consequence evidence | E16: Low | F16: FBI active-shooter distributions; NTSB SCADA/control-system investigations; CISA critical infrastructure guidance | G16: 0 | H16: 2 | I16: =IFERROR(INDEX('VSL and Injuries'!$G$21:$G$24,MATCH($AE16,'VSL and Injuries'!$A$21:$A$24,0)),"") -> 0.10233 | J16: =AI16*'VSL and Injuries'!$K$6 -> 517500 | K16: =G16*'VSL and Injuries'!$B$4+H16*'VSL and Injuries'!$B$4*I16 -> 2906172 | L16: =J16+K16 -> 3423672 | M16: 2 | N16: 10 | O16: =IFERROR(INDEX('VSL and Injuries'!$G$21:$G$24,MATCH($AE16,'VSL and Injuries'!$A$21:$A$24,0)),"") -> 0.10233 | P16: =AJ16*'VSL and Injuries'!$K$6 -> 5175000 | Q16: =M16*'VSL and Injuries'!$B$4+N16*'VSL and Injuries'!$B$4*O16 -> 42930860 | R16: =P16+Q16 -> 48105860 | S16: 10 | T16: 40 | U16: =IFERROR(INDEX('VSL and Injuries'!$G$21:$G$24,MATCH($AE16,'VSL and Injuries'!$A$21:$A$24,0)),"") -> 0.10233 | V16: =AK16*'VSL and Injuries'!$K$6 -> 51750000 | W16: =S16*'VSL and Injuries'!$B$4+T16*'VSL and Injuries'!$B$4*U16 -> 200123440 | X16: =V16+W16 -> 251873440 | Y16: S003; S023; S030 | Z16: Direct casualties/property damage at control center only; pipeline service loss is modeled in the consequence module. | AA16: Public data on pipeline-control-center attacks are extremely limited. | AB16: Pre-2001 admissible; steady-state use only; not aggregated with aviation | AC16: n/a (non-aviation) | AD16: To be recorded per run: accident (1st+2nd order) / crime (1st order only) / outage (2nd order only) | AE16: Ballistic / edged | AF16: 0.02 | AG16: 0.04 | AH16: 0.08 | AI16: 500000 | AJ16: 5000000 | AK16: 50000000
A17: SU-03 | B17: Surface | C17: Vehicle ramming | D17: Observed domestic terrorist and extremist attacks | E17: Moderate-High | F17: New York 2017 truck attack; New Orleans 2025 attack; Charlottesville 2017 | G17: 1 | H17: 5 | I17: =IFERROR(INDEX('VSL and Injuries'!$G$21:$G$24,MATCH($AE17,'VSL and Injuries'!$A$21:$A$24,0)),"") -> 0.04398 | J17: =AI17*'VSL and Injuries'!$K$6 -> 103500 | K17: =G17*'VSL and Injuries'!$B$4+H17*'VSL and Injuries'!$B$4*I17 -> 17322580 | L17: =J17+K17 -> 17426080 | M17: 8 | N17: 35 | O17: =IFERROR(INDEX('VSL and Injuries'!$G$21:$G$24,MATCH($AE17,'VSL and Injuries'!$A$21:$A$24,0)),"") -> 0.04398 | P17: =AJ17*'VSL and Injuries'!$K$6 -> 1035000 | Q17: =M17*'VSL and Injuries'!$B$4+N17*'VSL and Injuries'!$B$4*O17 -> 135458060 | R17: =P17+Q17 -> 136493060 | S17: 40 | T17: 150 | U17: =IFERROR(INDEX('VSL and Injuries'!$G$21:$G$24,MATCH($AE17,'VSL and Injuries'!$A$21:$A$24,0)),"") -> 0.04398 | V17: =AK17*'VSL and Injuries'!$K$6 -> 10350000 | W17: =S17*'VSL and Injuries'!$B$4+T17*'VSL and Injuries'!$B$4*U17 -> 661677400 | X17: =V17+W17 -> 672027400 | Y17: S009; S010; S027 | Z17: Single vehicle against a dense pedestrian area; excludes secondary explosives/firearms unless part of observed casualty totals. | AA17: Vehicle mass, speed, barriers, crowd geometry, and follow-on actions strongly affect results. | AB17: Pre-2001 admissible; steady-state use only; not aggregated with aviation | AC17: n/a (non-aviation) | AD17: To be recorded per run: accident (1st+2nd order) / crime (1st order only) / outage (2nd order only) | AE17: Blunt / vehicular (MAIS-adequate) | AF17: 0.03 | AG17: 0.06 | AH17: 0.12 | AI17: 100000 | AJ17: 1000000 | AK17: 10000000
A18: SU-04 | B18: Surface | C18: All UAS against surface transportation | D18: Mechanistic + critical-infrastructure threat guidance | E18: Low | F18: CISA UAS critical-infrastructure guidance; TSA C-UAS program; GAO unauthorized UAS findings | G18: 0 | H18: 3 | I18: =IFERROR(INDEX('VSL and Injuries'!$G$21:$G$24,MATCH($AE18,'VSL and Injuries'!$A$21:$A$24,0)),"") -> 0.16094 | J18: =AI18*'VSL and Injuries'!$K$6 -> 258750 | K18: =G18*'VSL and Injuries'!$B$4+H18*'VSL and Injuries'!$B$4*I18 -> 6856044 | L18: =J18+K18 -> 7114794 | M18: 2 | N18: 20 | O18: =IFERROR(INDEX('VSL and Injuries'!$G$21:$G$24,MATCH($AE18,'VSL and Injuries'!$A$21:$A$24,0)),"") -> 0.16094 | P18: =AJ18*'VSL and Injuries'!$K$6 -> 5175000 | Q18: =M18*'VSL and Injuries'!$B$4+N18*'VSL and Injuries'!$B$4*O18 -> 74106960 | R18: =P18+Q18 -> 79281960 | S18: 20 | T18: 100 | U18: =IFERROR(INDEX('VSL and Injuries'!$G$21:$G$24,MATCH($AE18,'VSL and Injuries'!$A$21:$A$24,0)),"") -> 0.16094 | V18: =AK18*'VSL and Injuries'!$K$6 -> 51750000 | W18: =S18*'VSL and Injuries'!$B$4+T18*'VSL and Injuries'!$B$4*U18 -> 512534800 | X18: =V18+W18 -> 564284800 | Y18: S011; S012; S013 | Z18: Ranges cover surveillance/disruption, collision, and limited payload attack against surface systems. | AA18: No directly comparable successful domestic terrorist event; high estimate is model-derived. | AB18: Pre-2001 admissible; steady-state use only; not aggregated with aviation | AC18: n/a (non-aviation) | AD18: To be recorded per run: accident (1st+2nd order) / crime (1st order only) / outage (2nd order only) | AE18: Blast (primary/secondary/quaternary) | AF18: 0.02 | AG18: 0.05 | AH18: 0.1 | AI18: 250000 | AJ18: 5000000 | AK18: 50000000
A19: SU-05 | B19: Surface | C19: Chem/Bio contamination of food transported by tanker truck | D19: Food-defense vulnerability framework + mechanistic public-health model | E19: Low | F19: FDA intentional-adulteration rule and bulk-food transport guidance; CDC toxicology | G19: 0 | H19: 10 | I19: =IFERROR(INDEX('VSL and Injuries'!$G$21:$G$24,MATCH($AE19,'VSL and Injuries'!$A$21:$A$24,0)),"") -> 0.13141 | J19: =AI19*'VSL and Injuries'!$K$6 -> 517500 | K19: =G19*'VSL and Injuries'!$B$4+H19*'VSL and Injuries'!$B$4*I19 -> 18660220 | L19: =J19+K19 -> 19177720 | M19: 10 | N19: 250 | O19: =IFERROR(INDEX('VSL and Injuries'!$G$21:$G$24,MATCH($AE19,'VSL and Injuries'!$A$21:$A$24,0)),"") -> 0.13141 | P19: =AJ19*'VSL and Injuries'!$K$6 -> 15525000 | Q19: =M19*'VSL and Injuries'!$B$4+N19*'VSL and Injuries'!$B$4*O19 -> 608505500 | R19: =P19+Q19 -> 624030500 | S19: 250 | T19: 3000 | U19: =IFERROR(INDEX('VSL and Injuries'!$G$21:$G$24,MATCH($AE19,'VSL and Injuries'!$A$21:$A$24,0)),"") -> 0.13141 | V19: =AK19*'VSL and Injuries'!$K$6 -> 103500000 | W19: =S19*'VSL and Injuries'!$B$4+T19*'VSL and Injuries'!$B$4*U19 -> 9148066000 | X19: =V19+W19 -> 9251566000 | Y19: S014; S015; S028 | Z19: Contamination enters a distributed food stream before detection; recalls and business interruption are excluded from outcome property damage. | AA19: Highly sensitive to food type, dilution, dose, detection point, distribution reach, and treatment. | AB19: Pre-2001 admissible; steady-state use only; not aggregated with aviation | AC19: n/a (non-aviation) | AD19: To be recorded per run: accident (1st+2nd order) / crime (1st order only) / outage (2nd order only) | AE19: Chemical / biological | AF19: 0.015 | AG19: 0.04 | AH19: 0.1 | AI19: 500000 | AJ19: 15000000 | AK19: 100000000
A20: AV-05b | B20: Aviation | C20: Commercial passenger aircraft hijacking - aircraft as weapon into populated/economic target (9/11-style) | D20: Mechanistic model | E20: Low | F20: 9/11 Commission documentation for ground-target impact mechanism; structural-collapse and mass-casualty building-impact analogs | G20: 100 | H20: 150 | I20: =IFERROR(INDEX('VSL and Injuries'!$G$21:$G$24,MATCH($AE20,'VSL and Injuries'!$A$21:$A$24,0)),"") -> 0.16094 | J20: =AI20*'VSL and Injuries'!$K$6 -> 517500000 | K20: =G20*'VSL and Injuries'!$B$4+H20*'VSL and Injuries'!$B$4*I20 -> 1762802200 | L20: =K20+J20 -> 2280302200 | M20: 500 | N20: 800 | O20: =IFERROR(INDEX('VSL and Injuries'!$G$21:$G$24,MATCH($AE20,'VSL and Injuries'!$A$21:$A$24,0)),"") -> 0.16094 | P20: =AJ20*'VSL and Injuries'!$K$6 -> 5175000000 | Q20: =M20*'VSL and Injuries'!$B$4+N20*'VSL and Injuries'!$B$4*O20 -> 8928278400 | R20: =Q20+P20 -> 14103278400 | S20: 3000 | T20: 6000 | U20: =IFERROR(INDEX('VSL and Injuries'!$G$21:$G$24,MATCH($AE20,'VSL and Injuries'!$A$21:$A$24,0)),"") -> 0.16094 | V20: =AK20*'VSL and Injuries'!$K$6 -> 41400000000 | W20: =S20*'VSL and Injuries'!$B$4+T20*'VSL and Injuries'!$B$4*U20 -> 56312088000 | X20: =W20+V20 -> 97712088000 | Y20: S007; S019; S032; S033 | Z20: Objective is to use the aircraft as a weapon against a high-occupancy ground target. Casualties and property dominated by the ground target, not the aircraft; blast/structural-collapse trauma governs injury severity. This is the catastrophic tail previously buried inside the lumped hijacking family. | AA20: Single defining U.S. event (2001) predates the post-2001 screen; used ONLY for the ground-impact mechanism, which the 2001-2002 regime change does not alter given breach. Probability of success not modeled; conditional consequence only. | AB20: On or after 2001-09-11 (ATSA regime change) | AC20: Exception taken: 9/11 used for ground-impact CONSEQUENCE mechanism only. Hardened doors/ATSA screening reduce likelihood of breach but do not change the physical consequence conditional on aircraft-as-weapon use. Recorded per Section 4.4. | AD20: Building-collapse and mass-casualty structural analogs used for casualty/property scale (1st order) only; not for adversary capability or feasibility. | AE20: Blast (primary/secondary/quaternary) | AI20: 500000000 | AJ20: 5000000000 | AK20: 40000000000
A21: AV-06b | B21: Aviation | C21: Cargo aircraft hijacking - aircraft as weapon into populated/economic target | D21: Mechanistic model | E21: Low | F21: Aircraft-as-weapon ground-impact mechanism (as AV-05b), scaled to cargo airframe; no onboard passenger load | G21: 50 | H21: 80 | I21: =IFERROR(INDEX('VSL and Injuries'!$G$21:$G$24,MATCH($AE21,'VSL and Injuries'!$A$21:$A$24,0)),"") -> 0.16094 | J21: =AI21*'VSL and Injuries'!$K$6 -> 310500000 | K21: =G21*'VSL and Injuries'!$B$4+H21*'VSL and Injuries'!$B$4*I21 -> 892827840 | L21: =K21+J21 -> 1203327840 | M21: 300 | N21: 500 | O21: =IFERROR(INDEX('VSL and Injuries'!$G$21:$G$24,MATCH($AE21,'VSL and Injuries'!$A$21:$A$24,0)),"") -> 0.16094 | P21: =AJ21*'VSL and Injuries'!$K$6 -> 3105000000 | Q21: =M21*'VSL and Injuries'!$B$4+N21*'VSL and Injuries'!$B$4*O21 -> 5402674000 | R21: =Q21+P21 -> 8507674000 | S21: 2000 | T21: 3500 | U21: =IFERROR(INDEX('VSL and Injuries'!$G$21:$G$24,MATCH($AE21,'VSL and Injuries'!$A$21:$A$24,0)),"") -> 0.16094 | V21: =AK21*'VSL and Injuries'!$K$6 -> 25875000000 | W21: =S21*'VSL and Injuries'!$B$4+T21*'VSL and Injuries'!$B$4*U21 -> 36398718000 | X21: =W21+V21 -> 62273718000 | Y21: S017; S018; S029; S032 | Z21: Same aircraft-as-weapon mechanism as AV-05b with a cargo airframe: no passenger load, so onboard casualties minimal and total casualties driven by the ground target. Cargo aircraft may carry larger long-haul fuel load, kept in the high case. | AA21: No observed cargo aircraft-as-weapon event; scale inferred from the passenger aircraft-as-weapon mechanism and ground-target analogs. Conditional consequence only; likelihood not modeled. | AB21: On or after 2001-09-11 (ATSA regime change) | AC21: Exception taken: ground-impact mechanism inferred from 9/11 consequence physics, applied to cargo airframe. Recorded per Section 4.4. | AD21: Ground-target structural analogs used for consequence scale only; cargo-specific fuel-load analogs for property. | AE21: Blast (primary/secondary/quaternary) | AI21: 300000000 | AJ21: 3000000000 | AK21: 25000000000

Sheet Target Inputs
A1: Consequence Target Archetype Inputs
A3: Target | B3: Scope | C3: Minimum Material Outage (h) | D3: P50 Restoration (h) | E3: P90 Restoration (h) | F3: Confidence | G3: Low Deaths | H3: Low Injuries | I3: Low Injury Fraction | J3: Low Infrastructure Damage | K3: Low Daily Indirect Loss | L3: Best Deaths | M3: Best Injuries | N3: Best Injury Fraction | O3: Best Infrastructure Damage | P3: Best Daily Indirect Loss | Q3: High Deaths | R3: High Injuries | S3: High Injury Fraction | T3: High Infrastructure Damage | U3: High Daily Indirect Loss | V3: Source IDs | W3: Assumptions | X3: Regulatory-Delay Days (CAO/site-control/pressure-restriction) | Y3: Effective P90 Restoration (h)
A4: Pipeline Segment | B4: Representative hazardous-liquid or natural-gas transmission segment | C4: 24 | D4: 72 | E4: 336 | F4: Moderate-Low | G4: 0 | H4: 1 | I4: 0.02 | J4: 2000000 | K4: 5000000 | L4: 1 | M4: 5 | N4: 0.05 | O4: 15000000 | P4: 25000000 | Q4: 5 | R4: 20 | S4: 0.12 | T4: 100000000 | U4: 100000000 | V4: S017; S029; S030; S031 | W4: Daily indirect loss represents affected commodity value, substitution, curtailment, and dependent-sector disruption; excludes price-spike transfers. | X4: 20 | Y4: =E4+X4*24 -> 816
A5: Pump Station | B5: Representative liquid-pipeline pump station | C5: 12 | D5: 48 | E5: 240 | F5: Low | G5: 0 | H5: 1 | I5: 0.02 | J5: 1000000 | K5: 3000000 | L5: 1 | M5: 4 | N5: 0.05 | O5: 8000000 | P5: 15000000 | Q5: 4 | R5: 15 | S5: 0.12 | T5: 50000000 | U5: 60000000 | V5: S017; S029; S031 | W5: Assumes partial rerouting/storage capability in low and central cases; no system-specific topology is embedded. | X5: 10 | Y5: =E5+X5*24 -> 480
A6: Compressor Station | B6: Representative natural-gas compressor station | C6: 12 | D6: 72 | E6: 336 | F6: Low | G6: 0 | H6: 1 | I6: 0.02 | J6: 2000000 | K6: 4000000 | L6: 1 | M6: 5 | N6: 0.05 | O6: 12000000 | P6: 20000000 | Q6: 5 | R6: 20 | S6: 0.12 | T6: 75000000 | U6: 80000000 | V6: S017; S029; S031 | W6: Indirect loss depends on season, storage, network redundancy, affected customers, and gas-fired generation exposure. | X6: 20 | Y6: =E6+X6*24 -> 816
A7: Airport Terminal | B7: Representative large-hub passenger terminal or major terminal complex | C7: 4 | D7: 24 | E7: 168 | F7: Moderate-Low | G7: 0 | H7: 5 | I7: 0.025 | J7: 25000000 | K7: 5000000 | L7: 5 | M7: 50 | N7: 0.05 | O7: 200000000 | P7: 40000000 | Q7: 30 | R7: 250 | S7: 0.12 | T7: 1000000000 | U7: 200000000 | V7: S007; S019; S032; S033 | W7: Daily indirect loss includes displaced aviation activity, passenger delay, airport concessions, air cargo, and visitor effects; not airport-specific. | X7: 5 | Y7: =E7+X7*24 -> 288
A8: Freight Rail | B8: Representative nationally significant freight-rail corridor, bridge, tunnel, yard, or intermodal node | C8: 12 | D8: 72 | E8: 336 | F8: Moderate-Low | G8: 0 | H8: 1 | I8: 0.02 | J8: 2000000 | K8: 2000000 | L8: 1 | M8: 8 | N8: 0.05 | O8: 20000000 | P8: 15000000 | Q8: 10 | R8: 50 | S8: 0.12 | T8: 150000000 | U8: 75000000 | V8: S018; S020; S034 | W8: Indirect loss reflects delayed/lost freight value and dependent production; substitute routing is represented only through the range. | X8: 10 | Y8: =E8+X8*24 -> 576
A10: Regulatory reality note | B10: Engineering P90 restoration understates outage for regulated assets. Effective P90 adds the federal regulatory lifecycle (NTSB site control, PHMSA Corrective Action Order, metallurgical/forensic testing, and mandatory post-restart pressure restrictions). Danville PIR22002 confirms multi-week to multi-month effective outage for a major transmission segment.

Sheet Duration Factors
A1: Outage Duration and Escalation Factors
A3: Duration Label | B3: Hours | C3: Days | D3: Escalation / Buffer Factor | E3: Regulatory-Delay Add-On (days) | F3: Basis | G3: Effective Outage Days (eng + regulatory)
A4: 4 hours | B4: 4 | C4: 0.16666667 | D4: 0.35 | E4: 0 | F4: Minor; no formal hold | G4: =C4+E4 -> 0.16666667
A5: 12 hours | B5: 12 | C5: 0.5 | D5: 0.55 | E5: 0 | F5: Minor; no formal hold | G5: =C5+E5 -> 0.5
A6: 1 day | B6: 24 | C6: 1 | D6: 0.7 | E6: 0 | F6: Possible incident notification | G6: =C6+E6 -> 1
A7: 3 days | B7: 72 | C7: 3 | D7: 0.9 | E7: 1 | F7: NTSB/PHMSA notification; short hold | G7: =C7+E7 -> 4
A8: 7 days | B8: 168 | C8: 7 | D8: 1 | E8: 2 | F8: Site control + initial CAO | G8: =C8+E8 -> 9
A9: 14 days | B9: 336 | C9: 14 | D9: 1.1 | E9: 3 | F9: CAO + metallurgical/forensic testing | G9: =C9+E9 -> 17
A10: 30 days | B10: 720 | C10: 30 | D10: 1.2 | E10: 5 | F10: CAO + mandatory post-restart pressure restriction ramp | G10: =C10+E10 -> 35
A11: 45 days | B11: 1080 | C11: 45 | D11: 1.3 | E11: 10 | F11: Prolonged CAO; extensive replacement + phased restart | G11: =C11+E11 -> 55
A12: 90 days | B12: 2160 | C12: 90 | D12: 1.4 | E12: 20 | F12: Full CAO lifecycle; hydro-test + regulator sign-off before full pressure | G12: =C12+E12 -> 110
A13: Escalation / buffer factor | B13: Represents inventories, linepack, rerouting, schedule recovery, and increasing cascade severity as outages persist.
A14: Use | B14: Multiply daily indirect loss by outage days and this factor. Replace with target-specific recovery curves when available.
A15: Regulatory-delay add-on | B15: Days added to engineering restoration for forensic hold, NTSB site control, PHMSA Corrective Action Orders (CAOs), and mandatory post-restart pressure restrictions. The Danville PIR22002 transmission rupture confirms that a 14-day cap for a major pipeline is an engineering fiction once the regulatory lifecycle is included.
A16: Use | B16: Multiply daily indirect loss by EFFECTIVE outage days (column G) and the escalation/buffer factor. Replace with target-specific recovery + regulatory curves when available.

Sheet Consequence Targets
A1: First- and Second-Order Consequences by Target and Outage Duration
A3: Target | B3: Outage | C3: Hours | D3: Days | E3: Escalation Factor | F3: Confidence | G3: Low Deaths | H3: Low Injuries | I3: Low Injury Fraction | J3: Low Infrastructure Damage | K3: Low Daily Indirect | L3: Low First Order | M3: Low Second Order | N3: Low Total | O3: Best Deaths | P3: Best Injuries | Q3: Best Injury Fraction | R3: Best Infrastructure Damage | S3: Best Daily Indirect | T3: Best First Order | U3: Best Second Order | V3: Best Total | W3: High Deaths | X3: High Injuries | Y3: High Injury Fraction | Z3: High Infrastructure Damage | AA3: High Daily Indirect | AB3: High First Order | AC3: High Second Order | AD3: High Total | AE3: Source IDs | AF3: Assumptions | AG3: Effective Outage Days (eng + regulatory)
A4: Pipeline Segment | B4: 4 hours | C4: 4 | D4: =IFERROR(INDEX('Duration Factors'!$C$4:$C$12,MATCH($B4,'Duration Factors'!$A$4:$A$12,0)),"") -> 0.16666667 | E4: =IFERROR(INDEX('Duration Factors'!$D$4:$D$12,MATCH($B4,'Duration Factors'!$A$4:$A$12,0)),"") -> 0.35 | F4: Moderate-Low | G4: ='Target Inputs'!G4 -> 0 | H4: ='Target Inputs'!H4 -> 1 | I4: ='Target Inputs'!I4 -> 0.02 | J4: ='Target Inputs'!J4 -> 2000000 | K4: ='Target Inputs'!K4 -> 5000000 | L4: =G4*'VSL and Injuries'!$B$4+H4*'VSL and Injuries'!$B$4*I4+J4*'VSL and Injuries'!$K$6 -> 2354000 | M4: =K4*'VSL and Injuries'!$K$6*$AG4*E4 -> 301875 | N4: =L4+M4 -> 2655875 | O4: ='Target Inputs'!L4 -> 1 | P4: ='Target Inputs'!M4 -> 5 | Q4: ='Target Inputs'!N4 -> 0.05 | R4: ='Target Inputs'!O4 -> 15000000 | S4: ='Target Inputs'!P4 -> 25000000 | T4: =O4*'VSL and Injuries'!$B$4+P4*'VSL and Injuries'!$B$4*Q4+R4*'VSL and Injuries'!$K$6 -> 33275000 | U4: =S4*'VSL and Injuries'!$K$6*$AG4*E4 -> 1509375 | V4: =T4+U4 -> 34784375 | W4: ='Target Inputs'!Q4 -> 5 | X4: ='Target Inputs'!R4 -> 20 | Y4: ='Target Inputs'!S4 -> 0.12 | Z4: ='Target Inputs'!T4 -> 100000000 | AA4: ='Target Inputs'!U4 -> 100000000 | AB4: =W4*'VSL and Injuries'!$B$4+X4*'VSL and Injuries'!$B$4*Y4+Z4*'VSL and Injuries'!$K$6 -> 208580000 | AC4: =AA4*'VSL and Injuries'!$K$6*$AG4*E4 -> 6037500 | AD4: =AB4+AC4 -> 214617500 | AE4: S017; S029; S030; S031 | AF4: Daily indirect loss represents affected commodity value, substitution, curtailment, and dependent-sector disruption; excludes price-spike transfers. | AG4: =IFERROR(INDEX('Duration Factors'!$G$4:$G$12,MATCH($B4,'Duration Factors'!$A$4:$A$12,0)),"") -> 0.16666667
A5: Pipeline Segment | B5: 12 hours | C5: 12 | D5: =IFERROR(INDEX('Duration Factors'!$C$4:$C$12,MATCH($B5,'Duration Factors'!$A$4:$A$12,0)),"") -> 0.5 | E5: =IFERROR(INDEX('Duration Factors'!$D$4:$D$12,MATCH($B5,'Duration Factors'!$A$4:$A$12,0)),"") -> 0.55 | F5: Moderate-Low | G5: ='Target Inputs'!G4 -> 0 | H5: ='Target Inputs'!H4 -> 1 | I5: ='Target Inputs'!I4 -> 0.02 | J5: ='Target Inputs'!J4 -> 2000000 | K5: ='Target Inputs'!K4 -> 5000000 | L5: =G5*'VSL and Injuries'!$B$4+H5*'VSL and Injuries'!$B$4*I5+J5*'VSL and Injuries'!$K$6 -> 2354000 | M5: =K5*'VSL and Injuries'!$K$6*$AG5*E5 -> 1423125 | N5: =L5+M5 -> 3777125 | O5: ='Target Inputs'!L4 -> 1 | P5: ='Target Inputs'!M4 -> 5 | Q5: ='Target Inputs'!N4 -> 0.05 | R5: ='Target Inputs'!O4 -> 15000000 | S5: ='Target Inputs'!P4 -> 25000000 | T5: =O5*'VSL and Injuries'!$B$4+P5*'VSL and Injuries'!$B$4*Q5+R5*'VSL and Injuries'!$K$6 -> 33275000 | U5: =S5*'VSL and Injuries'!$K$6*$AG5*E5 -> 7115625 | V5: =T5+U5 -> 40390625 | W5: ='Target Inputs'!Q4 -> 5 | X5: ='Target Inputs'!R4 -> 20 | Y5: ='Target Inputs'!S4 -> 0.12 | Z5: ='Target Inputs'!T4 -> 100000000 | AA5: ='Target Inputs'!U4 -> 100000000 | AB5: =W5*'VSL and Injuries'!$B$4+X5*'VSL and Injuries'!$B$4*Y5+Z5*'VSL and Injuries'!$K$6 -> 208580000 | AC5: =AA5*'VSL and Injuries'!$K$6*$AG5*E5 -> 28462500 | AD5: =AB5+AC5 -> 237042500 | AE5: S017; S029; S030; S031 | AF5: Daily indirect loss represents affected commodity value, substitution, curtailment, and dependent-sector disruption; excludes price-spike transfers. | AG5: =IFERROR(INDEX('Duration Factors'!$G$4:$G$12,MATCH($B5,'Duration Factors'!$A$4:$A$12,0)),"") -> 0.5
A6: Pipeline Segment | B6: 1 day | C6: 24 | D6: =IFERROR(INDEX('Duration Factors'!$C$4:$C$12,MATCH($B6,'Duration Factors'!$A$4:$A$12,0)),"") -> 1 | E6: =IFERROR(INDEX('Duration Factors'!$D$4:$D$12,MATCH($B6,'Duration Factors'!$A$4:$A$12,0)),"") -> 0.7 | F6: Moderate-Low | G6: ='Target Inputs'!G4 -> 0 | H6: ='Target Inputs'!H4 -> 1 | I6: ='Target Inputs'!I4 -> 0.02 | J6: ='Target Inputs'!J4 -> 2000000 | K6: ='Target Inputs'!K4 -> 5000000 | L6: =G6*'VSL and Injuries'!$B$4+H6*'VSL and Injuries'!$B$4*I6+J6*'VSL and Injuries'!$K$6 -> 2354000 | M6: =K6*'VSL and Injuries'!$K$6*$AG6*E6 -> 3622500 | N6: =L6+M6 -> 5976500 | O6: ='Target Inputs'!L4 -> 1 | P6: ='Target Inputs'!M4 -> 5 | Q6: ='Target Inputs'!N4 -> 0.05 | R6: ='Target Inputs'!O4 -> 15000000 | S6: ='Target Inputs'!P4 -> 25000000 | T6: =O6*'VSL and Injuries'!$B$4+P6*'VSL and Injuries'!$B$4*Q6+R6*'VSL and Injuries'!$K$6 -> 33275000 | U6: =S6*'VSL and Injuries'!$K$6*$AG6*E6 -> 18112500 | V6: =T6+U6 -> 51387500 | W6: ='Target Inputs'!Q4 -> 5 | X6: ='Target Inputs'!R4 -> 20 | Y6: ='Target Inputs'!S4 -> 0.12 | Z6: ='Target Inputs'!T4 -> 100000000 | AA6: ='Target Inputs'!U4 -> 100000000 | AB6: =W6*'VSL and Injuries'!$B$4+X6*'VSL and Injuries'!$B$4*Y6+Z6*'VSL and Injuries'!$K$6 -> 208580000 | AC6: =AA6*'VSL and Injuries'!$K$6*$AG6*E6 -> 72450000 | AD6: =AB6+AC6 -> 281030000 | AE6: S017; S029; S030; S031 | AF6: Daily indirect loss represents affected commodity value, substitution, curtailment, and dependent-sector disruption; excludes price-spike transfers. | AG6: =IFERROR(INDEX('Duration Factors'!$G$4:$G$12,MATCH($B6,'Duration Factors'!$A$4:$A$12,0)),"") -> 1
A7: Pipeline Segment | B7: 3 days | C7: 72 | D7: =IFERROR(INDEX('Duration Factors'!$C$4:$C$12,MATCH($B7,'Duration Factors'!$A$4:$A$12,0)),"") -> 3 | E7: =IFERROR(INDEX('Duration Factors'!$D$4:$D$12,MATCH($B7,'Duration Factors'!$A$4:$A$12,0)),"") -> 0.9 | F7: Moderate-Low | G7: ='Target Inputs'!G4 -> 0 | H7: ='Target Inputs'!H4 -> 1 | I7: ='Target Inputs'!I4 -> 0.02 | J7: ='Target Inputs'!J4 -> 2000000 | K7: ='Target Inputs'!K4 -> 5000000 | L7: =G7*'VSL and Injuries'!$B$4+H7*'VSL and Injuries'!$B$4*I7+J7*'VSL and Injuries'!$K$6 -> 2354000 | M7: =K7*'VSL and Injuries'!$K$6*$AG7*E7 -> 18630000 | N7: =L7+M7 -> 20984000 | O7: ='Target Inputs'!L4 -> 1 | P7: ='Target Inputs'!M4 -> 5 | Q7: ='Target Inputs'!N4 -> 0.05 | R7: ='Target Inputs'!O4 -> 15000000 | S7: ='Target Inputs'!P4 -> 25000000 | T7: =O7*'VSL and Injuries'!$B$4+P7*'VSL and Injuries'!$B$4*Q7+R7*'VSL and Injuries'!$K$6 -> 33275000 | U7: =S7*'VSL and Injuries'!$K$6*$AG7*E7 -> 93150000 | V7: =T7+U7 -> 126425000 | W7: ='Target Inputs'!Q4 -> 5 | X7: ='Target Inputs'!R4 -> 20 | Y7: ='Target Inputs'!S4 -> 0.12 | Z7: ='Target Inputs'!T4 -> 100000000 | AA7: ='Target Inputs'!U4 -> 100000000 | AB7: =W7*'VSL and Injuries'!$B$4+X7*'VSL and Injuries'!$B$4*Y7+Z7*'VSL and Injuries'!$K$6 -> 208580000 | AC7: =AA7*'VSL and Injuries'!$K$6*$AG7*E7 -> 372600000 | AD7: =AB7+AC7 -> 581180000 | AE7: S017; S029; S030; S031 | AF7: Daily indirect loss represents affected commodity value, substitution, curtailment, and dependent-sector disruption; excludes price-spike transfers. | AG7: =IFERROR(INDEX('Duration Factors'!$G$4:$G$12,MATCH($B7,'Duration Factors'!$A$4:$A$12,0)),"") -> 4
A8: Pipeline Segment | B8: 7 days | C8: 168 | D8: =IFERROR(INDEX('Duration Factors'!$C$4:$C$12,MATCH($B8,'Duration Factors'!$A$4:$A$12,0)),"") -> 7 | E8: =IFERROR(INDEX('Duration Factors'!$D$4:$D$12,MATCH($B8,'Duration Factors'!$A$4:$A$12,0)),"") -> 1 | F8: Moderate-Low | G8: ='Target Inputs'!G4 -> 0 | H8: ='Target Inputs'!H4 -> 1 | I8: ='Target Inputs'!I4 -> 0.02 | J8: ='Target Inputs'!J4 -> 2000000 | K8: ='Target Inputs'!K4 -> 5000000 | L8: =G8*'VSL and Injuries'!$B$4+H8*'VSL and Injuries'!$B$4*I8+J8*'VSL and Injuries'!$K$6 -> 2354000 | M8: =K8*'VSL and Injuries'!$K$6*$AG8*E8 -> 46575000 | N8: =L8+M8 -> 48929000 | O8: ='Target Inputs'!L4 -> 1 | P8: ='Target Inputs'!M4 -> 5 | Q8: ='Target Inputs'!N4 -> 0.05 | R8: ='Target Inputs'!O4 -> 15000000 | S8: ='Target Inputs'!P4 -> 25000000 | T8: =O8*'VSL and Injuries'!$B$4+P8*'VSL and Injuries'!$B$4*Q8+R8*'VSL and Injuries'!$K$6 -> 33275000 | U8: =S8*'VSL and Injuries'!$K$6*$AG8*E8 -> 232875000 | V8: =T8+U8 -> 266150000 | W8: ='Target Inputs'!Q4 -> 5 | X8: ='Target Inputs'!R4 -> 20 | Y8: ='Target Inputs'!S4 -> 0.12 | Z8: ='Target Inputs'!T4 -> 100000000 | AA8: ='Target Inputs'!U4 -> 100000000 | AB8: =W8*'VSL and Injuries'!$B$4+X8*'VSL and Injuries'!$B$4*Y8+Z8*'VSL and Injuries'!$K$6 -> 208580000 | AC8: =AA8*'VSL and Injuries'!$K$6*$AG8*E8 -> 931500000 | AD8: =AB8+AC8 -> 1140080000 | AE8: S017; S029; S030; S031 | AF8: Daily indirect loss represents affected commodity value, substitution, curtailment, and dependent-sector disruption; excludes price-spike transfers. | AG8: =IFERROR(INDEX('Duration Factors'!$G$4:$G$12,MATCH($B8,'Duration Factors'!$A$4:$A$12,0)),"") -> 9
A9: Pipeline Segment | B9: 14 days | C9: 336 | D9: =IFERROR(INDEX('Duration Factors'!$C$4:$C$12,MATCH($B9,'Duration Factors'!$A$4:$A$12,0)),"") -> 14 | E9: =IFERROR(INDEX('Duration Factors'!$D$4:$D$12,MATCH($B9,'Duration Factors'!$A$4:$A$12,0)),"") -> 1.1 | F9: Moderate-Low | G9: ='Target Inputs'!G4 -> 0 | H9: ='Target Inputs'!H4 -> 1 | I9: ='Target Inputs'!I4 -> 0.02 | J9: ='Target Inputs'!J4 -> 2000000 | K9: ='Target Inputs'!K4 -> 5000000 | L9: =G9*'VSL and Injuries'!$B$4+H9*'VSL and Injuries'!$B$4*I9+J9*'VSL and Injuries'!$K$6 -> 2354000 | M9: =K9*'VSL and Injuries'!$K$6*$AG9*E9 -> 96772500 | N9: =L9+M9 -> 99126500 | O9: ='Target Inputs'!L4 -> 1 | P9: ='Target Inputs'!M4 -> 5 | Q9: ='Target Inputs'!N4 -> 0.05 | R9: ='Target Inputs'!O4 -> 15000000 | S9: ='Target Inputs'!P4 -> 25000000 | T9: =O9*'VSL and Injuries'!$B$4+P9*'VSL and Injuries'!$B$4*Q9+R9*'VSL and Injuries'!$K$6 -> 33275000 | U9: =S9*'VSL and Injuries'!$K$6*$AG9*E9 -> 483862500 | V9: =T9+U9 -> 517137500 | W9: ='Target Inputs'!Q4 -> 5 | X9: ='Target Inputs'!R4 -> 20 | Y9: ='Target Inputs'!S4 -> 0.12 | Z9: ='Target Inputs'!T4 -> 100000000 | AA9: ='Target Inputs'!U4 -> 100000000 | AB9: =W9*'VSL and Injuries'!$B$4+X9*'VSL and Injuries'!$B$4*Y9+Z9*'VSL and Injuries'!$K$6 -> 208580000 | AC9: =AA9*'VSL and Injuries'!$K$6*$AG9*E9 -> 1935450000 | AD9: =AB9+AC9 -> 2144030000 | AE9: S017; S029; S030; S031 | AF9: Daily indirect loss represents affected commodity value, substitution, curtailment, and dependent-sector disruption; excludes price-spike transfers. | AG9: =IFERROR(INDEX('Duration Factors'!$G$4:$G$12,MATCH($B9,'Duration Factors'!$A$4:$A$12,0)),"") -> 17
A10: Pipeline Segment | B10: 30 days | C10: 720 | D10: =IFERROR(INDEX('Duration Factors'!$C$4:$C$12,MATCH($B10,'Duration Factors'!$A$4:$A$12,0)),"") -> 30 | E10: =IFERROR(INDEX('Duration Factors'!$D$4:$D$12,MATCH($B10,'Duration Factors'!$A$4:$A$12,0)),"") -> 1.2 | F10: Moderate-Low | G10: ='Target Inputs'!G4 -> 0 | H10: ='Target Inputs'!H4 -> 1 | I10: ='Target Inputs'!I4 -> 0.02 | J10: ='Target Inputs'!J4 -> 2000000 | K10: ='Target Inputs'!K4 -> 5000000 | L10: =G10*'VSL and Injuries'!$B$4+H10*'VSL and Injuries'!$B$4*I10+J10*'VSL and Injuries'!$K$6 -> 2354000 | M10: =K10*'VSL and Injuries'!$K$6*$AG10*E10 -> 217350000 | N10: =L10+M10 -> 219704000 | O10: ='Target Inputs'!L4 -> 1 | P10: ='Target Inputs'!M4 -> 5 | Q10: ='Target Inputs'!N4 -> 0.05 | R10: ='Target Inputs'!O4 -> 15000000 | S10: ='Target Inputs'!P4 -> 25000000 | T10: =O10*'VSL and Injuries'!$B$4+P10*'VSL and Injuries'!$B$4*Q10+R10*'VSL and Injuries'!$K$6 -> 33275000 | U10: =S10*'VSL and Injuries'!$K$6*$AG10*E10 -> 1086750000 | V10: =T10+U10 -> 1120025000 | W10: ='Target Inputs'!Q4 -> 5 | X10: ='Target Inputs'!R4 -> 20 | Y10: ='Target Inputs'!S4 -> 0.12 | Z10: ='Target Inputs'!T4 -> 100000000 | AA10: ='Target Inputs'!U4 -> 100000000 | AB10: =W10*'VSL and Injuries'!$B$4+X10*'VSL and Injuries'!$B$4*Y10+Z10*'VSL and Injuries'!$K$6 -> 208580000 | AC10: =AA10*'VSL and Injuries'!$K$6*$AG10*E10 -> 4347000000 | AD10: =AB10+AC10 -> 4555580000 | AE10: S017; S029; S030; S031 | AF10: Daily indirect loss represents affected commodity value, substitution, curtailment, and dependent-sector disruption; excludes price-spike transfers. | AG10: =IFERROR(INDEX('Duration Factors'!$G$4:$G$12,MATCH($B10,'Duration Factors'!$A$4:$A$12,0)),"") -> 35
A11: Pipeline Segment | B11: 45 days | C11: 1080 | D11: =IFERROR(INDEX('Duration Factors'!$C$4:$C$12,MATCH($B11,'Duration Factors'!$A$4:$A$12,0)),"") -> 45 | E11: =IFERROR(INDEX('Duration Factors'!$D$4:$D$12,MATCH($B11,'Duration Factors'!$A$4:$A$12,0)),"") -> 1.3 | F11: Moderate-Low | G11: ='Target Inputs'!G4 -> 0 | H11: ='Target Inputs'!H4 -> 1 | I11: ='Target Inputs'!I4 -> 0.02 | J11: ='Target Inputs'!J4 -> 2000000 | K11: ='Target Inputs'!K4 -> 5000000 | L11: =G11*'VSL and Injuries'!$B$4+H11*'VSL and Injuries'!$B$4*I11+J11*'VSL and Injuries'!$K$6 -> 2354000 | M11: =K11*'VSL and Injuries'!$K$6*$AG11*E11 -> 370012500 | N11: =L11+M11 -> 372366500 | O11: ='Target Inputs'!L4 -> 1 | P11: ='Target Inputs'!M4 -> 5 | Q11: ='Target Inputs'!N4 -> 0.05 | R11: ='Target Inputs'!O4 -> 15000000 | S11: ='Target Inputs'!P4 -> 25000000 | T11: =O11*'VSL and Injuries'!$B$4+P11*'VSL and Injuries'!$B$4*Q11+R11*'VSL and Injuries'!$K$6 -> 33275000 | U11: =S11*'VSL and Injuries'!$K$6*$AG11*E11 -> 1850062500 | V11: =T11+U11 -> 1883337500 | W11: ='Target Inputs'!Q4 -> 5 | X11: ='Target Inputs'!R4 -> 20 | Y11: ='Target Inputs'!S4 -> 0.12 | Z11: ='Target Inputs'!T4 -> 100000000 | AA11: ='Target Inputs'!U4 -> 100000000 | AB11: =W11*'VSL and Injuries'!$B$4+X11*'VSL and Injuries'!$B$4*Y11+Z11*'VSL and Injuries'!$K$6 -> 208580000 | AC11: =AA11*'VSL and Injuries'!$K$6*$AG11*E11 -> 7400250000 | AD11: =AB11+AC11 -> 7608830000 | AE11: S017; S029; S030; S031 | AF11: Daily indirect loss represents affected commodity value, substitution, curtailment, and dependent-sector disruption; excludes price-spike transfers. | AG11: =IFERROR(INDEX('Duration Factors'!$G$4:$G$12,MATCH($B11,'Duration Factors'!$A$4:$A$12,0)),"") -> 55
A12: Pipeline Segment | B12: 90 days | C12: 2160 | D12: =IFERROR(INDEX('Duration Factors'!$C$4:$C$12,MATCH($B12,'Duration Factors'!$A$4:$A$12,0)),"") -> 90 | E12: =IFERROR(INDEX('Duration Factors'!$D$4:$D$12,MATCH($B12,'Duration Factors'!$A$4:$A$12,0)),"") -> 1.4 | F12: Moderate-Low | G12: ='Target Inputs'!G4 -> 0 | H12: ='Target Inputs'!H4 -> 1 | I12: ='Target Inputs'!I4 -> 0.02 | J12: ='Target Inputs'!J4 -> 2000000 | K12: ='Target Inputs'!K4 -> 5000000 | L12: =G12*'VSL and Injuries'!$B$4+H12*'VSL and Injuries'!$B$4*I12+J12*'VSL and Injuries'!$K$6 -> 2354000 | M12: =K12*'VSL and Injuries'!$K$6*$AG12*E12 -> 796950000 | N12: =L12+M12 -> 799304000 | O12: ='Target Inputs'!L4 -> 1 | P12: ='Target Inputs'!M4 -> 5 | Q12: ='Target Inputs'!N4 -> 0.05 | R12: ='Target Inputs'!O4 -> 15000000 | S12: ='Target Inputs'!P4 -> 25000000 | T12: =O12*'VSL and Injuries'!$B$4+P12*'VSL and Injuries'!$B$4*Q12+R12*'VSL and Injuries'!$K$6 -> 33275000 | U12: =S12*'VSL and Injuries'!$K$6*$AG12*E12 -> 3984750000 | V12: =T12+U12 -> 4018025000 | W12: ='Target Inputs'!Q4 -> 5 | X12: ='Target Inputs'!R4 -> 20 | Y12: ='Target Inputs'!S4 -> 0.12 | Z12: ='Target Inputs'!T4 -> 100000000 | AA12: ='Target Inputs'!U4 -> 100000000 | AB12: =W12*'VSL and Injuries'!$B$4+X12*'VSL and Injuries'!$B$4*Y12+Z12*'VSL and Injuries'!$K$6 -> 208580000 | AC12: =AA12*'VSL and Injuries'!$K$6*$AG12*E12 -> 15939000000 | AD12: =AB12+AC12 -> 16147580000 | AE12: S017; S029; S030; S031 | AF12: Daily indirect loss represents affected commodity value, substitution, curtailment, and dependent-sector disruption; excludes price-spike transfers. | AG12: =IFERROR(INDEX('Duration Factors'!$G$4:$G$12,MATCH($B12,'Duration Factors'!$A$4:$A$12,0)),"") -> 110
A13: Pump Station | B13: 4 hours | C13: 4 | D13: =IFERROR(INDEX('Duration Factors'!$C$4:$C$12,MATCH($B13,'Duration Factors'!$A$4:$A$12,0)),"") -> 0.16666667 | E13: =IFERROR(INDEX('Duration Factors'!$D$4:$D$12,MATCH($B13,'Duration Factors'!$A$4:$A$12,0)),"") -> 0.35 | F13: Low | G13: ='Target Inputs'!G5 -> 0 | H13: ='Target Inputs'!H5 -> 1 | I13: ='Target Inputs'!I5 -> 0.02 | J13: ='Target Inputs'!J5 -> 1000000 | K13: ='Target Inputs'!K5 -> 3000000 | L13: =G13*'VSL and Injuries'!$B$4+H13*'VSL and Injuries'!$B$4*I13+J13*'VSL and Injuries'!$K$6 -> 1319000 | M13: =K13*'VSL and Injuries'!$K$6*$AG13*E13 -> 181125 | N13: =L13+M13 -> 1500125 | O13: ='Target Inputs'!L5 -> 1 | P13: ='Target Inputs'!M5 -> 4 | Q13: ='Target Inputs'!N5 -> 0.05 | R13: ='Target Inputs'!O5 -> 8000000 | S13: ='Target Inputs'!P5 -> 15000000 | T13: =O13*'VSL and Injuries'!$B$4+P13*'VSL and Injuries'!$B$4*Q13+R13*'VSL and Injuries'!$K$6 -> 25320000 | U13: =S13*'VSL and Injuries'!$K$6*$AG13*E13 -> 905625 | V13: =T13+U13 -> 26225625 | W13: ='Target Inputs'!Q5 -> 4 | X13: ='Target Inputs'!R5 -> 15 | Y13: ='Target Inputs'!S5 -> 0.12 | Z13: ='Target Inputs'!T5 -> 50000000 | AA13: ='Target Inputs'!U5 -> 60000000 | AB13: =W13*'VSL and Injuries'!$B$4+X13*'VSL and Injuries'!$B$4*Y13+Z13*'VSL and Injuries'!$K$6 -> 134110000 | AC13: =AA13*'VSL and Injuries'!$K$6*$AG13*E13 -> 3622500 | AD13: =AB13+AC13 -> 137732500 | AE13: S017; S029; S031 | AF13: Assumes partial rerouting/storage capability in low and central cases; no system-specific topology is embedded. | AG13: =IFERROR(INDEX('Duration Factors'!$G$4:$G$12,MATCH($B13,'Duration Factors'!$A$4:$A$12,0)),"") -> 0.16666667
A14: Pump Station | B14: 12 hours | C14: 12 | D14: =IFERROR(INDEX('Duration Factors'!$C$4:$C$12,MATCH($B14,'Duration Factors'!$A$4:$A$12,0)),"") -> 0.5 | E14: =IFERROR(INDEX('Duration Factors'!$D$4:$D$12,MATCH($B14,'Duration Factors'!$A$4:$A$12,0)),"") -> 0.55 | F14: Low | G14: ='Target Inputs'!G5 -> 0 | H14: ='Target Inputs'!H5 -> 1 | I14: ='Target Inputs'!I5 -> 0.02 | J14: ='Target Inputs'!J5 -> 1000000 | K14: ='Target Inputs'!K5 -> 3000000 | L14: =G14*'VSL and Injuries'!$B$4+H14*'VSL and Injuries'!$B$4*I14+J14*'VSL and Injuries'!$K$6 -> 1319000 | M14: =K14*'VSL and Injuries'!$K$6*$AG14*E14 -> 853875 | N14: =L14+M14 -> 2172875 | O14: ='Target Inputs'!L5 -> 1 | P14: ='Target Inputs'!M5 -> 4 | Q14: ='Target Inputs'!N5 -> 0.05 | R14: ='Target Inputs'!O5 -> 8000000 | S14: ='Target Inputs'!P5 -> 15000000 | T14: =O14*'VSL and Injuries'!$B$4+P14*'VSL and Injuries'!$B$4*Q14+R14*'VSL and Injuries'!$K$6 -> 25320000 | U14: =S14*'VSL and Injuries'!$K$6*$AG14*E14 -> 4269375 | V14: =T14+U14 -> 29589375 | W14: ='Target Inputs'!Q5 -> 4 | X14: ='Target Inputs'!R5 -> 15 | Y14: ='Target Inputs'!S5 -> 0.12 | Z14: ='Target Inputs'!T5 -> 50000000 | AA14: ='Target Inputs'!U5 -> 60000000 | AB14: =W14*'VSL and Injuries'!$B$4+X14*'VSL and Injuries'!$B$4*Y14+Z14*'VSL and Injuries'!$K$6 -> 134110000 | AC14: =AA14*'VSL and Injuries'!$K$6*$AG14*E14 -> 17077500 | AD14: =AB14+AC14 -> 151187500 | AE14: S017; S029; S031 | AF14: Assumes partial rerouting/storage capability in low and central cases; no system-specific topology is embedded. | AG14: =IFERROR(INDEX('Duration Factors'!$G$4:$G$12,MATCH($B14,'Duration Factors'!$A$4:$A$12,0)),"") -> 0.5
A15: Pump Station | B15: 1 day | C15: 24 | D15: =IFERROR(INDEX('Duration Factors'!$C$4:$C$12,MATCH($B15,'Duration Factors'!$A$4:$A$12,0)),"") -> 1 | E15: =IFERROR(INDEX('Duration Factors'!$D$4:$D$12,MATCH($B15,'Duration Factors'!$A$4:$A$12,0)),"") -> 0.7 | F15: Low | G15: ='Target Inputs'!G5 -> 0 | H15: ='Target Inputs'!H5 -> 1 | I15: ='Target Inputs'!I5 -> 0.02 | J15: ='Target Inputs'!J5 -> 1000000 | K15: ='Target Inputs'!K5 -> 3000000 | L15: =G15*'VSL and Injuries'!$B$4+H15*'VSL and Injuries'!$B$4*I15+J15*'VSL and Injuries'!$K$6 -> 1319000 | M15: =K15*'VSL and Injuries'!$K$6*$AG15*E15 -> 2173500 | N15: =L15+M15 -> 3492500 | O15: ='Target Inputs'!L5 -> 1 | P15: ='Target Inputs'!M5 -> 4 | Q15: ='Target Inputs'!N5 -> 0.05 | R15: ='Target Inputs'!O5 -> 8000000 | S15: ='Target Inputs'!P5 -> 15000000 | T15: =O15*'VSL and Injuries'!$B$4+P15*'VSL and Injuries'!$B$4*Q15+R15*'VSL and Injuries'!$K$6 -> 25320000 | U15: =S15*'VSL and Injuries'!$K$6*$AG15*E15 -> 10867500 | V15: =T15+U15 -> 36187500 | W15: ='Target Inputs'!Q5 -> 4 | X15: ='Target Inputs'!R5 -> 15 | Y15: ='Target Inputs'!S5 -> 0.12 | Z15: ='Target Inputs'!T5 -> 50000000 | AA15: ='Target Inputs'!U5 -> 60000000 | AB15: =W15*'VSL and Injuries'!$B$4+X15*'VSL and Injuries'!$B$4*Y15+Z15*'VSL and Injuries'!$K$6 -> 134110000 | AC15: =AA15*'VSL and Injuries'!$K$6*$AG15*E15 -> 43470000 | AD15: =AB15+AC15 -> 177580000 | AE15: S017; S029; S031 | AF15: Assumes partial rerouting/storage capability in low and central cases; no system-specific topology is embedded. | AG15: =IFERROR(INDEX('Duration Factors'!$G$4:$G$12,MATCH($B15,'Duration Factors'!$A$4:$A$12,0)),"") -> 1
A16: Pump Station | B16: 3 days | C16: 72 | D16: =IFERROR(INDEX('Duration Factors'!$C$4:$C$12,MATCH($B16,'Duration Factors'!$A$4:$A$12,0)),"") -> 3 | E16: =IFERROR(INDEX('Duration Factors'!$D$4:$D$12,MATCH($B16,'Duration Factors'!$A$4:$A$12,0)),"") -> 0.9 | F16: Low | G16: ='Target Inputs'!G5 -> 0 | H16: ='Target Inputs'!H5 -> 1 | I16: ='Target Inputs'!I5 -> 0.02 | J16: ='Target Inputs'!J5 -> 1000000 | K16: ='Target Inputs'!K5 -> 3000000 | L16: =G16*'VSL and Injuries'!$B$4+H16*'VSL and Injuries'!$B$4*I16+J16*'VSL and Injuries'!$K$6 -> 1319000 | M16: =K16*'VSL and Injuries'!$K$6*$AG16*E16 -> 11178000 | N16: =L16+M16 -> 12497000 | O16: ='Target Inputs'!L5 -> 1 | P16: ='Target Inputs'!M5 -> 4 | Q16: ='Target Inputs'!N5 -> 0.05 | R16: ='Target Inputs'!O5 -> 8000000 | S16: ='Target Inputs'!P5 -> 15000000 | T16: =O16*'VSL and Injuries'!$B$4+P16*'VSL and Injuries'!$B$4*Q16+R16*'VSL and Injuries'!$K$6 -> 25320000 | U16: =S16*'VSL and Injuries'!$K$6*$AG16*E16 -> 55890000 | V16: =T16+U16 -> 81210000 | W16: ='Target Inputs'!Q5 -> 4 | X16: ='Target Inputs'!R5 -> 15 | Y16: ='Target Inputs'!S5 -> 0.12 | Z16: ='Target Inputs'!T5 -> 50000000 | AA16: ='Target Inputs'!U5 -> 60000000 | AB16: =W16*'VSL and Injuries'!$B$4+X16*'VSL and Injuries'!$B$4*Y16+Z16*'VSL and Injuries'!$K$6 -> 134110000 | AC16: =AA16*'VSL and Injuries'!$K$6*$AG16*E16 -> 223560000 | AD16: =AB16+AC16 -> 357670000 | AE16: S017; S029; S031 | AF16: Assumes partial rerouting/storage capability in low and central cases; no system-specific topology is embedded. | AG16: =IFERROR(INDEX('Duration Factors'!$G$4:$G$12,MATCH($B16,'Duration Factors'!$A$4:$A$12,0)),"") -> 4
A17: Pump Station | B17: 7 days | C17: 168 | D17: =IFERROR(INDEX('Duration Factors'!$C$4:$C$12,MATCH($B17,'Duration Factors'!$A$4:$A$12,0)),"") -> 7 | E17: =IFERROR(INDEX('Duration Factors'!$D$4:$D$12,MATCH($B17,'Duration Factors'!$A$4:$A$12,0)),"") -> 1 | F17: Low | G17: ='Target Inputs'!G5 -> 0 | H17: ='Target Inputs'!H5 -> 1 | I17: ='Target Inputs'!I5 -> 0.02 | J17: ='Target Inputs'!J5 -> 1000000 | K17: ='Target Inputs'!K5 -> 3000000 | L17: =G17*'VSL and Injuries'!$B$4+H17*'VSL and Injuries'!$B$4*I17+J17*'VSL and Injuries'!$K$6 -> 1319000 | M17: =K17*'VSL and Injuries'!$K$6*$AG17*E17 -> 27945000 | N17: =L17+M17 -> 29264000 | O17: ='Target Inputs'!L5 -> 1 | P17: ='Target Inputs'!M5 -> 4 | Q17: ='Target Inputs'!N5 -> 0.05 | R17: ='Target Inputs'!O5 -> 8000000 | S17: ='Target Inputs'!P5 -> 15000000 | T17: =O17*'VSL and Injuries'!$B$4+P17*'VSL and Injuries'!$B$4*Q17+R17*'VSL and Injuries'!$K$6 -> 25320000 | U17: =S17*'VSL and Injuries'!$K$6*$AG17*E17 -> 139725000 | V17: =T17+U17 -> 165045000 | W17: ='Target Inputs'!Q5 -> 4 | X17: ='Target Inputs'!R5 -> 15 | Y17: ='Target Inputs'!S5 -> 0.12 | Z17: ='Target Inputs'!T5 -> 50000000 | AA17: ='Target Inputs'!U5 -> 60000000 | AB17: =W17*'VSL and Injuries'!$B$4+X17*'VSL and Injuries'!$B$4*Y17+Z17*'VSL and Injuries'!$K$6 -> 134110000 | AC17: =AA17*'VSL and Injuries'!$K$6*$AG17*E17 -> 558900000 | AD17: =AB17+AC17 -> 693010000 | AE17: S017; S029; S031 | AF17: Assumes partial rerouting/storage capability in low and central cases; no system-specific topology is embedded. | AG17: =IFERROR(INDEX('Duration Factors'!$G$4:$G$12,MATCH($B17,'Duration Factors'!$A$4:$A$12,0)),"") -> 9
A18: Pump Station | B18: 14 days | C18: 336 | D18: =IFERROR(INDEX('Duration Factors'!$C$4:$C$12,MATCH($B18,'Duration Factors'!$A$4:$A$12,0)),"") -> 14 | E18: =IFERROR(INDEX('Duration Factors'!$D$4:$D$12,MATCH($B18,'Duration Factors'!$A$4:$A$12,0)),"") -> 1.1 | F18: Low | G18: ='Target Inputs'!G5 -> 0 | H18: ='Target Inputs'!H5 -> 1 | I18: ='Target Inputs'!I5 -> 0.02 | J18: ='Target Inputs'!J5 -> 1000000 | K18: ='Target Inputs'!K5 -> 3000000 | L18: =G18*'VSL and Injuries'!$B$4+H18*'VSL and Injuries'!$B$4*I18+J18*'VSL and Injuries'!$K$6 -> 1319000 | M18: =K18*'VSL and Injuries'!$K$6*$AG18*E18 -> 58063500 | N18: =L18+M18 -> 59382500 | O18: ='Target Inputs'!L5 -> 1 | P18: ='Target Inputs'!M5 -> 4 | Q18: ='Target Inputs'!N5 -> 0.05 | R18: ='Target Inputs'!O5 -> 8000000 | S18: ='Target Inputs'!P5 -> 15000000 | T18: =O18*'VSL and Injuries'!$B$4+P18*'VSL and Injuries'!$B$4*Q18+R18*'VSL and Injuries'!$K$6 -> 25320000 | U18: =S18*'VSL and Injuries'!$K$6*$AG18*E18 -> 290317500 | V18: =T18+U18 -> 315637500 | W18: ='Target Inputs'!Q5 -> 4 | X18: ='Target Inputs'!R5 -> 15 | Y18: ='Target Inputs'!S5 -> 0.12 | Z18: ='Target Inputs'!T5 -> 50000000 | AA18: ='Target Inputs'!U5 -> 60000000 | AB18: =W18*'VSL and Injuries'!$B$4+X18*'VSL and Injuries'!$B$4*Y18+Z18*'VSL and Injuries'!$K$6 -> 134110000 | AC18: =AA18*'VSL and Injuries'!$K$6*$AG18*E18 -> 1161270000 | AD18: =AB18+AC18 -> 1295380000 | AE18: S017; S029; S031 | AF18: Assumes partial rerouting/storage capability in low and central cases; no system-specific topology is embedded. | AG18: =IFERROR(INDEX('Duration Factors'!$G$4:$G$12,MATCH($B18,'Duration Factors'!$A$4:$A$12,0)),"") -> 17
A19: Pump Station | B19: 30 days | C19: 720 | D19: =IFERROR(INDEX('Duration Factors'!$C$4:$C$12,MATCH($B19,'Duration Factors'!$A$4:$A$12,0)),"") -> 30 | E19: =IFERROR(INDEX('Duration Factors'!$D$4:$D$12,MATCH($B19,'Duration Factors'!$A$4:$A$12,0)),"") -> 1.2 | F19: Low | G19: ='Target Inputs'!G5 -> 0 | H19: ='Target Inputs'!H5 -> 1 | I19: ='Target Inputs'!I5 -> 0.02 | J19: ='Target Inputs'!J5 -> 1000000 | K19: ='Target Inputs'!K5 -> 3000000 | L19: =G19*'VSL and Injuries'!$B$4+H19*'VSL and Injuries'!$B$4*I19+J19*'VSL and Injuries'!$K$6 -> 1319000 | M19: =K19*'VSL and Injuries'!$K$6*$AG19*E19 -> 130410000 | N19: =L19+M19 -> 131729000 | O19: ='Target Inputs'!L5 -> 1 | P19: ='Target Inputs'!M5 -> 4 | Q19: ='Target Inputs'!N5 -> 0.05 | R19: ='Target Inputs'!O5 -> 8000000 | S19: ='Target Inputs'!P5 -> 15000000 | T19: =O19*'VSL and Injuries'!$B$4+P19*'VSL and Injuries'!$B$4*Q19+R19*'VSL and Injuries'!$K$6 -> 25320000 | U19: =S19*'VSL and Injuries'!$K$6*$AG19*E19 -> 652050000 | V19: =T19+U19 -> 677370000 | W19: ='Target Inputs'!Q5 -> 4 | X19: ='Target Inputs'!R5 -> 15 | Y19: ='Target Inputs'!S5 -> 0.12 | Z19: ='Target Inputs'!T5 -> 50000000 | AA19: ='Target Inputs'!U5 -> 60000000 | AB19: =W19*'VSL and Injuries'!$B$4+X19*'VSL and Injuries'!$B$4*Y19+Z19*'VSL and Injuries'!$K$6 -> 134110000 | AC19: =AA19*'VSL and Injuries'!$K$6*$AG19*E19 -> 2608200000 | AD19: =AB19+AC19 -> 2742310000 | AE19: S017; S029; S031 | AF19: Assumes partial rerouting/storage capability in low and central cases; no system-specific topology is embedded. | AG19: =IFERROR(INDEX('Duration Factors'!$G$4:$G$12,MATCH($B19,'Duration Factors'!$A$4:$A$12,0)),"") -> 35
A20: Pump Station | B20: 45 days | C20: 1080 | D20: =IFERROR(INDEX('Duration Factors'!$C$4:$C$12,MATCH($B20,'Duration Factors'!$A$4:$A$12,0)),"") -> 45 | E20: =IFERROR(INDEX('Duration Factors'!$D$4:$D$12,MATCH($B20,'Duration Factors'!$A$4:$A$12,0)),"") -> 1.3 | F20: Low | G20: ='Target Inputs'!G5 -> 0 | H20: ='Target Inputs'!H5 -> 1 | I20: ='Target Inputs'!I5 -> 0.02 | J20: ='Target Inputs'!J5 -> 1000000 | K20: ='Target Inputs'!K5 -> 3000000 | L20: =G20*'VSL and Injuries'!$B$4+H20*'VSL and Injuries'!$B$4*I20+J20*'VSL and Injuries'!$K$6 -> 1319000 | M20: =K20*'VSL and Injuries'!$K$6*$AG20*E20 -> 222007500 | N20: =L20+M20 -> 223326500 | O20: ='Target Inputs'!L5 -> 1 | P20: ='Target Inputs'!M5 -> 4 | Q20: ='Target Inputs'!N5 -> 0.05 | R20: ='Target Inputs'!O5 -> 8000000 | S20: ='Target Inputs'!P5 -> 15000000 | T20: =O20*'VSL and Injuries'!$B$4+P20*'VSL and Injuries'!$B$4*Q20+R20*'VSL and Injuries'!$K$6 -> 25320000 | U20: =S20*'VSL and Injuries'!$K$6*$AG20*E20 -> 1110037500 | V20: =T20+U20 -> 1135357500 | W20: ='Target Inputs'!Q5 -> 4 | X20: ='Target Inputs'!R5 -> 15 | Y20: ='Target Inputs'!S5 -> 0.12 | Z20: ='Target Inputs'!T5 -> 50000000 | AA20: ='Target Inputs'!U5 -> 60000000 | AB20: =W20*'VSL and Injuries'!$B$4+X20*'VSL and Injuries'!$B$4*Y20+Z20*'VSL and Injuries'!$K$6 -> 134110000 | AC20: =AA20*'VSL and Injuries'!$K$6*$AG20*E20 -> 4440150000 | AD20: =AB20+AC20 -> 4574260000 | AE20: S017; S029; S031 | AF20: Assumes partial rerouting/storage capability in low and central cases; no system-specific topology is embedded. | AG20: =IFERROR(INDEX('Duration Factors'!$G$4:$G$12,MATCH($B20,'Duration Factors'!$A$4:$A$12,0)),"") -> 55
A21: Pump Station | B21: 90 days | C21: 2160 | D21: =IFERROR(INDEX('Duration Factors'!$C$4:$C$12,MATCH($B21,'Duration Factors'!$A$4:$A$12,0)),"") -> 90 | E21: =IFERROR(INDEX('Duration Factors'!$D$4:$D$12,MATCH($B21,'Duration Factors'!$A$4:$A$12,0)),"") -> 1.4 | F21: Low | G21: ='Target Inputs'!G5 -> 0 | H21: ='Target Inputs'!H5 -> 1 | I21: ='Target Inputs'!I5 -> 0.02 | J21: ='Target Inputs'!J5 -> 1000000 | K21: ='Target Inputs'!K5 -> 3000000 | L21: =G21*'VSL and Injuries'!$B$4+H21*'VSL and Injuries'!$B$4*I21+J21*'VSL and Injuries'!$K$6 -> 1319000 | M21: =K21*'VSL and Injuries'!$K$6*$AG21*E21 -> 478170000 | N21: =L21+M21 -> 479489000 | O21: ='Target Inputs'!L5 -> 1 | P21: ='Target Inputs'!M5 -> 4 | Q21: ='Target Inputs'!N5 -> 0.05 | R21: ='Target Inputs'!O5 -> 8000000 | S21: ='Target Inputs'!P5 -> 15000000 | T21: =O21*'VSL and Injuries'!$B$4+P21*'VSL and Injuries'!$B$4*Q21+R21*'VSL and Injuries'!$K$6 -> 25320000 | U21: =S21*'VSL and Injuries'!$K$6*$AG21*E21 -> 2390850000 | V21: =T21+U21 -> 2416170000 | W21: ='Target Inputs'!Q5 -> 4 | X21: ='Target Inputs'!R5 -> 15 | Y21: ='Target Inputs'!S5 -> 0.12 | Z21: ='Target Inputs'!T5 -> 50000000 | AA21: ='Target Inputs'!U5 -> 60000000 | AB21: =W21*'VSL and Injuries'!$B$4+X21*'VSL and Injuries'!$B$4*Y21+Z21*'VSL and Injuries'!$K$6 -> 134110000 | AC21: =AA21*'VSL and Injuries'!$K$6*$AG21*E21 -> 9563400000 | AD21: =AB21+AC21 -> 9697510000 | AE21: S017; S029; S031 | AF21: Assumes partial rerouting/storage capability in low and central cases; no system-specific topology is embedded. | AG21: =IFERROR(INDEX('Duration Factors'!$G$4:$G$12,MATCH($B21,'Duration Factors'!$A$4:$A$12,0)),"") -> 110
A22: Compressor Station | B22: 4 hours | C22: 4 | D22: =IFERROR(INDEX('Duration Factors'!$C$4:$C$12,MATCH($B22,'Duration Factors'!$A$4:$A$12,0)),"") -> 0.16666667 | E22: =IFERROR(INDEX('Duration Factors'!$D$4:$D$12,MATCH($B22,'Duration Factors'!$A$4:$A$12,0)),"") -> 0.35 | F22: Low | G22: ='Target Inputs'!G6 -> 0 | H22: ='Target Inputs'!H6 -> 1 | I22: ='Target Inputs'!I6 -> 0.02 | J22: ='Target Inputs'!J6 -> 2000000 | K22: ='Target Inputs'!K6 -> 4000000 | L22: =G22*'VSL and Injuries'!$B$4+H22*'VSL and Injuries'!$B$4*I22+J22*'VSL and Injuries'!$K$6 -> 2354000 | M22: =K22*'VSL and Injuries'!$K$6*$AG22*E22 -> 241500 | N22: =L22+M22 -> 2595500 | O22: ='Target Inputs'!L6 -> 1 | P22: ='Target Inputs'!M6 -> 5 | Q22: ='Target Inputs'!N6 -> 0.05 | R22: ='Target Inputs'!O6 -> 12000000 | S22: ='Target Inputs'!P6 -> 20000000 | T22: =O22*'VSL and Injuries'!$B$4+P22*'VSL and Injuries'!$B$4*Q22+R22*'VSL and Injuries'!$K$6 -> 30170000 | U22: =S22*'VSL and Injuries'!$K$6*$AG22*E22 -> 1207500 | V22: =T22+U22 -> 31377500 | W22: ='Target Inputs'!Q6 -> 5 | X22: ='Target Inputs'!R6 -> 20 | Y22: ='Target Inputs'!S6 -> 0.12 | Z22: ='Target Inputs'!T6 -> 75000000 | AA22: ='Target Inputs'!U6 -> 80000000 | AB22: =W22*'VSL and Injuries'!$B$4+X22*'VSL and Injuries'!$B$4*Y22+Z22*'VSL and Injuries'!$K$6 -> 182705000 | AC22: =AA22*'VSL and Injuries'!$K$6*$AG22*E22 -> 4830000 | AD22: =AB22+AC22 -> 187535000 | AE22: S017; S029; S031 | AF22: Indirect loss depends on season, storage, network redundancy, affected customers, and gas-fired generation exposure. | AG22: =IFERROR(INDEX('Duration Factors'!$G$4:$G$12,MATCH($B22,'Duration Factors'!$A$4:$A$12,0)),"") -> 0.16666667
A23: Compressor Station | B23: 12 hours | C23: 12 | D23: =IFERROR(INDEX('Duration Factors'!$C$4:$C$12,MATCH($B23,'Duration Factors'!$A$4:$A$12,0)),"") -> 0.5 | E23: =IFERROR(INDEX('Duration Factors'!$D$4:$D$12,MATCH($B23,'Duration Factors'!$A$4:$A$12,0)),"") -> 0.55 | F23: Low | G23: ='Target Inputs'!G6 -> 0 | H23: ='Target Inputs'!H6 -> 1 | I23: ='Target Inputs'!I6 -> 0.02 | J23: ='Target Inputs'!J6 -> 2000000 | K23: ='Target Inputs'!K6 -> 4000000 | L23: =G23*'VSL and Injuries'!$B$4+H23*'VSL and Injuries'!$B$4*I23+J23*'VSL and Injuries'!$K$6 -> 2354000 | M23: =K23*'VSL and Injuries'!$K$6*$AG23*E23 -> 1138500 | N23: =L23+M23 -> 3492500 | O23: ='Target Inputs'!L6 -> 1 | P23: ='Target Inputs'!M6 -> 5 | Q23: ='Target Inputs'!N6 -> 0.05 | R23: ='Target Inputs'!O6 -> 12000000 | S23: ='Target Inputs'!P6 -> 20000000 | T23: =O23*'VSL and Injuries'!$B$4+P23*'VSL and Injuries'!$B$4*Q23+R23*'VSL and Injuries'!$K$6 -> 30170000 | U23: =S23*'VSL and Injuries'!$K$6*$AG23*E23 -> 5692500 | V23: =T23+U23 -> 35862500 | W23: ='Target Inputs'!Q6 -> 5 | X23: ='Target Inputs'!R6 -> 20 | Y23: ='Target Inputs'!S6 -> 0.12 | Z23: ='Target Inputs'!T6 -> 75000000 | AA23: ='Target Inputs'!U6 -> 80000000 | AB23: =W23*'VSL and Injuries'!$B$4+X23*'VSL and Injuries'!$B$4*Y23+Z23*'VSL and Injuries'!$K$6 -> 182705000 | AC23: =AA23*'VSL and Injuries'!$K$6*$AG23*E23 -> 22770000 | AD23: =AB23+AC23 -> 205475000 | AE23: S017; S029; S031 | AF23: Indirect loss depends on season, storage, network redundancy, affected customers, and gas-fired generation exposure. | AG23: =IFERROR(INDEX('Duration Factors'!$G$4:$G$12,MATCH($B23,'Duration Factors'!$A$4:$A$12,0)),"") -> 0.5
A24: Compressor Station | B24: 1 day | C24: 24 | D24: =IFERROR(INDEX('Duration Factors'!$C$4:$C$12,MATCH($B24,'Duration Factors'!$A$4:$A$12,0)),"") -> 1 | E24: =IFERROR(INDEX('Duration Factors'!$D$4:$D$12,MATCH($B24,'Duration Factors'!$A$4:$A$12,0)),"") -> 0.7 | F24: Low | G24: ='Target Inputs'!G6 -> 0 | H24: ='Target Inputs'!H6 -> 1 | I24: ='Target Inputs'!I6 -> 0.02 | J24: ='Target Inputs'!J6 -> 2000000 | K24: ='Target Inputs'!K6 -> 4000000 | L24: =G24*'VSL and Injuries'!$B$4+H24*'VSL and Injuries'!$B$4*I24+J24*'VSL and Injuries'!$K$6 -> 2354000 | M24: =K24*'VSL and Injuries'!$K$6*$AG24*E24 -> 2898000 | N24: =L24+M24 -> 5252000 | O24: ='Target Inputs'!L6 -> 1 | P24: ='Target Inputs'!M6 -> 5 | Q24: ='Target Inputs'!N6 -> 0.05 | R24: ='Target Inputs'!O6 -> 12000000 | S24: ='Target Inputs'!P6 -> 20000000 | T24: =O24*'VSL and Injuries'!$B$4+P24*'VSL and Injuries'!$B$4*Q24+R24*'VSL and Injuries'!$K$6 -> 30170000 | U24: =S24*'VSL and Injuries'!$K$6*$AG24*E24 -> 14490000 | V24: =T24+U24 -> 44660000 | W24: ='Target Inputs'!Q6 -> 5 | X24: ='Target Inputs'!R6 -> 20 | Y24: ='Target Inputs'!S6 -> 0.12 | Z24: ='Target Inputs'!T6 -> 75000000 | AA24: ='Target Inputs'!U6 -> 80000000 | AB24: =W24*'VSL and Injuries'!$B$4+X24*'VSL and Injuries'!$B$4*Y24+Z24*'VSL and Injuries'!$K$6 -> 182705000 | AC24: =AA24*'VSL and Injuries'!$K$6*$AG24*E24 -> 57960000 | AD24: =AB24+AC24 -> 240665000 | AE24: S017; S029; S031 | AF24: Indirect loss depends on season, storage, network redundancy, affected customers, and gas-fired generation exposure. | AG24: =IFERROR(INDEX('Duration Factors'!$G$4:$G$12,MATCH($B24,'Duration Factors'!$A$4:$A$12,0)),"") -> 1
A25: Compressor Station | B25: 3 days | C25: 72 | D25: =IFERROR(INDEX('Duration Factors'!$C$4:$C$12,MATCH($B25,'Duration Factors'!$A$4:$A$12,0)),"") -> 3 | E25: =IFERROR(INDEX('Duration Factors'!$D$4:$D$12,MATCH($B25,'Duration Factors'!$A$4:$A$12,0)),"") -> 0.9 | F25: Low | G25: ='Target Inputs'!G6 -> 0 | H25: ='Target Inputs'!H6 -> 1 | I25: ='Target Inputs'!I6 -> 0.02 | J25: ='Target Inputs'!J6 -> 2000000 | K25: ='Target Inputs'!K6 -> 4000000 | L25: =G25*'VSL and Injuries'!$B$4+H25*'VSL and Injuries'!$B$4*I25+J25*'VSL and Injuries'!$K$6 -> 2354000 | M25: =K25*'VSL and Injuries'!$K$6*$AG25*E25 -> 14904000 | N25: =L25+M25 -> 17258000 | O25: ='Target Inputs'!L6 -> 1 | P25: ='Target Inputs'!M6 -> 5 | Q25: ='Target Inputs'!N6 -> 0.05 | R25: ='Target Inputs'!O6 -> 12000000 | S25: ='Target Inputs'!P6 -> 20000000 | T25: =O25*'VSL and Injuries'!$B$4+P25*'VSL and Injuries'!$B$4*Q25+R25*'VSL and Injuries'!$K$6 -> 30170000 | U25: =S25*'VSL and Injuries'!$K$6*$AG25*E25 -> 74520000 | V25: =T25+U25 -> 104690000 | W25: ='Target Inputs'!Q6 -> 5 | X25: ='Target Inputs'!R6 -> 20 | Y25: ='Target Inputs'!S6 -> 0.12 | Z25: ='Target Inputs'!T6 -> 75000000 | AA25: ='Target Inputs'!U6 -> 80000000 | AB25: =W25*'VSL and Injuries'!$B$4+X25*'VSL and Injuries'!$B$4*Y25+Z25*'VSL and Injuries'!$K$6 -> 182705000 | AC25: =AA25*'VSL and Injuries'!$K$6*$AG25*E25 -> 298080000 | AD25: =AB25+AC25 -> 480785000 | AE25: S017; S029; S031 | AF25: Indirect loss depends on season, storage, network redundancy, affected customers, and gas-fired generation exposure. | AG25: =IFERROR(INDEX('Duration Factors'!$G$4:$G$12,MATCH($B25,'Duration Factors'!$A$4:$A$12,0)),"") -> 4
A26: Compressor Station | B26: 7 days | C26: 168 | D26: =IFERROR(INDEX('Duration Factors'!$C$4:$C$12,MATCH($B26,'Duration Factors'!$A$4:$A$12,0)),"") -> 7 | E26: =IFERROR(INDEX('Duration Factors'!$D$4:$D$12,MATCH($B26,'Duration Factors'!$A$4:$A$12,0)),"") -> 1 | F26: Low | G26: ='Target Inputs'!G6 -> 0 | H26: ='Target Inputs'!H6 -> 1 | I26: ='Target Inputs'!I6 -> 0.02 | J26: ='Target Inputs'!J6 -> 2000000 | K26: ='Target Inputs'!K6 -> 4000000 | L26: =G26*'VSL and Injuries'!$B$4+H26*'VSL and Injuries'!$B$4*I26+J26*'VSL and Injuries'!$K$6 -> 2354000 | M26: =K26*'VSL and Injuries'!$K$6*$AG26*E26 -> 37260000 | N26: =L26+M26 -> 39614000 | O26: ='Target Inputs'!L6 -> 1 | P26: ='Target Inputs'!M6 -> 5 | Q26: ='Target Inputs'!N6 -> 0.05 | R26: ='Target Inputs'!O6 -> 12000000 | S26: ='Target Inputs'!P6 -> 20000000 | T26: =O26*'VSL and Injuries'!$B$4+P26*'VSL and Injuries'!$B$4*Q26+R26*'VSL and Injuries'!$K$6 -> 30170000 | U26: =S26*'VSL and Injuries'!$K$6*$AG26*E26 -> 186300000 | V26: =T26+U26 -> 216470000 | W26: ='Target Inputs'!Q6 -> 5 | X26: ='Target Inputs'!R6 -> 20 | Y26: ='Target Inputs'!S6 -> 0.12 | Z26: ='Target Inputs'!T6 -> 75000000 | AA26: ='Target Inputs'!U6 -> 80000000 | AB26: =W26*'VSL and Injuries'!$B$4+X26*'VSL and Injuries'!$B$4*Y26+Z26*'VSL and Injuries'!$K$6 -> 182705000 | AC26: =AA26*'VSL and Injuries'!$K$6*$AG26*E26 -> 745200000 | AD26: =AB26+AC26 -> 927905000 | AE26: S017; S029; S031 | AF26: Indirect loss depends on season, storage, network redundancy, affected customers, and gas-fired generation exposure. | AG26: =IFERROR(INDEX('Duration Factors'!$G$4:$G$12,MATCH($B26,'Duration Factors'!$A$4:$A$12,0)),"") -> 9
A27: Compressor Station | B27: 14 days | C27: 336 | D27: =IFERROR(INDEX('Duration Factors'!$C$4:$C$12,MATCH($B27,'Duration Factors'!$A$4:$A$12,0)),"") -> 14 | E27: =IFERROR(INDEX('Duration Factors'!$D$4:$D$12,MATCH($B27,'Duration Factors'!$A$4:$A$12,0)),"") -> 1.1 | F27: Low | G27: ='Target Inputs'!G6 -> 0 | H27: ='Target Inputs'!H6 -> 1 | I27: ='Target Inputs'!I6 -> 0.02 | J27: ='Target Inputs'!J6 -> 2000000 | K27: ='Target Inputs'!K6 -> 4000000 | L27: =G27*'VSL and Injuries'!$B$4+H27*'VSL and Injuries'!$B$4*I27+J27*'VSL and Injuries'!$K$6 -> 2354000 | M27: =K27*'VSL and Injuries'!$K$6*$AG27*E27 -> 77418000 | N27: =L27+M27 -> 79772000 | O27: ='Target Inputs'!L6 -> 1 | P27: ='Target Inputs'!M6 -> 5 | Q27: ='Target Inputs'!N6 -> 0.05 | R27: ='Target Inputs'!O6 -> 12000000 | S27: ='Target Inputs'!P6 -> 20000000 | T27: =O27*'VSL and Injuries'!$B$4+P27*'VSL and Injuries'!$B$4*Q27+R27*'VSL and Injuries'!$K$6 -> 30170000 | U27: =S27*'VSL and Injuries'!$K$6*$AG27*E27 -> 387090000 | V27: =T27+U27 -> 417260000 | W27: ='Target Inputs'!Q6 -> 5 | X27: ='Target Inputs'!R6 -> 20 | Y27: ='Target Inputs'!S6 -> 0.12 | Z27: ='Target Inputs'!T6 -> 75000000 | AA27: ='Target Inputs'!U6 -> 80000000 | AB27: =W27*'VSL and Injuries'!$B$4+X27*'VSL and Injuries'!$B$4*Y27+Z27*'VSL and Injuries'!$K$6 -> 182705000 | AC27: =AA27*'VSL and Injuries'!$K$6*$AG27*E27 -> 1548360000 | AD27: =AB27+AC27 -> 1731065000 | AE27: S017; S029; S031 | AF27: Indirect loss depends on season, storage, network redundancy, affected customers, and gas-fired generation exposure. | AG27: =IFERROR(INDEX('Duration Factors'!$G$4:$G$12,MATCH($B27,'Duration Factors'!$A$4:$A$12,0)),"") -> 17
A28: Compressor Station | B28: 30 days | C28: 720 | D28: =IFERROR(INDEX('Duration Factors'!$C$4:$C$12,MATCH($B28,'Duration Factors'!$A$4:$A$12,0)),"") -> 30 | E28: =IFERROR(INDEX('Duration Factors'!$D$4:$D$12,MATCH($B28,'Duration Factors'!$A$4:$A$12,0)),"") -> 1.2 | F28: Low | G28: ='Target Inputs'!G6 -> 0 | H28: ='Target Inputs'!H6 -> 1 | I28: ='Target Inputs'!I6 -> 0.02 | J28: ='Target Inputs'!J6 -> 2000000 | K28: ='Target Inputs'!K6 -> 4000000 | L28: =G28*'VSL and Injuries'!$B$4+H28*'VSL and Injuries'!$B$4*I28+J28*'VSL and Injuries'!$K$6 -> 2354000 | M28: =K28*'VSL and Injuries'!$K$6*$AG28*E28 -> 173880000 | N28: =L28+M28 -> 176234000 | O28: ='Target Inputs'!L6 -> 1 | P28: ='Target Inputs'!M6 -> 5 | Q28: ='Target Inputs'!N6 -> 0.05 | R28: ='Target Inputs'!O6 -> 12000000 | S28: ='Target Inputs'!P6 -> 20000000 | T28: =O28*'VSL and Injuries'!$B$4+P28*'VSL and Injuries'!$B$4*Q28+R28*'VSL and Injuries'!$K$6 -> 30170000 | U28: =S28*'VSL and Injuries'!$K$6*$AG28*E28 -> 869400000 | V28: =T28+U28 -> 899570000 | W28: ='Target Inputs'!Q6 -> 5 | X28: ='Target Inputs'!R6 -> 20 | Y28: ='Target Inputs'!S6 -> 0.12 | Z28: ='Target Inputs'!T6 -> 75000000 | AA28: ='Target Inputs'!U6 -> 80000000 | AB28: =W28*'VSL and Injuries'!$B$4+X28*'VSL and Injuries'!$B$4*Y28+Z28*'VSL and Injuries'!$K$6 -> 182705000 | AC28: =AA28*'VSL and Injuries'!$K$6*$AG28*E28 -> 3477600000 | AD28: =AB28+AC28 -> 3660305000 | AE28: S017; S029; S031 | AF28: Indirect loss depends on season, storage, network redundancy, affected customers, and gas-fired generation exposure. | AG28: =IFERROR(INDEX('Duration Factors'!$G$4:$G$12,MATCH($B28,'Duration Factors'!$A$4:$A$12,0)),"") -> 35
A29: Compressor Station | B29: 45 days | C29: 1080 | D29: =IFERROR(INDEX('Duration Factors'!$C$4:$C$12,MATCH($B29,'Duration Factors'!$A$4:$A$12,0)),"") -> 45 | E29: =IFERROR(INDEX('Duration Factors'!$D$4:$D$12,MATCH($B29,'Duration Factors'!$A$4:$A$12,0)),"") -> 1.3 | F29: Low | G29: ='Target Inputs'!G6 -> 0 | H29: ='Target Inputs'!H6 -> 1 | I29: ='Target Inputs'!I6 -> 0.02 | J29: ='Target Inputs'!J6 -> 2000000 | K29: ='Target Inputs'!K6 -> 4000000 | L29: =G29*'VSL and Injuries'!$B$4+H29*'VSL and Injuries'!$B$4*I29+J29*'VSL and Injuries'!$K$6 -> 2354000 | M29: =K29*'VSL and Injuries'!$K$6*$AG29*E29 -> 296010000 | N29: =L29+M29 -> 298364000 | O29: ='Target Inputs'!L6 -> 1 | P29: ='Target Inputs'!M6 -> 5 | Q29: ='Target Inputs'!N6 -> 0.05 | R29: ='Target Inputs'!O6 -> 12000000 | S29: ='Target Inputs'!P6 -> 20000000 | T29: =O29*'VSL and Injuries'!$B$4+P29*'VSL and Injuries'!$B$4*Q29+R29*'VSL and Injuries'!$K$6 -> 30170000 | U29: =S29*'VSL and Injuries'!$K$6*$AG29*E29 -> 1480050000 | V29: =T29+U29 -> 1510220000 | W29: ='Target Inputs'!Q6 -> 5 | X29: ='Target Inputs'!R6 -> 20 | Y29: ='Target Inputs'!S6 -> 0.12 | Z29: ='Target Inputs'!T6 -> 75000000 | AA29: ='Target Inputs'!U6 -> 80000000 | AB29: =W29*'VSL and Injuries'!$B$4+X29*'VSL and Injuries'!$B$4*Y29+Z29*'VSL and Injuries'!$K$6 -> 182705000 | AC29: =AA29*'VSL and Injuries'!$K$6*$AG29*E29 -> 5920200000 | AD29: =AB29+AC29 -> 6102905000 | AE29: S017; S029; S031 | AF29: Indirect loss depends on season, storage, network redundancy, affected customers, and gas-fired generation exposure. | AG29: =IFERROR(INDEX('Duration Factors'!$G$4:$G$12,MATCH($B29,'Duration Factors'!$A$4:$A$12,0)),"") -> 55
A30: Compressor Station | B30: 90 days | C30: 2160 | D30: =IFERROR(INDEX('Duration Factors'!$C$4:$C$12,MATCH($B30,'Duration Factors'!$A$4:$A$12,0)),"") -> 90 | E30: =IFERROR(INDEX('Duration Factors'!$D$4:$D$12,MATCH($B30,'Duration Factors'!$A$4:$A$12,0)),"") -> 1.4 | F30: Low | G30: ='Target Inputs'!G6 -> 0 | H30: ='Target Inputs'!H6 -> 1 | I30: ='Target Inputs'!I6 -> 0.02 | J30: ='Target Inputs'!J6 -> 2000000 | K30: ='Target Inputs'!K6 -> 4000000 | L30: =G30*'VSL and Injuries'!$B$4+H30*'VSL and Injuries'!$B$4*I30+J30*'VSL and Injuries'!$K$6 -> 2354000 | M30: =K30*'VSL and Injuries'!$K$6*$AG30*E30 -> 637560000 | N30: =L30+M30 -> 639914000 | O30: ='Target Inputs'!L6 -> 1 | P30: ='Target Inputs'!M6 -> 5 | Q30: ='Target Inputs'!N6 -> 0.05 | R30: ='Target Inputs'!O6 -> 12000000 | S30: ='Target Inputs'!P6 -> 20000000 | T30: =O30*'VSL and Injuries'!$B$4+P30*'VSL and Injuries'!$B$4*Q30+R30*'VSL and Injuries'!$K$6 -> 30170000 | U30: =S30*'VSL and Injuries'!$K$6*$AG30*E30 -> 3187800000 | V30: =T30+U30 -> 3217970000 | W30: ='Target Inputs'!Q6 -> 5 | X30: ='Target Inputs'!R6 -> 20 | Y30: ='Target Inputs'!S6 -> 0.12 | Z30: ='Target Inputs'!T6 -> 75000000 | AA30: ='Target Inputs'!U6 -> 80000000 | AB30: =W30*'VSL and Injuries'!$B$4+X30*'VSL and Injuries'!$B$4*Y30+Z30*'VSL and Injuries'!$K$6 -> 182705000 | AC30: =AA30*'VSL and Injuries'!$K$6*$AG30*E30 -> 12751200000 | AD30: =AB30+AC30 -> 12933905000 | AE30: S017; S029; S031 | AF30: Indirect loss depends on season, storage, network redundancy, affected customers, and gas-fired generation exposure. | AG30: =IFERROR(INDEX('Duration Factors'!$G$4:$G$12,MATCH($B30,'Duration Factors'!$A$4:$A$12,0)),"") -> 110
A31: Airport Terminal | B31: 4 hours | C31: 4 | D31: =IFERROR(INDEX('Duration Factors'!$C$4:$C$12,MATCH($B31,'Duration Factors'!$A$4:$A$12,0)),"") -> 0.16666667 | E31: =IFERROR(INDEX('Duration Factors'!$D$4:$D$12,MATCH($B31,'Duration Factors'!$A$4:$A$12,0)),"") -> 0.35 | F31: Moderate-Low | G31: ='Target Inputs'!G7 -> 0 | H31: ='Target Inputs'!H7 -> 5 | I31: ='Target Inputs'!I7 -> 0.025 | J31: ='Target Inputs'!J7 -> 25000000 | K31: ='Target Inputs'!K7 -> 5000000 | L31: =G31*'VSL and Injuries'!$B$4+H31*'VSL and Injuries'!$B$4*I31+J31*'VSL and Injuries'!$K$6 -> 27650000 | M31: =K31*'VSL and Injuries'!$K$6*$AG31*E31 -> 301875 | N31: =L31+M31 -> 27951875 | O31: ='Target Inputs'!L7 -> 5 | P31: ='Target Inputs'!M7 -> 50 | Q31: ='Target Inputs'!N7 -> 0.05 | R31: ='Target Inputs'!O7 -> 200000000 | S31: ='Target Inputs'!P7 -> 40000000 | T31: =O31*'VSL and Injuries'!$B$4+P31*'VSL and Injuries'!$B$4*Q31+R31*'VSL and Injuries'!$K$6 -> 313500000 | U31: =S31*'VSL and Injuries'!$K$6*$AG31*E31 -> 2415000 | V31: =T31+U31 -> 315915000 | W31: ='Target Inputs'!Q7 -> 30 | X31: ='Target Inputs'!R7 -> 250 | Y31: ='Target Inputs'!S7 -> 0.12 | Z31: ='Target Inputs'!T7 -> 1000000000 | AA31: ='Target Inputs'!U7 -> 200000000 | AB31: =W31*'VSL and Injuries'!$B$4+X31*'VSL and Injuries'!$B$4*Y31+Z31*'VSL and Injuries'!$K$6 -> 1887000000 | AC31: =AA31*'VSL and Injuries'!$K$6*$AG31*E31 -> 12075000 | AD31: =AB31+AC31 -> 1899075000 | AE31: S007; S019; S032; S033 | AF31: Daily indirect loss includes displaced aviation activity, passenger delay, airport concessions, air cargo, and visitor effects; not airport-specific. | AG31: =IFERROR(INDEX('Duration Factors'!$G$4:$G$12,MATCH($B31,'Duration Factors'!$A$4:$A$12,0)),"") -> 0.16666667
A32: Airport Terminal | B32: 12 hours | C32: 12 | D32: =IFERROR(INDEX('Duration Factors'!$C$4:$C$12,MATCH($B32,'Duration Factors'!$A$4:$A$12,0)),"") -> 0.5 | E32: =IFERROR(INDEX('Duration Factors'!$D$4:$D$12,MATCH($B32,'Duration Factors'!$A$4:$A$12,0)),"") -> 0.55 | F32: Moderate-Low | G32: ='Target Inputs'!G7 -> 0 | H32: ='Target Inputs'!H7 -> 5 | I32: ='Target Inputs'!I7 -> 0.025 | J32: ='Target Inputs'!J7 -> 25000000 | K32: ='Target Inputs'!K7 -> 5000000 | L32: =G32*'VSL and Injuries'!$B$4+H32*'VSL and Injuries'!$B$4*I32+J32*'VSL and Injuries'!$K$6 -> 27650000 | M32: =K32*'VSL and Injuries'!$K$6*$AG32*E32 -> 1423125 | N32: =L32+M32 -> 29073125 | O32: ='Target Inputs'!L7 -> 5 | P32: ='Target Inputs'!M7 -> 50 | Q32: ='Target Inputs'!N7 -> 0.05 | R32: ='Target Inputs'!O7 -> 200000000 | S32: ='Target Inputs'!P7 -> 40000000 | T32: =O32*'VSL and Injuries'!$B$4+P32*'VSL and Injuries'!$B$4*Q32+R32*'VSL and Injuries'!$K$6 -> 313500000 | U32: =S32*'VSL and Injuries'!$K$6*$AG32*E32 -> 11385000 | V32: =T32+U32 -> 324885000 | W32: ='Target Inputs'!Q7 -> 30 | X32: ='Target Inputs'!R7 -> 250 | Y32: ='Target Inputs'!S7 -> 0.12 | Z32: ='Target Inputs'!T7 -> 1000000000 | AA32: ='Target Inputs'!U7 -> 200000000 | AB32: =W32*'VSL and Injuries'!$B$4+X32*'VSL and Injuries'!$B$4*Y32+Z32*'VSL and Injuries'!$K$6 -> 1887000000 | AC32: =AA32*'VSL and Injuries'!$K$6*$AG32*E32 -> 56925000 | AD32: =AB32+AC32 -> 1943925000 | AE32: S007; S019; S032; S033 | AF32: Daily indirect loss includes displaced aviation activity, passenger delay, airport concessions, air cargo, and visitor effects; not airport-specific. | AG32: =IFERROR(INDEX('Duration Factors'!$G$4:$G$12,MATCH($B32,'Duration Factors'!$A$4:$A$12,0)),"") -> 0.5
A33: Airport Terminal | B33: 1 day | C33: 24 | D33: =IFERROR(INDEX('Duration Factors'!$C$4:$C$12,MATCH($B33,'Duration Factors'!$A$4:$A$12,0)),"") -> 1 | E33: =IFERROR(INDEX('Duration Factors'!$D$4:$D$12,MATCH($B33,'Duration Factors'!$A$4:$A$12,0)),"") -> 0.7 | F33: Moderate-Low | G33: ='Target Inputs'!G7 -> 0 | H33: ='Target Inputs'!H7 -> 5 | I33: ='Target Inputs'!I7 -> 0.025 | J33: ='Target Inputs'!J7 -> 25000000 | K33: ='Target Inputs'!K7 -> 5000000 | L33: =G33*'VSL and Injuries'!$B$4+H33*'VSL and Injuries'!$B$4*I33+J33*'VSL and Injuries'!$K$6 -> 27650000 | M33: =K33*'VSL and Injuries'!$K$6*$AG33*E33 -> 3622500 | N33: =L33+M33 -> 31272500 | O33: ='Target Inputs'!L7 -> 5 | P33: ='Target Inputs'!M7 -> 50 | Q33: ='Target Inputs'!N7 -> 0.05 | R33: ='Target Inputs'!O7 -> 200000000 | S33: ='Target Inputs'!P7 -> 40000000 | T33: =O33*'VSL and Injuries'!$B$4+P33*'VSL and Injuries'!$B$4*Q33+R33*'VSL and Injuries'!$K$6 -> 313500000 | U33: =S33*'VSL and Injuries'!$K$6*$AG33*E33 -> 28980000 | V33: =T33+U33 -> 342480000 | W33: ='Target Inputs'!Q7 -> 30 | X33: ='Target Inputs'!R7 -> 250 | Y33: ='Target Inputs'!S7 -> 0.12 | Z33: ='Target Inputs'!T7 -> 1000000000 | AA33: ='Target Inputs'!U7 -> 200000000 | AB33: =W33*'VSL and Injuries'!$B$4+X33*'VSL and Injuries'!$B$4*Y33+Z33*'VSL and Injuries'!$K$6 -> 1887000000 | AC33: =AA33*'VSL and Injuries'!$K$6*$AG33*E33 -> 144900000 | AD33: =AB33+AC33 -> 2031900000 | AE33: S007; S019; S032; S033 | AF33: Daily indirect loss includes displaced aviation activity, passenger delay, airport concessions, air cargo, and visitor effects; not airport-specific. | AG33: =IFERROR(INDEX('Duration Factors'!$G$4:$G$12,MATCH($B33,'Duration Factors'!$A$4:$A$12,0)),"") -> 1
A34: Airport Terminal | B34: 3 days | C34: 72 | D34: =IFERROR(INDEX('Duration Factors'!$C$4:$C$12,MATCH($B34,'Duration Factors'!$A$4:$A$12,0)),"") -> 3 | E34: =IFERROR(INDEX('Duration Factors'!$D$4:$D$12,MATCH($B34,'Duration Factors'!$A$4:$A$12,0)),"") -> 0.9 | F34: Moderate-Low | G34: ='Target Inputs'!G7 -> 0 | H34: ='Target Inputs'!H7 -> 5 | I34: ='Target Inputs'!I7 -> 0.025 | J34: ='Target Inputs'!J7 -> 25000000 | K34: ='Target Inputs'!K7 -> 5000000 | L34: =G34*'VSL and Injuries'!$B$4+H34*'VSL and Injuries'!$B$4*I34+J34*'VSL and Injuries'!$K$6 -> 27650000 | M34: =K34*'VSL and Injuries'!$K$6*$AG34*E34 -> 18630000 | N34: =L34+M34 -> 46280000 | O34: ='Target Inputs'!L7 -> 5 | P34: ='Target Inputs'!M7 -> 50 | Q34: ='Target Inputs'!N7 -> 0.05 | R34: ='Target Inputs'!O7 -> 200000000 | S34: ='Target Inputs'!P7 -> 40000000 | T34: =O34*'VSL and Injuries'!$B$4+P34*'VSL and Injuries'!$B$4*Q34+R34*'VSL and Injuries'!$K$6 -> 313500000 | U34: =S34*'VSL and Injuries'!$K$6*$AG34*E34 -> 149040000 | V34: =T34+U34 -> 462540000 | W34: ='Target Inputs'!Q7 -> 30 | X34: ='Target Inputs'!R7 -> 250 | Y34: ='Target Inputs'!S7 -> 0.12 | Z34: ='Target Inputs'!T7 -> 1000000000 | AA34: ='Target Inputs'!U7 -> 200000000 | AB34: =W34*'VSL and Injuries'!$B$4+X34*'VSL and Injuries'!$B$4*Y34+Z34*'VSL and Injuries'!$K$6 -> 1887000000 | AC34: =AA34*'VSL and Injuries'!$K$6*$AG34*E34 -> 745200000 | AD34: =AB34+AC34 -> 2632200000 | AE34: S007; S019; S032; S033 | AF34: Daily indirect loss includes displaced aviation activity, passenger delay, airport concessions, air cargo, and visitor effects; not airport-specific. | AG34: =IFERROR(INDEX('Duration Factors'!$G$4:$G$12,MATCH($B34,'Duration Factors'!$A$4:$A$12,0)),"") -> 4
A35: Airport Terminal | B35: 7 days | C35: 168 | D35: =IFERROR(INDEX('Duration Factors'!$C$4:$C$12,MATCH($B35,'Duration Factors'!$A$4:$A$12,0)),"") -> 7 | E35: =IFERROR(INDEX('Duration Factors'!$D$4:$D$12,MATCH($B35,'Duration Factors'!$A$4:$A$12,0)),"") -> 1 | F35: Moderate-Low | G35: ='Target Inputs'!G7 -> 0 | H35: ='Target Inputs'!H7 -> 5 | I35: ='Target Inputs'!I7 -> 0.025 | J35: ='Target Inputs'!J7 -> 25000000 | K35: ='Target Inputs'!K7 -> 5000000 | L35: =G35*'VSL and Injuries'!$B$4+H35*'VSL and Injuries'!$B$4*I35+J35*'VSL and Injuries'!$K$6 -> 27650000 | M35: =K35*'VSL and Injuries'!$K$6*$AG35*E35 -> 46575000 | N35: =L35+M35 -> 74225000 | O35: ='Target Inputs'!L7 -> 5 | P35: ='Target Inputs'!M7 -> 50 | Q35: ='Target Inputs'!N7 -> 0.05 | R35: ='Target Inputs'!O7 -> 200000000 | S35: ='Target Inputs'!P7 -> 40000000 | T35: =O35*'VSL and Injuries'!$B$4+P35*'VSL and Injuries'!$B$4*Q35+R35*'VSL and Injuries'!$K$6 -> 313500000 | U35: =S35*'VSL and Injuries'!$K$6*$AG35*E35 -> 372600000 | V35: =T35+U35 -> 686100000 | W35: ='Target Inputs'!Q7 -> 30 | X35: ='Target Inputs'!R7 -> 250 | Y35: ='Target Inputs'!S7 -> 0.12 | Z35: ='Target Inputs'!T7 -> 1000000000 | AA35: ='Target Inputs'!U7 -> 200000000 | AB35: =W35*'VSL and Injuries'!$B$4+X35*'VSL and Injuries'!$B$4*Y35+Z35*'VSL and Injuries'!$K$6 -> 1887000000 | AC35: =AA35*'VSL and Injuries'!$K$6*$AG35*E35 -> 1863000000 | AD35: =AB35+AC35 -> 3750000000 | AE35: S007; S019; S032; S033 | AF35: Daily indirect loss includes displaced aviation activity, passenger delay, airport concessions, air cargo, and visitor effects; not airport-specific. | AG35: =IFERROR(INDEX('Duration Factors'!$G$4:$G$12,MATCH($B35,'Duration Factors'!$A$4:$A$12,0)),"") -> 9
A36: Airport Terminal | B36: 14 days | C36: 336 | D36: =IFERROR(INDEX('Duration Factors'!$C$4:$C$12,MATCH($B36,'Duration Factors'!$A$4:$A$12,0)),"") -> 14 | E36: =IFERROR(INDEX('Duration Factors'!$D$4:$D$12,MATCH($B36,'Duration Factors'!$A$4:$A$12,0)),"") -> 1.1 | F36: Moderate-Low | G36: ='Target Inputs'!G7 -> 0 | H36: ='Target Inputs'!H7 -> 5 | I36: ='Target Inputs'!I7 -> 0.025 | J36: ='Target Inputs'!J7 -> 25000000 | K36: ='Target Inputs'!K7 -> 5000000 | L36: =G36*'VSL and Injuries'!$B$4+H36*'VSL and Injuries'!$B$4*I36+J36*'VSL and Injuries'!$K$6 -> 27650000 | M36: =K36*'VSL and Injuries'!$K$6*$AG36*E36 -> 96772500 | N36: =L36+M36 -> 124422500 | O36: ='Target Inputs'!L7 -> 5 | P36: ='Target Inputs'!M7 -> 50 | Q36: ='Target Inputs'!N7 -> 0.05 | R36: ='Target Inputs'!O7 -> 200000000 | S36: ='Target Inputs'!P7 -> 40000000 | T36: =O36*'VSL and Injuries'!$B$4+P36*'VSL and Injuries'!$B$4*Q36+R36*'VSL and Injuries'!$K$6 -> 313500000 | U36: =S36*'VSL and Injuries'!$K$6*$AG36*E36 -> 774180000 | V36: =T36+U36 -> 1087680000 | W36: ='Target Inputs'!Q7 -> 30 | X36: ='Target Inputs'!R7 -> 250 | Y36: ='Target Inputs'!S7 -> 0.12 | Z36: ='Target Inputs'!T7 -> 1000000000 | AA36: ='Target Inputs'!U7 -> 200000000 | AB36: =W36*'VSL and Injuries'!$B$4+X36*'VSL and Injuries'!$B$4*Y36+Z36*'VSL and Injuries'!$K$6 -> 1887000000 | AC36: =AA36*'VSL and Injuries'!$K$6*$AG36*E36 -> 3870900000 | AD36: =AB36+AC36 -> 5757900000 | AE36: S007; S019; S032; S033 | AF36: Daily indirect loss includes displaced aviation activity, passenger delay, airport concessions, air cargo, and visitor effects; not airport-specific. | AG36: =IFERROR(INDEX('Duration Factors'!$G$4:$G$12,MATCH($B36,'Duration Factors'!$A$4:$A$12,0)),"") -> 17
A37: Airport Terminal | B37: 30 days | C37: 720 | D37: =IFERROR(INDEX('Duration Factors'!$C$4:$C$12,MATCH($B37,'Duration Factors'!$A$4:$A$12,0)),"") -> 30 | E37: =IFERROR(INDEX('Duration Factors'!$D$4:$D$12,MATCH($B37,'Duration Factors'!$A$4:$A$12,0)),"") -> 1.2 | F37: Moderate-Low | G37: ='Target Inputs'!G7 -> 0 | H37: ='Target Inputs'!H7 -> 5 | I37: ='Target Inputs'!I7 -> 0.025 | J37: ='Target Inputs'!J7 -> 25000000 | K37: ='Target Inputs'!K7 -> 5000000 | L37: =G37*'VSL and Injuries'!$B$4+H37*'VSL and Injuries'!$B$4*I37+J37*'VSL and Injuries'!$K$6 -> 27650000 | M37: =K37*'VSL and Injuries'!$K$6*$AG37*E37 -> 217350000 | N37: =L37+M37 -> 245000000 | O37: ='Target Inputs'!L7 -> 5 | P37: ='Target Inputs'!M7 -> 50 | Q37: ='Target Inputs'!N7 -> 0.05 | R37: ='Target Inputs'!O7 -> 200000000 | S37: ='Target Inputs'!P7 -> 40000000 | T37: =O37*'VSL and Injuries'!$B$4+P37*'VSL and Injuries'!$B$4*Q37+R37*'VSL and Injuries'!$K$6 -> 313500000 | U37: =S37*'VSL and Injuries'!$K$6*$AG37*E37 -> 1738800000 | V37: =T37+U37 -> 2052300000 | W37: ='Target Inputs'!Q7 -> 30 | X37: ='Target Inputs'!R7 -> 250 | Y37: ='Target Inputs'!S7 -> 0.12 | Z37: ='Target Inputs'!T7 -> 1000000000 | AA37: ='Target Inputs'!U7 -> 200000000 | AB37: =W37*'VSL and Injuries'!$B$4+X37*'VSL and Injuries'!$B$4*Y37+Z37*'VSL and Injuries'!$K$6 -> 1887000000 | AC37: =AA37*'VSL and Injuries'!$K$6*$AG37*E37 -> 8694000000 | AD37: =AB37+AC37 -> 10581000000 | AE37: S007; S019; S032; S033 | AF37: Daily indirect loss includes displaced aviation activity, passenger delay, airport concessions, air cargo, and visitor effects; not airport-specific. | AG37: =IFERROR(INDEX('Duration Factors'!$G$4:$G$12,MATCH($B37,'Duration Factors'!$A$4:$A$12,0)),"") -> 35
A38: Airport Terminal | B38: 45 days | C38: 1080 | D38: =IFERROR(INDEX('Duration Factors'!$C$4:$C$12,MATCH($B38,'Duration Factors'!$A$4:$A$12,0)),"") -> 45 | E38: =IFERROR(INDEX('Duration Factors'!$D$4:$D$12,MATCH($B38,'Duration Factors'!$A$4:$A$12,0)),"") -> 1.3 | F38: Moderate-Low | G38: ='Target Inputs'!G7 -> 0 | H38: ='Target Inputs'!H7 -> 5 | I38: ='Target Inputs'!I7 -> 0.025 | J38: ='Target Inputs'!J7 -> 25000000 | K38: ='Target Inputs'!K7 -> 5000000 | L38: =G38*'VSL and Injuries'!$B$4+H38*'VSL and Injuries'!$B$4*I38+J38*'VSL and Injuries'!$K$6 -> 27650000 | M38: =K38*'VSL and Injuries'!$K$6*$AG38*E38 -> 370012500 | N38: =L38+M38 -> 397662500 | O38: ='Target Inputs'!L7 -> 5 | P38: ='Target Inputs'!M7 -> 50 | Q38: ='Target Inputs'!N7 -> 0.05 | R38: ='Target Inputs'!O7 -> 200000000 | S38: ='Target Inputs'!P7 -> 40000000 | T38: =O38*'VSL and Injuries'!$B$4+P38*'VSL and Injuries'!$B$4*Q38+R38*'VSL and Injuries'!$K$6 -> 313500000 | U38: =S38*'VSL and Injuries'!$K$6*$AG38*E38 -> 2960100000 | V38: =T38+U38 -> 3273600000 | W38: ='Target Inputs'!Q7 -> 30 | X38: ='Target Inputs'!R7 -> 250 | Y38: ='Target Inputs'!S7 -> 0.12 | Z38: ='Target Inputs'!T7 -> 1000000000 | AA38: ='Target Inputs'!U7 -> 200000000 | AB38: =W38*'VSL and Injuries'!$B$4+X38*'VSL and Injuries'!$B$4*Y38+Z38*'VSL and Injuries'!$K$6 -> 1887000000 | AC38: =AA38*'VSL and Injuries'!$K$6*$AG38*E38 -> 14800500000 | AD38: =AB38+AC38 -> 16687500000 | AE38: S007; S019; S032; S033 | AF38: Daily indirect loss includes displaced aviation activity, passenger delay, airport concessions, air cargo, and visitor effects; not airport-specific. | AG38: =IFERROR(INDEX('Duration Factors'!$G$4:$G$12,MATCH($B38,'Duration Factors'!$A$4:$A$12,0)),"") -> 55
A39: Airport Terminal | B39: 90 days | C39: 2160 | D39: =IFERROR(INDEX('Duration Factors'!$C$4:$C$12,MATCH($B39,'Duration Factors'!$A$4:$A$12,0)),"") -> 90 | E39: =IFERROR(INDEX('Duration Factors'!$D$4:$D$12,MATCH($B39,'Duration Factors'!$A$4:$A$12,0)),"") -> 1.4 | F39: Moderate-Low | G39: ='Target Inputs'!G7 -> 0 | H39: ='Target Inputs'!H7 -> 5 | I39: ='Target Inputs'!I7 -> 0.025 | J39: ='Target Inputs'!J7 -> 25000000 | K39: ='Target Inputs'!K7 -> 5000000 | L39: =G39*'VSL and Injuries'!$B$4+H39*'VSL and Injuries'!$B$4*I39+J39*'VSL and Injuries'!$K$6 -> 27650000 | M39: =K39*'VSL and Injuries'!$K$6*$AG39*E39 -> 796950000 | N39: =L39+M39 -> 824600000 | O39: ='Target Inputs'!L7 -> 5 | P39: ='Target Inputs'!M7 -> 50 | Q39: ='Target Inputs'!N7 -> 0.05 | R39: ='Target Inputs'!O7 -> 200000000 | S39: ='Target Inputs'!P7 -> 40000000 | T39: =O39*'VSL and Injuries'!$B$4+P39*'VSL and Injuries'!$B$4*Q39+R39*'VSL and Injuries'!$K$6 -> 313500000 | U39: =S39*'VSL and Injuries'!$K$6*$AG39*E39 -> 6375600000 | V39: =T39+U39 -> 6689100000 | W39: ='Target Inputs'!Q7 -> 30 | X39: ='Target Inputs'!R7 -> 250 | Y39: ='Target Inputs'!S7 -> 0.12 | Z39: ='Target Inputs'!T7 -> 1000000000 | AA39: ='Target Inputs'!U7 -> 200000000 | AB39: =W39*'VSL and Injuries'!$B$4+X39*'VSL and Injuries'!$B$4*Y39+Z39*'VSL and Injuries'!$K$6 -> 1887000000 | AC39: =AA39*'VSL and Injuries'!$K$6*$AG39*E39 -> 31878000000 | AD39: =AB39+AC39 -> 33765000000 | AE39: S007; S019; S032; S033 | AF39: Daily indirect loss includes displaced aviation activity, passenger delay, airport concessions, air cargo, and visitor effects; not airport-specific. | AG39: =IFERROR(INDEX('Duration Factors'!$G$4:$G$12,MATCH($B39,'Duration Factors'!$A$4:$A$12,0)),"") -> 110
A40: Freight Rail | B40: 4 hours | C40: 4 | D40: =IFERROR(INDEX('Duration Factors'!$C$4:$C$12,MATCH($B40,'Duration Factors'!$A$4:$A$12,0)),"") -> 0.16666667 | E40: =IFERROR(INDEX('Duration Factors'!$D$4:$D$12,MATCH($B40,'Duration Factors'!$A$4:$A$12,0)),"") -> 0.35 | F40: Moderate-Low | G40: ='Target Inputs'!G8 -> 0 | H40: ='Target Inputs'!H8 -> 1 | I40: ='Target Inputs'!I8 -> 0.02 | J40: ='Target Inputs'!J8 -> 2000000 | K40: ='Target Inputs'!K8 -> 2000000 | L40: =G40*'VSL and Injuries'!$B$4+H40*'VSL and Injuries'!$B$4*I40+J40*'VSL and Injuries'!$K$6 -> 2354000 | M40: =K40*'VSL and Injuries'!$K$6*$AG40*E40 -> 120750 | N40: =L40+M40 -> 2474750 | O40: ='Target Inputs'!L8 -> 1 | P40: ='Target Inputs'!M8 -> 8 | Q40: ='Target Inputs'!N8 -> 0.05 | R40: ='Target Inputs'!O8 -> 20000000 | S40: ='Target Inputs'!P8 -> 15000000 | T40: =O40*'VSL and Injuries'!$B$4+P40*'VSL and Injuries'!$B$4*Q40+R40*'VSL and Injuries'!$K$6 -> 40580000 | U40: =S40*'VSL and Injuries'!$K$6*$AG40*E40 -> 905625 | V40: =T40+U40 -> 41485625 | W40: ='Target Inputs'!Q8 -> 10 | X40: ='Target Inputs'!R8 -> 50 | Y40: ='Target Inputs'!S8 -> 0.12 | Z40: ='Target Inputs'!T8 -> 150000000 | AA40: ='Target Inputs'!U8 -> 75000000 | AB40: =W40*'VSL and Injuries'!$B$4+X40*'VSL and Injuries'!$B$4*Y40+Z40*'VSL and Injuries'!$K$6 -> 382450000 | AC40: =AA40*'VSL and Injuries'!$K$6*$AG40*E40 -> 4528125 | AD40: =AB40+AC40 -> 386978125 | AE40: S018; S020; S034 | AF40: Indirect loss reflects delayed/lost freight value and dependent production; substitute routing is represented only through the range. | AG40: =IFERROR(INDEX('Duration Factors'!$G$4:$G$12,MATCH($B40,'Duration Factors'!$A$4:$A$12,0)),"") -> 0.16666667
A41: Freight Rail | B41: 12 hours | C41: 12 | D41: =IFERROR(INDEX('Duration Factors'!$C$4:$C$12,MATCH($B41,'Duration Factors'!$A$4:$A$12,0)),"") -> 0.5 | E41: =IFERROR(INDEX('Duration Factors'!$D$4:$D$12,MATCH($B41,'Duration Factors'!$A$4:$A$12,0)),"") -> 0.55 | F41: Moderate-Low | G41: ='Target Inputs'!G8 -> 0 | H41: ='Target Inputs'!H8 -> 1 | I41: ='Target Inputs'!I8 -> 0.02 | J41: ='Target Inputs'!J8 -> 2000000 | K41: ='Target Inputs'!K8 -> 2000000 | L41: =G41*'VSL and Injuries'!$B$4+H41*'VSL and Injuries'!$B$4*I41+J41*'VSL and Injuries'!$K$6 -> 2354000 | M41: =K41*'VSL and Injuries'!$K$6*$AG41*E41 -> 569250 | N41: =L41+M41 -> 2923250 | O41: ='Target Inputs'!L8 -> 1 | P41: ='Target Inputs'!M8 -> 8 | Q41: ='Target Inputs'!N8 -> 0.05 | R41: ='Target Inputs'!O8 -> 20000000 | S41: ='Target Inputs'!P8 -> 15000000 | T41: =O41*'VSL and Injuries'!$B$4+P41*'VSL and Injuries'!$B$4*Q41+R41*'VSL and Injuries'!$K$6 -> 40580000 | U41: =S41*'VSL and Injuries'!$K$6*$AG41*E41 -> 4269375 | V41: =T41+U41 -> 44849375 | W41: ='Target Inputs'!Q8 -> 10 | X41: ='Target Inputs'!R8 -> 50 | Y41: ='Target Inputs'!S8 -> 0.12 | Z41: ='Target Inputs'!T8 -> 150000000 | AA41: ='Target Inputs'!U8 -> 75000000 | AB41: =W41*'VSL and Injuries'!$B$4+X41*'VSL and Injuries'!$B$4*Y41+Z41*'VSL and Injuries'!$K$6 -> 382450000 | AC41: =AA41*'VSL and Injuries'!$K$6*$AG41*E41 -> 21346875 | AD41: =AB41+AC41 -> 403796875 | AE41: S018; S020; S034 | AF41: Indirect loss reflects delayed/lost freight value and dependent production; substitute routing is represented only through the range. | AG41: =IFERROR(INDEX('Duration Factors'!$G$4:$G$12,MATCH($B41,'Duration Factors'!$A$4:$A$12,0)),"") -> 0.5
A42: Freight Rail | B42: 1 day | C42: 24 | D42: =IFERROR(INDEX('Duration Factors'!$C$4:$C$12,MATCH($B42,'Duration Factors'!$A$4:$A$12,0)),"") -> 1 | E42: =IFERROR(INDEX('Duration Factors'!$D$4:$D$12,MATCH($B42,'Duration Factors'!$A$4:$A$12,0)),"") -> 0.7 | F42: Moderate-Low | G42: ='Target Inputs'!G8 -> 0 | H42: ='Target Inputs'!H8 -> 1 | I42: ='Target Inputs'!I8 -> 0.02 | J42: ='Target Inputs'!J8 -> 2000000 | K42: ='Target Inputs'!K8 -> 2000000 | L42: =G42*'VSL and Injuries'!$B$4+H42*'VSL and Injuries'!$B$4*I42+J42*'VSL and Injuries'!$K$6 -> 2354000 | M42: =K42*'VSL and Injuries'!$K$6*$AG42*E42 -> 1449000 | N42: =L42+M42 -> 3803000 | O42: ='Target Inputs'!L8 -> 1 | P42: ='Target Inputs'!M8 -> 8 | Q42: ='Target Inputs'!N8 -> 0.05 | R42: ='Target Inputs'!O8 -> 20000000 | S42: ='Target Inputs'!P8 -> 15000000 | T42: =O42*'VSL and Injuries'!$B$4+P42*'VSL and Injuries'!$B$4*Q42+R42*'VSL and Injuries'!$K$6 -> 40580000 | U42: =S42*'VSL and Injuries'!$K$6*$AG42*E42 -> 10867500 | V42: =T42+U42 -> 51447500 | W42: ='Target Inputs'!Q8 -> 10 | X42: ='Target Inputs'!R8 -> 50 | Y42: ='Target Inputs'!S8 -> 0.12 | Z42: ='Target Inputs'!T8 -> 150000000 | AA42: ='Target Inputs'!U8 -> 75000000 | AB42: =W42*'VSL and Injuries'!$B$4+X42*'VSL and Injuries'!$B$4*Y42+Z42*'VSL and Injuries'!$K$6 -> 382450000 | AC42: =AA42*'VSL and Injuries'!$K$6*$AG42*E42 -> 54337500 | AD42: =AB42+AC42 -> 436787500 | AE42: S018; S020; S034 | AF42: Indirect loss reflects delayed/lost freight value and dependent production; substitute routing is represented only through the range. | AG42: =IFERROR(INDEX('Duration Factors'!$G$4:$G$12,MATCH($B42,'Duration Factors'!$A$4:$A$12,0)),"") -> 1
A43: Freight Rail | B43: 3 days | C43: 72 | D43: =IFERROR(INDEX('Duration Factors'!$C$4:$C$12,MATCH($B43,'Duration Factors'!$A$4:$A$12,0)),"") -> 3 | E43: =IFERROR(INDEX('Duration Factors'!$D$4:$D$12,MATCH($B43,'Duration Factors'!$A$4:$A$12,0)),"") -> 0.9 | F43: Moderate-Low | G43: ='Target Inputs'!G8 -> 0 | H43: ='Target Inputs'!H8 -> 1 | I43: ='Target Inputs'!I8 -> 0.02 | J43: ='Target Inputs'!J8 -> 2000000 | K43: ='Target Inputs'!K8 -> 2000000 | L43: =G43*'VSL and Injuries'!$B$4+H43*'VSL and Injuries'!$B$4*I43+J43*'VSL and Injuries'!$K$6 -> 2354000 | M43: =K43*'VSL and Injuries'!$K$6*$AG43*E43 -> 7452000 | N43: =L43+M43 -> 9806000 | O43: ='Target Inputs'!L8 -> 1 | P43: ='Target Inputs'!M8 -> 8 | Q43: ='Target Inputs'!N8 -> 0.05 | R43: ='Target Inputs'!O8 -> 20000000 | S43: ='Target Inputs'!P8 -> 15000000 | T43: =O43*'VSL and Injuries'!$B$4+P43*'VSL and Injuries'!$B$4*Q43+R43*'VSL and Injuries'!$K$6 -> 40580000 | U43: =S43*'VSL and Injuries'!$K$6*$AG43*E43 -> 55890000 | V43: =T43+U43 -> 96470000 | W43: ='Target Inputs'!Q8 -> 10 | X43: ='Target Inputs'!R8 -> 50 | Y43: ='Target Inputs'!S8 -> 0.12 | Z43: ='Target Inputs'!T8 -> 150000000 | AA43: ='Target Inputs'!U8 -> 75000000 | AB43: =W43*'VSL and Injuries'!$B$4+X43*'VSL and Injuries'!$B$4*Y43+Z43*'VSL and Injuries'!$K$6 -> 382450000 | AC43: =AA43*'VSL and Injuries'!$K$6*$AG43*E43 -> 279450000 | AD43: =AB43+AC43 -> 661900000 | AE43: S018; S020; S034 | AF43: Indirect loss reflects delayed/lost freight value and dependent production; substitute routing is represented only through the range. | AG43: =IFERROR(INDEX('Duration Factors'!$G$4:$G$12,MATCH($B43,'Duration Factors'!$A$4:$A$12,0)),"") -> 4
A44: Freight Rail | B44: 7 days | C44: 168 | D44: =IFERROR(INDEX('Duration Factors'!$C$4:$C$12,MATCH($B44,'Duration Factors'!$A$4:$A$12,0)),"") -> 7 | E44: =IFERROR(INDEX('Duration Factors'!$D$4:$D$12,MATCH($B44,'Duration Factors'!$A$4:$A$12,0)),"") -> 1 | F44: Moderate-Low | G44: ='Target Inputs'!G8 -> 0 | H44: ='Target Inputs'!H8 -> 1 | I44: ='Target Inputs'!I8 -> 0.02 | J44: ='Target Inputs'!J8 -> 2000000 | K44: ='Target Inputs'!K8 -> 2000000 | L44: =G44*'VSL and Injuries'!$B$4+H44*'VSL and Injuries'!$B$4*I44+J44*'VSL and Injuries'!$K$6 -> 2354000 | M44: =K44*'VSL and Injuries'!$K$6*$AG44*E44 -> 18630000 | N44: =L44+M44 -> 20984000 | O44: ='Target Inputs'!L8 -> 1 | P44: ='Target Inputs'!M8 -> 8 | Q44: ='Target Inputs'!N8 -> 0.05 | R44: ='Target Inputs'!O8 -> 20000000 | S44: ='Target Inputs'!P8 -> 15000000 | T44: =O44*'VSL and Injuries'!$B$4+P44*'VSL and Injuries'!$B$4*Q44+R44*'VSL and Injuries'!$K$6 -> 40580000 | U44: =S44*'VSL and Injuries'!$K$6*$AG44*E44 -> 139725000 | V44: =T44+U44 -> 180305000 | W44: ='Target Inputs'!Q8 -> 10 | X44: ='Target Inputs'!R8 -> 50 | Y44: ='Target Inputs'!S8 -> 0.12 | Z44: ='Target Inputs'!T8 -> 150000000 | AA44: ='Target Inputs'!U8 -> 75000000 | AB44: =W44*'VSL and Injuries'!$B$4+X44*'VSL and Injuries'!$B$4*Y44+Z44*'VSL and Injuries'!$K$6 -> 382450000 | AC44: =AA44*'VSL and Injuries'!$K$6*$AG44*E44 -> 698625000 | AD44: =AB44+AC44 -> 1081075000 | AE44: S018; S020; S034 | AF44: Indirect loss reflects delayed/lost freight value and dependent production; substitute routing is represented only through the range. | AG44: =IFERROR(INDEX('Duration Factors'!$G$4:$G$12,MATCH($B44,'Duration Factors'!$A$4:$A$12,0)),"") -> 9
A45: Freight Rail | B45: 14 days | C45: 336 | D45: =IFERROR(INDEX('Duration Factors'!$C$4:$C$12,MATCH($B45,'Duration Factors'!$A$4:$A$12,0)),"") -> 14 | E45: =IFERROR(INDEX('Duration Factors'!$D$4:$D$12,MATCH($B45,'Duration Factors'!$A$4:$A$12,0)),"") -> 1.1 | F45: Moderate-Low | G45: ='Target Inputs'!G8 -> 0 | H45: ='Target Inputs'!H8 -> 1 | I45: ='Target Inputs'!I8 -> 0.02 | J45: ='Target Inputs'!J8 -> 2000000 | K45: ='Target Inputs'!K8 -> 2000000 | L45: =G45*'VSL and Injuries'!$B$4+H45*'VSL and Injuries'!$B$4*I45+J45*'VSL and Injuries'!$K$6 -> 2354000 | M45: =K45*'VSL and Injuries'!$K$6*$AG45*E45 -> 38709000 | N45: =L45+M45 -> 41063000 | O45: ='Target Inputs'!L8 -> 1 | P45: ='Target Inputs'!M8 -> 8 | Q45: ='Target Inputs'!N8 -> 0.05 | R45: ='Target Inputs'!O8 -> 20000000 | S45: ='Target Inputs'!P8 -> 15000000 | T45: =O45*'VSL and Injuries'!$B$4+P45*'VSL and Injuries'!$B$4*Q45+R45*'VSL and Injuries'!$K$6 -> 40580000 | U45: =S45*'VSL and Injuries'!$K$6*$AG45*E45 -> 290317500 | V45: =T45+U45 -> 330897500 | W45: ='Target Inputs'!Q8 -> 10 | X45: ='Target Inputs'!R8 -> 50 | Y45: ='Target Inputs'!S8 -> 0.12 | Z45: ='Target Inputs'!T8 -> 150000000 | AA45: ='Target Inputs'!U8 -> 75000000 | AB45: =W45*'VSL and Injuries'!$B$4+X45*'VSL and Injuries'!$B$4*Y45+Z45*'VSL and Injuries'!$K$6 -> 382450000 | AC45: =AA45*'VSL and Injuries'!$K$6*$AG45*E45 -> 1451587500 | AD45: =AB45+AC45 -> 1834037500 | AE45: S018; S020; S034 | AF45: Indirect loss reflects delayed/lost freight value and dependent production; substitute routing is represented only through the range. | AG45: =IFERROR(INDEX('Duration Factors'!$G$4:$G$12,MATCH($B45,'Duration Factors'!$A$4:$A$12,0)),"") -> 17
A46: Freight Rail | B46: 30 days | C46: 720 | D46: =IFERROR(INDEX('Duration Factors'!$C$4:$C$12,MATCH($B46,'Duration Factors'!$A$4:$A$12,0)),"") -> 30 | E46: =IFERROR(INDEX('Duration Factors'!$D$4:$D$12,MATCH($B46,'Duration Factors'!$A$4:$A$12,0)),"") -> 1.2 | F46: Moderate-Low | G46: ='Target Inputs'!G8 -> 0 | H46: ='Target Inputs'!H8 -> 1 | I46: ='Target Inputs'!I8 -> 0.02 | J46: ='Target Inputs'!J8 -> 2000000 | K46: ='Target Inputs'!K8 -> 2000000 | L46: =G46*'VSL and Injuries'!$B$4+H46*'VSL and Injuries'!$B$4*I46+J46*'VSL and Injuries'!$K$6 -> 2354000 | M46: =K46*'VSL and Injuries'!$K$6*$AG46*E46 -> 86940000 | N46: =L46+M46 -> 89294000 | O46: ='Target Inputs'!L8 -> 1 | P46: ='Target Inputs'!M8 -> 8 | Q46: ='Target Inputs'!N8 -> 0.05 | R46: ='Target Inputs'!O8 -> 20000000 | S46: ='Target Inputs'!P8 -> 15000000 | T46: =O46*'VSL and Injuries'!$B$4+P46*'VSL and Injuries'!$B$4*Q46+R46*'VSL and Injuries'!$K$6 -> 40580000 | U46: =S46*'VSL and Injuries'!$K$6*$AG46*E46 -> 652050000 | V46: =T46+U46 -> 692630000 | W46: ='Target Inputs'!Q8 -> 10 | X46: ='Target Inputs'!R8 -> 50 | Y46: ='Target Inputs'!S8 -> 0.12 | Z46: ='Target Inputs'!T8 -> 150000000 | AA46: ='Target Inputs'!U8 -> 75000000 | AB46: =W46*'VSL and Injuries'!$B$4+X46*'VSL and Injuries'!$B$4*Y46+Z46*'VSL and Injuries'!$K$6 -> 382450000 | AC46: =AA46*'VSL and Injuries'!$K$6*$AG46*E46 -> 3260250000 | AD46: =AB46+AC46 -> 3642700000 | AE46: S018; S020; S034 | AF46: Indirect loss reflects delayed/lost freight value and dependent production; substitute routing is represented only through the range. | AG46: =IFERROR(INDEX('Duration Factors'!$G$4:$G$12,MATCH($B46,'Duration Factors'!$A$4:$A$12,0)),"") -> 35
A47: Freight Rail | B47: 45 days | C47: 1080 | D47: =IFERROR(INDEX('Duration Factors'!$C$4:$C$12,MATCH($B47,'Duration Factors'!$A$4:$A$12,0)),"") -> 45 | E47: =IFERROR(INDEX('Duration Factors'!$D$4:$D$12,MATCH($B47,'Duration Factors'!$A$4:$A$12,0)),"") -> 1.3 | F47: Moderate-Low | G47: ='Target Inputs'!G8 -> 0 | H47: ='Target Inputs'!H8 -> 1 | I47: ='Target Inputs'!I8 -> 0.02 | J47: ='Target Inputs'!J8 -> 2000000 | K47: ='Target Inputs'!K8 -> 2000000 | L47: =G47*'VSL and Injuries'!$B$4+H47*'VSL and Injuries'!$B$4*I47+J47*'VSL and Injuries'!$K$6 -> 2354000 | M47: =K47*'VSL and Injuries'!$K$6*$AG47*E47 -> 148005000 | N47: =L47+M47 -> 150359000 | O47: ='Target Inputs'!L8 -> 1 | P47: ='Target Inputs'!M8 -> 8 | Q47: ='Target Inputs'!N8 -> 0.05 | R47: ='Target Inputs'!O8 -> 20000000 | S47: ='Target Inputs'!P8 -> 15000000 | T47: =O47*'VSL and Injuries'!$B$4+P47*'VSL and Injuries'!$B$4*Q47+R47*'VSL and Injuries'!$K$6 -> 40580000 | U47: =S47*'VSL and Injuries'!$K$6*$AG47*E47 -> 1110037500 | V47: =T47+U47 -> 1150617500 | W47: ='Target Inputs'!Q8 -> 10 | X47: ='Target Inputs'!R8 -> 50 | Y47: ='Target Inputs'!S8 -> 0.12 | Z47: ='Target Inputs'!T8 -> 150000000 | AA47: ='Target Inputs'!U8 -> 75000000 | AB47: =W47*'VSL and Injuries'!$B$4+X47*'VSL and Injuries'!$B$4*Y47+Z47*'VSL and Injuries'!$K$6 -> 382450000 | AC47: =AA47*'VSL and Injuries'!$K$6*$AG47*E47 -> 5550187500 | AD47: =AB47+AC47 -> 5932637500 | AE47: S018; S020; S034 | AF47: Indirect loss reflects delayed/lost freight value and dependent production; substitute routing is represented only through the range. | AG47: =IFERROR(INDEX('Duration Factors'!$G$4:$G$12,MATCH($B47,'Duration Factors'!$A$4:$A$12,0)),"") -> 55
A48: Freight Rail | B48: 90 days | C48: 2160 | D48: =IFERROR(INDEX('Duration Factors'!$C$4:$C$12,MATCH($B48,'Duration Factors'!$A$4:$A$12,0)),"") -> 90 | E48: =IFERROR(INDEX('Duration Factors'!$D$4:$D$12,MATCH($B48,'Duration Factors'!$A$4:$A$12,0)),"") -> 1.4 | F48: Moderate-Low | G48: ='Target Inputs'!G8 -> 0 | H48: ='Target Inputs'!H8 -> 1 | I48: ='Target Inputs'!I8 -> 0.02 | J48: ='Target Inputs'!J8 -> 2000000 | K48: ='Target Inputs'!K8 -> 2000000 | L48: =G48*'VSL and Injuries'!$B$4+H48*'VSL and Injuries'!$B$4*I48+J48*'VSL and Injuries'!$K$6 -> 2354000 | M48: =K48*'VSL and Injuries'!$K$6*$AG48*E48 -> 318780000 | N48: =L48+M48 -> 321134000 | O48: ='Target Inputs'!L8 -> 1 | P48: ='Target Inputs'!M8 -> 8 | Q48: ='Target Inputs'!N8 -> 0.05 | R48: ='Target Inputs'!O8 -> 20000000 | S48: ='Target Inputs'!P8 -> 15000000 | T48: =O48*'VSL and Injuries'!$B$4+P48*'VSL and Injuries'!$B$4*Q48+R48*'VSL and Injuries'!$K$6 -> 40580000 | U48: =S48*'VSL and Injuries'!$K$6*$AG48*E48 -> 2390850000 | V48: =T48+U48 -> 2431430000 | W48: ='Target Inputs'!Q8 -> 10 | X48: ='Target Inputs'!R8 -> 50 | Y48: ='Target Inputs'!S8 -> 0.12 | Z48: ='Target Inputs'!T8 -> 150000000 | AA48: ='Target Inputs'!U8 -> 75000000 | AB48: =W48*'VSL and Injuries'!$B$4+X48*'VSL and Injuries'!$B$4*Y48+Z48*'VSL and Injuries'!$K$6 -> 382450000 | AC48: =AA48*'VSL and Injuries'!$K$6*$AG48*E48 -> 11954250000 | AD48: =AB48+AC48 -> 12336700000 | AE48: S018; S020; S034 | AF48: Indirect loss reflects delayed/lost freight value and dependent production; substitute routing is represented only through the range. | AG48: =IFERROR(INDEX('Duration Factors'!$G$4:$G$12,MATCH($B48,'Duration Factors'!$A$4:$A$12,0)),"") -> 110

Sheet Cross-Sector Allocation
A1: Illustrative Static Screening Allocation of Second-Order Consequences Across CISA Sectors (pending CGE/REMI replacement)
A3: Target | B3: CISA Sector | C3: Share of Second-Order Loss | D3: Dependency Rationale | E3: Evidence Status | F3: Source IDs | G3: Validation Note | I3: Target | J3: Share Check | L3: Method status and required transition
A4: Pipeline Segment | B4: Chemical | C4: 0.1 | D4: Feedstock/product movement and energy dependence. | E4: Illustrative allocation | F4: S017; S029; S030; S031; S002; S003 | G4: Replace with asset-specific dependency mapping and approved multipliers. | I4: Pipeline Segment | J4: =SUM(C4:C19) -> 1 | L4: - These shares are STATIC screening assumptions (RIMS II-style fixed coefficients). They cannot capture non-linear network failure, capacity constraints, price-spike transfers, or behavioral shocks.
A5: Pipeline Segment | B5: Commercial Facilities | C5: 0.05 | D5: Passenger, workforce, retail, hospitality, and facility-access losses. | E5: Illustrative allocation | F5: S017; S029; S030; S031; S002; S003 | G5: Replace with asset-specific dependency mapping and approved multipliers. | I5: Pump Station | J5: =SUM(C20:C35) -> 1 | L5: - Required transition: replace/supplement with a dynamic Computable General Equilibrium (CGE) model or a REMI platform before any resource-allocation use.
A6: Pipeline Segment | B6: Communications | C6: 0.02 | D6: Power, equipment, workforce access, and logistics dependencies. | E6: Illustrative allocation | F6: S017; S029; S030; S031; S002; S003 | G6: Replace with asset-specific dependency mapping and approved multipliers. | I6: Compressor Station | J6: =SUM(C36:C51) -> 1 | L6: - CGE/REMI captures: substitution under constraint, cascading capacity limits, price transmission, and third-order macroeconomic behavior (e.g., panic-buying and commodity hoarding seen in the Colonial Pipeline event).
A7: Pipeline Segment | B7: Critical Manufacturing | C7: 0.1 | D7: Input shortages, delayed components, and production interruption. | E7: Illustrative allocation | F7: S017; S029; S030; S031; S002; S003 | G7: Replace with asset-specific dependency mapping and approved multipliers. | I7: Airport Terminal | J7: =SUM(C52:C67) -> 1 | L7: - Until replaced, treat this sheet only as a pointer to which sector pathways need asset-specific modeling.
A8: Pipeline Segment | B8: Dams | C8: 0.01 | D8: Limited indirect exposure through power, access, and maintenance logistics. | E8: Illustrative allocation | F8: S017; S029; S030; S031; S002; S003 | G8: Replace with asset-specific dependency mapping and approved multipliers. | I8: Freight Rail | J8: =SUM(C68:C83) -> 1
A9: Pipeline Segment | B9: Defense Industrial Base | C9: 0.07 | D9: Publicly observable logistics and supplier exposure; not classified mission impact. | E9: Illustrative allocation | F9: S017; S029; S030; S031; S002; S003 | G9: Replace with asset-specific dependency mapping and approved multipliers.
A10: Pipeline Segment | B10: Emergency Services | C10: 0.02 | D10: Response demand, access, fuel, and mutual-aid movement. | E10: Illustrative allocation | F10: S017; S029; S030; S031; S002; S003 | G10: Replace with asset-specific dependency mapping and approved multipliers.
A11: Pipeline Segment | B11: Energy | C11: 0.35 | D11: Fuel or natural-gas availability, electric generation, and operating energy dependencies. | E11: Illustrative allocation | F11: S017; S029; S030; S031; S002; S003 | G11: Replace with asset-specific dependency mapping and approved multipliers.
A12: Pipeline Segment | B12: Financial Services | C12: 0.02 | D12: Payment, insurance, market, and business interruption effects. | E12: Illustrative allocation | F12: S017; S029; S030; S031; S002; S003 | G12: Replace with asset-specific dependency mapping and approved multipliers.
A13: Pipeline Segment | B13: Food and Agriculture | C13: 0.05 | D13: Cold chain, bulk transport, inventory, and market-access effects. | E13: Illustrative allocation | F13: S017; S029; S030; S031; S002; S003 | G13: Replace with asset-specific dependency mapping and approved multipliers.
A14: Pipeline Segment | B14: Government Services and Facilities | C14: 0.03 | D14: Workforce, continuity, and service-delivery disruption. | E14: Illustrative allocation | F14: S017; S029; S030; S031; S002; S003 | G14: Replace with asset-specific dependency mapping and approved multipliers.
A15: Pipeline Segment | B15: Healthcare and Public Health | C15: 0.02 | D15: Medical logistics, workforce access, and emergency demand. | E15: Illustrative allocation | F15: S017; S029; S030; S031; S002; S003 | G15: Replace with asset-specific dependency mapping and approved multipliers.
A16: Pipeline Segment | B16: Information Technology | C16: 0.02 | D16: Data-center, hardware, workforce, and service-support dependencies. | E16: Illustrative allocation | F16: S017; S029; S030; S031; S002; S003 | G16: Replace with asset-specific dependency mapping and approved multipliers.
A17: Pipeline Segment | B17: Nuclear Reactors, Materials, and Waste | C17: 0.01 | D17: Fuel, specialist logistics, workforce, and material movement. | E17: Illustrative allocation | F17: S017; S029; S030; S031; S002; S003 | G17: Replace with asset-specific dependency mapping and approved multipliers.
A18: Pipeline Segment | B18: Transportation Systems | C18: 0.1 | D18: Direct modal service loss, substitution, delay, and network recovery. | E18: Illustrative allocation | F18: S017; S029; S030; S031; S002; S003 | G18: Replace with asset-specific dependency mapping and approved multipliers.
A19: Pipeline Segment | B19: Water and Wastewater | C19: 0.03 | D19: Chemical delivery, power/fuel, and maintenance logistics. | E19: Illustrative allocation | F19: S017; S029; S030; S031; S002; S003 | G19: Replace with asset-specific dependency mapping and approved multipliers.
A20: Pump Station | B20: Chemical | C20: 0.09 | D20: Feedstock/product movement and energy dependence. | E20: Illustrative allocation | F20: S017; S029; S031; S002; S003 | G20: Replace with asset-specific dependency mapping and approved multipliers.
... A83: Freight Rail | B83: Water and Wastewater | C83: 0.02 | D83: Chemical delivery, power/fuel, and maintenance logistics. | E83: Illustrative allocation | F83: S018; S020; S034; S002; S003 | G83: Replace with asset-specific dependency mapping and approved multipliers.
A85: Third-Order Behavioral / Macroeconomic Shock (screening flags, NOT in static shares above)
A86: Shock Channel | B86: Trigger Condition | C86: Illustrative Analog | D86: Modeling Requirement
A87: Panic-buying / hoarding | B87: Fuel or food outage perceived as prolonged | C87: Colonial Pipeline (2021) regional fuel runs | D87: CGE with demand-shock elasticity; not a fixed multiplier
A88: Price-spike transfer | B88: Constrained supply + inelastic demand | C88: Fuel/commodity price surges post-disruption | D88: Price transmission module (excluded from static shares)
A89: Confidence / avoidance | B89: High-salience terror event at public transport hub | C89: Post-attack ridership and travel avoidance | D89: Behavioral demand model with recovery decay
A90: Insurance / capital repricing | B90: Large or repeated critical-infrastructure loss | C90: Post-event risk repricing | D90: Financial-sector dynamic feedback

Sheet Cross-Sector Impacts
A1: Cross-Sector Impacts of Modeled Scenarios (2026 dollars)
A2: Standalone view of how each target scenario second-order loss distributes across CISA critical-infrastructure sectors. Dollar figures apply the static screening shares (Cross-Sector Allocation sheet) to the 2026-escalated second-order consequence at the 30-day outage duration, best (P50) estimate. These are screening allocations pending CGE/REMI replacement; they are NOT additive to the direct-cost totals and are presented separately so they can be read on their own.
A4: CISA Sector | B4: Pipeline Segment (2026$) | C4: Pump Station (2026$) | D4: Compressor Station (2026$) | E4: Airport Terminal (2026$) | F4: Freight Rail (2026$) | G4: Sector Total (2026$)
A5: Chemical | B5: ='Cross-Sector Allocation'!C4*'Consequence Targets'!U10 -> 108675000 | C5: ='Cross-Sector Allocation'!C20*'Consequence Targets'!U19 -> 58684500 | D5: ='Cross-Sector Allocation'!C36*'Consequence Targets'!U28 -> 69552000 | E5: ='Cross-Sector Allocation'!C52*'Consequence Targets'!U37 -> 34776000 | F5: ='Cross-Sector Allocation'!C68*'Consequence Targets'!U46 -> 65205000 | G5: =SUM(B5:F5) -> 336892500
A6: Commercial Facilities | B6: ='Cross-Sector Allocation'!C5*'Consequence Targets'!U10 -> 54337500 | C6: ='Cross-Sector Allocation'!C21*'Consequence Targets'!U19 -> 32602500 | D6: ='Cross-Sector Allocation'!C37*'Consequence Targets'!U28 -> 34776000 | E6: ='Cross-Sector Allocation'!C53*'Consequence Targets'!U37 -> 260820000 | F6: ='Cross-Sector Allocation'!C69*'Consequence Targets'!U46 -> 32602500 | G6: =SUM(B6:F6) -> 415138500
A7: Communications | B7: ='Cross-Sector Allocation'!C6*'Consequence Targets'!U10 -> 21735000 | C7: ='Cross-Sector Allocation'!C22*'Consequence Targets'!U19 -> 13041000 | D7: ='Cross-Sector Allocation'!C38*'Consequence Targets'!U28 -> 17388000 | E7: ='Cross-Sector Allocation'!C54*'Consequence Targets'!U37 -> 69552000 | F7: ='Cross-Sector Allocation'!C70*'Consequence Targets'!U46 -> 13041000 | G7: =SUM(B7:F7) -> 134757000
A8: Critical Manufacturing | B8: ='Cross-Sector Allocation'!C7*'Consequence Targets'!U10 -> 108675000 | C8: ='Cross-Sector Allocation'!C23*'Consequence Targets'!U19 -> 65205000 | D8: ='Cross-Sector Allocation'!C39*'Consequence Targets'!U28 -> 78246000 | E8: ='Cross-Sector Allocation'!C55*'Consequence Targets'!U37 -> 86940000 | F8: ='Cross-Sector Allocation'!C71*'Consequence Targets'!U46 -> 97807500 | G8: =SUM(B8:F8) -> 436873500
A9: Dams | B9: ='Cross-Sector Allocation'!C8*'Consequence Targets'!U10 -> 10867500 | C9: ='Cross-Sector Allocation'!C24*'Consequence Targets'!U19 -> 6520500 | D9: ='Cross-Sector Allocation'!C40*'Consequence Targets'!U28 -> 8694000 | E9: ='Cross-Sector Allocation'!C56*'Consequence Targets'!U37 -> 17388000 | F9: ='Cross-Sector Allocation'!C72*'Consequence Targets'!U46 -> 6520500 | G9: =SUM(B9:F9) -> 49990500
A10: Defense Industrial Base | B10: ='Cross-Sector Allocation'!C9*'Consequence Targets'!U10 -> 76072500 | C10: ='Cross-Sector Allocation'!C25*'Consequence Targets'!U19 -> 39123000 | D10: ='Cross-Sector Allocation'!C41*'Consequence Targets'!U28 -> 60858000 | E10: ='Cross-Sector Allocation'!C57*'Consequence Targets'!U37 -> 86940000 | F10: ='Cross-Sector Allocation'!C73*'Consequence Targets'!U46 -> 52164000 | G10: =SUM(B10:F10) -> 315157500
A11: Emergency Services | B11: ='Cross-Sector Allocation'!C10*'Consequence Targets'!U10 -> 21735000 | C11: ='Cross-Sector Allocation'!C26*'Consequence Targets'!U19 -> 13041000 | D11: ='Cross-Sector Allocation'!C42*'Consequence Targets'!U28 -> 17388000 | E11: ='Cross-Sector Allocation'!C58*'Consequence Targets'!U37 -> 52164000 | F11: ='Cross-Sector Allocation'!C74*'Consequence Targets'!U46 -> 13041000 | G11: =SUM(B11:F11) -> 117369000
A12: Energy | B12: ='Cross-Sector Allocation'!C11*'Consequence Targets'!U10 -> 380362500 | C12: ='Cross-Sector Allocation'!C27*'Consequence Targets'!U19 -> 234738000 | D12: ='Cross-Sector Allocation'!C43*'Consequence Targets'!U28 -> 330372000 | E12: ='Cross-Sector Allocation'!C59*'Consequence Targets'!U37 -> 52164000 | F12: ='Cross-Sector Allocation'!C75*'Consequence Targets'!U46 -> 65205000 | G12: =SUM(B12:F12) -> 1062841500
A13: Financial Services | B13: ='Cross-Sector Allocation'!C12*'Consequence Targets'!U10 -> 21735000 | C13: ='Cross-Sector Allocation'!C28*'Consequence Targets'!U19 -> 13041000 | D13: ='Cross-Sector Allocation'!C44*'Consequence Targets'!U28 -> 17388000 | E13: ='Cross-Sector Allocation'!C60*'Consequence Targets'!U37 -> 86940000 | F13: ='Cross-Sector Allocation'!C76*'Consequence Targets'!U46 -> 13041000 | G13: =SUM(B13:F13) -> 152145000
A14: Food and Agriculture | B14: ='Cross-Sector Allocation'!C13*'Consequence Targets'!U10 -> 54337500 | C14: ='Cross-Sector Allocation'!C29*'Consequence Targets'!U19 -> 32602500 | D14: ='Cross-Sector Allocation'!C45*'Consequence Targets'!U28 -> 34776000 | E14: ='Cross-Sector Allocation'!C61*'Consequence Targets'!U37 -> 69552000 | F14: ='Cross-Sector Allocation'!C77*'Consequence Targets'!U46 -> 65205000 | G14: =SUM(B14:F14) -> 256473000
A15: Government Services and Facilities | B15: ='Cross-Sector Allocation'!C14*'Consequence Targets'!U10 -> 32602500 | C15: ='Cross-Sector Allocation'!C30*'Consequence Targets'!U19 -> 19561500 | D15: ='Cross-Sector Allocation'!C46*'Consequence Targets'!U28 -> 26082000 | E15: ='Cross-Sector Allocation'!C62*'Consequence Targets'!U37 -> 86940000 | F15: ='Cross-Sector Allocation'!C78*'Consequence Targets'!U46 -> 19561500 | G15: =SUM(B15:F15) -> 184747500
A16: Healthcare and Public Health | B16: ='Cross-Sector Allocation'!C15*'Consequence Targets'!U10 -> 21735000 | C16: ='Cross-Sector Allocation'!C31*'Consequence Targets'!U19 -> 13041000 | D16: ='Cross-Sector Allocation'!C47*'Consequence Targets'!U28 -> 17388000 | E16: ='Cross-Sector Allocation'!C63*'Consequence Targets'!U37 -> 34776000 | F16: ='Cross-Sector Allocation'!C79*'Consequence Targets'!U46 -> 13041000 | G16: =SUM(B16:F16) -> 99981000
A17: Information Technology | B17: ='Cross-Sector Allocation'!C16*'Consequence Targets'!U10 -> 21735000 | C17: ='Cross-Sector Allocation'!C32*'Consequence Targets'!U19 -> 13041000 | D17: ='Cross-Sector Allocation'!C48*'Consequence Targets'!U28 -> 17388000 | E17: ='Cross-Sector Allocation'!C64*'Consequence Targets'!U37 -> 69552000 | F17: ='Cross-Sector Allocation'!C80*'Consequence Targets'!U46 -> 13041000 | G17: =SUM(B17:F17) -> 134757000
A18: Nuclear Reactors, Materials, and Waste | B18: ='Cross-Sector Allocation'!C17*'Consequence Targets'!U10 -> 10867500 | C18: ='Cross-Sector Allocation'!C33*'Consequence Targets'!U19 -> 6520500 | D18: ='Cross-Sector Allocation'!C49*'Consequence Targets'!U28 -> 17388000 | E18: ='Cross-Sector Allocation'!C65*'Consequence Targets'!U37 -> 17388000 | F18: ='Cross-Sector Allocation'!C81*'Consequence Targets'!U46 -> 6520500 | G18: =SUM(B18:F18) -> 58684500
A19: Transportation Systems | B19: ='Cross-Sector Allocation'!C18*'Consequence Targets'!U10 -> 108675000 | C19: ='Cross-Sector Allocation'!C34*'Consequence Targets'!U19 -> 78246000 | D19: ='Cross-Sector Allocation'!C50*'Consequence Targets'!U28 -> 86940000 | E19: ='Cross-Sector Allocation'!C66*'Consequence Targets'!U37 -> 660744000 | F19: ='Cross-Sector Allocation'!C82*'Consequence Targets'!U46 -> 163012500 | G19: =SUM(B19:F19) -> 1097617500
A20: Water and Wastewater | B20: ='Cross-Sector Allocation'!C19*'Consequence Targets'!U10 -> 32602500 | C20: ='Cross-Sector Allocation'!C35*'Consequence Targets'!U19 -> 13041000 | D20: ='Cross-Sector Allocation'!C51*'Consequence Targets'!U28 -> 34776000 | E20: ='Cross-Sector Allocation'!C67*'Consequence Targets'!U37 -> 52164000 | F20: ='Cross-Sector Allocation'!C83*'Consequence Targets'!U46 -> 13041000 | G20: =SUM(B20:F20) -> 145624500
A21: Target Second-Order Total (30d, P50) | B21: =SUM(B5:B20) -> 1086750000 | C21: =SUM(C5:C20) -> 652050000 | D21: =SUM(D5:D20) -> 869400000 | E21: =SUM(E5:E20) -> 1738800000 | F21: =SUM(F5:F20) -> 652050000 | G21: =SUM(G5:G20) -> 4999050000

Sheet Sources
A1: Approved Public Source Catalog Used in the Pilot
A3: Source ID | B3: Agency / Organization | C3: Title | D3: URL | E3: Analytic Role | F3: Applied To
A4: S001 | B4: U.S. Department of Transportation | C4: Revised Departmental Guidance on Valuation of a Statistical Life in Economic Analysis | D4: https://www.transportation.gov/office-policy/transportation-policy/revised-departmental-guidance-on-valuation-of-a-statistical-life-in-economic-analysis | E4: VSL and injury valuation basis | F4: All scenarios and targets
A5: S002 | B5: Bureau of Economic Analysis | C5: Input-Output Accounts data and methodology | D5: https://www.bea.gov/data/industries/input-output-accounts-data | E5: Cross-industry dependency and indirect-consequence framework | F5: Consequence model
A6: S003 | B6: Cybersecurity and Infrastructure Security Agency | C6: Critical Infrastructure Sectors | D6: https://www.cisa.gov/topics/critical-infrastructure-security-and-resilience/critical-infrastructure-sectors | E6: Sector taxonomy and dependency framing | F6: Cross-sector model
A7: S004 | B7: National Transportation Safety Board | C7: Aviation accident reports and sabotage/explosion investigations | D7: https://www.ntsb.gov/investigations/AccidentReports/Pages/Reports.aspx | E7: Aircraft fire/explosion and consequence analogs | F7: AV-08; AV-09
A8: S005 | B8: National Commission on Terrorist Attacks Upon the United States | C8: The 9/11 Commission Report | D8: https://9-11commission.gov/report/911Report.pdf | E8: Hijacking and bladed-weapon attack evidence | F8: AV-03; AV-05; AV-06; AV-07
A9: S006 | B9: U.S. Department of Justice | C9: Pan Am Flight 73 sentencing memorandum / Safarini case | D9: https://www.justice.gov/sites/default/files/usao-dc/legacy/2013/08/07/pan_am_73_sentg_memo.pdf | E9: Ground aircraft assault and hijacking analog | F9: AV-02; AV-05; AV-07
A10: S007 | B10: Federal Bureau of Investigation | C10: Active Shooter Incidents in the United States, 2000-2018 | D10: https://www.fbi.gov/file-repository/active-shooter-incidents-2000-2018.pdf | E10: Airport passenger-assembly and facility assault casualty analogs | F10: AV-04; SU-02
A11: S008 | B11: Federal Bureau of Investigation | C11: Frank James sentenced for Brooklyn subway mass shooting | D11: https://www.fbi.gov/contact-us/field-offices/newyork/news/frank-james-sentenced-to-life-in-prison-for-subway-mass-shooting | E11: Surface passenger system assault analog | F11: SU-01
A12: S009 | B12: U.S. Department of Justice | C12: Sayfullo Saipov sentencing for 2017 New York truck attack | D12: https://www.justice.gov/archives/opa/pr/judge-imposes-eight-consecutive-life-sentences-plus-260-years-prison-isis-inspired-2017 | E12: Vehicle-ramming casualty analog | F12: SU-03
A13: S010 | B13: Federal Bureau of Investigation | C13: Bourbon Street Attack Investigation Updates | D13: https://www.fbi.gov/news/press-releases/bourbon-street-attack-investigation-updates | E13: Vehicle-ramming casualty analog | F13: SU-03
A14: S011 | B14: U.S. Government Accountability Office | C14: Federal Efforts to Address Unauthorized Drone Flights Near Airports | D14: https://www.gao.gov/products/gao-24-107195 | E14: UAS aviation hazard, incident, and mitigation evidence | F14: AV-01; SU-04
... A37: S034 | B37: Federal Highway Administration / BTS | C37: Freight Analysis Framework overview | D37: https://ops.fhwa.dot.gov/freight/freight_analysis/faf/ | E37: Freight network and commodity-flow methodology | F37: Freight Rail

Sheet Executive Summary
A1: TSSRA Open-Source AI Pilot - Executive Summary
A3: Metric | B3: Value | C3: Interpretation | D3: Status
A4: Outcome families modeled | B4: 18 | C4: 16 base families + 2 hijacking splits (passenger and cargo, aircraft-as-weapon) | D4: Complete
A5: Consequence target archetypes | B5: 5 | C5: Pipeline segment, pump station, compressor station, airport terminal, freight rail | D5: Complete
A6: Outage durations | B6: 9 | C6: 4 hours through 90 days | D6: Complete
A7: CISA sectors represented | B7: 16 | C7: Illustrative second-order allocation | D7: Complete
A8: DOT VSL | B8: 14200000 | C8: 2025-dollar VSL used for casualty monetization | D8: Current public guidance
A9: Low-confidence outcome families | B9: 9 | C9: Sparse or mechanistic evidence; requires expert review | D9: Review required
A10: Injury model | B10: Weapon-class bi-modal | C10: Replaces single averaged MAIS fraction (NISS/TRISS for blast) | D10: Overhauled
A11: Restoration model | B11: Eng + regulatory | C11: Adds CAO/site-control/pressure-restriction delay; extended to 90 days | D11: Overhauled
A12: Outcome Scenario | B12: Best Direct Cost
A13: AV-01 All UAS against aviation | B13: ='Outcome Scenarios'!R4 -> 58830220
A14: AV-02 Aircraft assault on ground | B14: ='Outcome Scenarios'!R5 -> 170627150
A15: AV-03 Aircraft passenger assault with bladed weapons | B15: ='Outcome Scenarios'!R6 -> 40542188
A16: AV-04 Airport passenger assembly assault | B16: ='Outcome Scenarios'!R7 -> 212563870
A17: AV-05a Passenger hijacking - traditional | B17: ='Outcome Scenarios'!R8 -> 70896290
A18: AV-06a Cargo hijacking - traditional | B18: ='Outcome Scenarios'!R9 -> 45887344
A19: AV-07 Public charter hijacking | B19: ='Outcome Scenarios'!R10 -> 209377150
A20: AV-08 All IID on commercial passenger aircraft | B20: ='Outcome Scenarios'!R11 -> 230888920
A21: AV-09 All IID on cargo aircraft | B21: ='Outcome Scenarios'!R12 -> 82907784
A22: AV-10 All Chem/Bio on commercial passenger aircraft | B22: ='Outcome Scenarios'!R13 -> 267952200
A23: AV-11 All Chem/Bio at airport | B23: ='Outcome Scenarios'!R14 -> 803856600
A24: SU-01 Assault on surface passenger vessels/stations | B24: ='Outcome Scenarios'!R15 -> 219829300
... A30: AV-06b Cargo hijacking - aircraft as weapon | B30: ='Outcome Scenarios'!R21 -> 8507674000
A32: Note | B32: Aircraft-as-weapon scenarios (AV-05b, AV-06b) carry catastrophic P50 values that were previously masked when averaged into the lumped hijacking families. They are conditional consequences and are not probability-weighted.
A33: Pipeline Segment | B33: =SUMIFS('Consequence Targets'!$V$4:$V$48,'Consequence Targets'!$A$4:$A$48,$A33,'Consequence Targets'!$B$4:$B$48,"3 days") -> 126425000
A34: Dollar basis | B34: 2026$ (property + 2nd-order via CPI-U +3.5%); VSL at official 2025 basis
A35: Cross-sector view | B35: See Cross-Sector Impacts sheet (separable from direct results)
A36: Airport Terminal | B36: =SUMIFS('Consequence Targets'!$V$4:$V$48,'Consequence Targets'!$A$4:$A$48,$A36,'Consequence Targets'!$B$4:$B$48,"3 days") -> 462540000
A37: Freight Rail | B37: =SUMIFS('Consequence Targets'!$V$4:$V$48,'Consequence Targets'!$A$4:$A$48,$A37,'Consequence Targets'!$B$4:$B$48,"3 days") -> 96470000
A40: Important: These are conditional planning estimates, not forecasts of attack likelihood. Totals should not be summed across mutually exclusive scenarios. Replace generic assumptions with scenario- and asset-specific DHS inputs before formal use.
